Workbook
Name TRAINING_UNIT_PRICE: Variables!#REF!
Name UNIT_5: Variables!$J$12
Name Z_E6596C0B_1A16_4C13_A664_892027304A31_.wvu.PrintArea: Financements!$B$1:$T$67
Name Z_EEA24EE8_2525_C446_8B59_1C9C99656C98_.wvu.PrintArea: 'Plan de financement'!$A$1:$G$57
Name Z_EEA24EE8_2525_C446_8B59_1C9C99656C98_.wvu.PrintArea: 'BFR '!$B$26:$O$44
Name UNIT_PRICE_CLIENT_F: Variables!$I$15
Name Statut_JEI: Variables!$C$24
Name UNIT_PRICE_CLIENT_A: Variables!$I$10
Name UNIT_PRICE_DECOUVERTE: Variables!$I$10
Name UNIT_20: Variables!$J$14
Name Z_15B2DCEA_87E0_4C3D_A53F_208BD26E925F_.wvu.PrintArea: Investissements!$B$1:$Q$77
Name Z_8C30E345_2AE0_4C49_8CA3_C007F1DFF339_.wvu.PrintArea: 'Cash Flow'!$B$1:$AF$40
Name Z_E6596C0B_1A16_4C13_A664_892027304A31_.wvu.PrintArea: 'Cash Flow'!$B$1:$AF$40
Name Z_15B2DCEA_87E0_4C3D_A53F_208BD26E925F_.wvu.PrintArea: 'Cash Flow'!$B$1:$AF$40
Name SIZE_LARGE: Variables!$C$35
Name Z_15B2DCEA_87E0_4C3D_A53F_208BD26E925F_.wvu.PrintArea: CR!$B$1:$O$58
Name Taux_de_commission: Variables!$C$11
Name Salaires_Immob_DG: Variables!$C$14
Name Z_8C30E345_2AE0_4C49_8CA3_C007F1DFF339_.wvu.PrintArea: CR!$B$1:$O$58
Name Z_61AF70DF_5A11_444F_A95C_90F81E928498_.wvu.PrintArea: Financements!$B$1:$T$67
Name CONFLUENCE_PRICE: Variables!$F$27
Name GOOGLE_PRICE: Variables!$F$25
Name UNIT_1: Variables!$J$11
Name UNIT_60: Variables!$J$16
Name Impot_sur_sociétés: Variables!$C$19
Name Z_15B2DCEA_87E0_4C3D_A53F_208BD26E925F_.wvu.PrintArea: Bilan!$A$1:$G$57
Name Z_61AF70DF_5A11_444F_A95C_90F81E928498_.wvu.PrintArea: 'BFR '!$B$26:$O$44
Name Salaires_Immob_Prod_Dev: Variables!$C$15
Name Délai_paiement_invest: Variables!$F$18
Name Taux_de_CICE: Variables!$C$10
Name Z_E6596C0B_1A16_4C13_A664_892027304A31_.wvu.PrintArea: Investissements!$B$1:$Q$77
Name SIZE_SMALL: Variables!$C$33
Name Z_8C30E345_2AE0_4C49_8CA3_C007F1DFF339_.wvu.PrintArea: Bilan!$A$1:$G$57
Name Taux_de_TVA_investissement: Variables!$C$20
Name Délai_paiement_ST: Variables!$F$16
Name Z_B9E23C8B_E79A_4E77_BB37_453028BABEDF_.wvu.PrintArea: Financements!$B$1:$H$67
Name Z_E6596C0B_1A16_4C13_A664_892027304A31_.wvu.PrintArea: 'Plan de financement'!$A$1:$G$57
Name UNIT_PRICE_ILLIMITE: Variables!$I$17
Name Z_9F2F25DB_E3B2_4813_9899_141DF1E6770F_.wvu.PrintArea: CR!$B$1:$O$58
Name Z_9F2F25DB_E3B2_4813_9899_141DF1E6770F_.wvu.PrintArea: Investissements!$B$1:$G$78
Name Z_8C30E345_2AE0_4C49_8CA3_C007F1DFF339_.wvu.PrintArea: 'BFR '!$B$26:$O$44
Name Z_8C30E345_2AE0_4C49_8CA3_C007F1DFF339_.wvu.PrintArea: Financements!$B$1:$T$67
Name Inflation_salaires: Variables!$C$12
Name UNIT_PRICE_CLIENT_D: Variables!$I$13
Name inflation_vente: Variables!$I$45
Name EMPLOYEE_KIT_COST: Variables!$C$34
Name UNIT_PRICE_60_UNITE: Variables!$I$16
Name WEBFLOW_PRICING: Variables!$F$31
Name Durée_de_stockage_A: Variables!$F$21
Name Z_9F2F25DB_E3B2_4813_9899_141DF1E6770F_.wvu.PrintArea: Financements!$B$1:$G$67
Name Z_EEA24EE8_2525_C446_8B59_1C9C99656C98_.wvu.PrintArea: Bilan!$A$1:$G$57
Name TJH: #REF!
Name date_début: Variables!$F$5
Name Délai_paiement_Achat: Variables!$F$15
Name Z_8C30E345_2AE0_4C49_8CA3_C007F1DFF339_.wvu.PrintArea: 'Plan de financement'!$A$1:$G$57
Name UNIT_PRICE_CLIENT_B: Variables!$I$11
Name Z_61AF70DF_5A11_444F_A95C_90F81E928498_.wvu.PrintArea: Bilan!$A$1:$G$57
Name wacc: Valorisation!$C$27
Name Délai_encaissement_B: Variables!$F$10
Name Z_61AF70DF_5A11_444F_A95C_90F81E928498_.wvu.PrintArea: 'Cash Flow'!$B$1:$AF$40

Sheet Cover Pres
A1: $^`
H2: BUSINESS PLAN
H3: PLAN D'AFFAIRES
B7: A) ORGANISATION GENERALE
C9: Ce modèle est destiné à permettre de calculer pour un projet les états financiers suivants :
C10: - Compte de résultat
C11: - Plan de trésorerie (cash-flow)
C12: - Bilan
C13: - Valorisation
C15: Les calculs sont réalisés dans plusieurs modules auxquels correspondent les onglets du présent fichier Excel :
C17: - Onglet Variables : Inputs et hypothèses du BP (masse salariale, macroéconomie, délais paiement…)
C18: - Onglet CA : Chiffre d'affaire et Prix de Revient (ventilation et calcul de la marge brute sur coûts variables directs)
C19: - Onglet Personnel : Dimensionnement dans le temps des Ressources Humaines, par fonction clé
C20: - Onglet Charges externes : notamment dépenses de communication et commerciales (hors Personnel)
C21: - Onglet Investissements : décomposition des investissements et de leurs amortissements
C22: - Onglet Financements : structuration des financements (part capital et part endettement)
... C31: 5 de synthèse (Bilan, CR, BFR, Cash Flow, Résumé 4 ans), un de valorisation
B33: B) OPTIONS GRAPHIQUES
C35: Dans tout le modèle le type de trait et la couleur des cellules permettent de connaitre la nature du chiffre indiqué
C37: Les cellules qui incluent des résultats de calcul ou qui viennent
C38: d'autres modules sont dans des cellules de type | I38: xxxx | J38: yyyy | L38: / ! \ ne pas entrer de données dans ces cellules
L39: au risque de corrompre le modèle (chiffres calculés par des formules)
C41: Les totaux de premier niveau sont dans des cellules de type | I41: xxxx | J41: yyyy | L41: " | M41: " | N41: "
C43: Les totaux de deuxième niveau sont dans des cellules de type | I43: xxxx | J43: yyyy | L43: " | M43: " | N43: "
C46: Les cellules qui doivent recueillir des entrées de données sont de type | I46: xxxx | J46: xxxx | L46: données à saisir
C48: Les cellules qui sont logiquement vides
C49: sont de type | L49: Pas de données
C51: Les cellules "contrôle" sont destinées a vérifier la cohérence de certains tableaux | I51: 0 | J51: 0 | L51: si le chiffre est différent de 0
C52: sont de type | I52: check | J52: 0 | L52: il y a un probléme de logique dans le module !
C54: Les cellules où est inclus un commentaire explicatif sont de type
B57: C) PERIODES CONSIDEREES
C59: Le format du modèle couvre 4 ans.
C60: Pour les chiffres découlant des années antérieures, seuls les soldes utiles aux calculs sont repris,
C61: en partant de la liasse fiscale, les onglets Bilan et CR alimentent le BFR et le Cash-Flow
C62: Pour les 2 premières années les calculs sont fait mensuellement ou par trimestre, avec des totaux annuels.

Sheet Variables
B2: INPUTS BUSINESS PLAN
E5: Date début BP | F5: 45658
B7: HYPOTHESES GENERALES | E7: HYPOTHESE D'EXPLOITATION | H7: HYPOTHESE DE MODELE ECONOMIQUE
B8: MASSE SALARIALE | E8: DÉLAIS D'ENCAISSEMENT CLIENTS | F8: en nb de jours | H8: Persona | I8: Prix HT | J8: N° unités | K8: TVA | L8: Prix à l'unité | M8: Description
B9: Taux charges sociales (patronale) | C9: 0.45 | E9: Délai d'encaissement - Court | F9: 0 | H9: Unité de gestion | I9: 1h30
B10: Taux de CICE | C10: 0 | E10: Délai d'encaissement - Moyen | F10: 1 | H10: client A | I10: =(L10/(1+K10))*J10 -> 5 | J10: 1 | K10: 0.1 | L10: 5.5 | M10: drink
B11: Taux de commission | C11: 0.25 | E11: Délai d'encaissement - Long | F11: 1 | H11: client B | I11: =(L11/(1+K11))*J11 -> 9.1818182 | J11: 1 | K11: 0.1 | L11: 10.1 | M11: drink+patisserie ( gouter/ collation)
B12: Inflation salaires | C12: 0.05 | E12: xx | F12: 0 | H12: client C | I12: =(L12/(1+K12))*J12 -> 12.727273 | J12: 1 | K12: 0.1 | L12: 14 | M12: breakfast
B13: Part de salaires immob. R&D | H13: client D | I13: =(L13/(1+K13))*J13 -> 16.363636 | J13: 1 | K13: 0.1 | L13: 18 | M13: lunch
B14: Directeur général | C14: 0 | E14: DÉLAIS DE PAIEMENT FOURNISSEURS | F14: en nb de jours | H14: client E | I14: =(L14/(1+K14))*J14 -> 20.590909 | J14: 1 | K14: 0.1 | L14: 22.65 | M14: brunch (lunch+drink+patisserie)
B15: Effectif - Production & Dev | C15: 0 | E15: Délai de paiement - Court | F15: 30 | I15: =(L15/(1+K15))*J15 -> 0
E16: Délai de paiement - Moyen | F16: 60
E17: Délai de paiement - Long | F17: 90 | H17: Business Days | I17: jours
B18: FISCALITE | E18: xx | F18: 0 | H18: Nombre de jours par an | I18: 365
B19: Impôt sur les Sociétés | C19: 0.25 | H19: Nombre de jours flottants (fermeture) | I19: 10
B20: Taux de TVA investissement | C20: 0.2 | E20: DURÉE DE STOCKAGE | F20: en nb de jours | H20: Nombre de jours ferié | I20: 11
B21: Taux de TVA moyen (alcohol 20%, drinks 10%, food10%) | C21: 0.12 | E21: xx | F21: 0 | H21: Nombre de jours non ouvrés | I21: 52
E22: xx | F22: 0 | H22: nombre de jours de fermeture annuelle | I22: 15
B23: INNOVATION / SUBVENTION
B24: Statut JEI | C24: 0 | E24: PRIX ABONNEMENTS | F24: Prix | H24: Nombre de jours business | I24: =I18-I19-I21-I22 -> 288
B25: Taux Charges Sociales JEI | C25: 0 | F25: 0
B26: Statut CIR | C26: 0 | F26: 0 | H26: Taux de remplissage | I26: %
B27: Taux de CIR | C27: =IF(C26=1,30%,0%) -> 0 | F27: 0 | H27: Remplissage minimal à atteindre | I27: 1
F28: 0 | H28: Remplissage Optimal | I28: 1.5
B29: KIT Collaborateur | C29: Prix | F29: 0
B30: xxx | C30: 0 | F30: 0
B31: xxx | C31: 0 | F31: 0 | H31: Nombre de couverts | I31: Places
B32: xxx | C32: 0 | F32: 0 | H32: Interieur | I32: 18
B33: xxx | C33: 0 | H33: Terssase | I33: 0
B34: Total Kit Collaborateur | C34: =SUM(C30:C33) -> 0 | H34: T.estivale | I34: 24
H36: Services | I36: Min | J36: AVG | K36: Max
H37: Brunch | I37: 17 | J37: 23 | L37: 29
H38: Coallation | I38: 5 | J38: 8 | L38: 14
H39: Livraison | I39: 17 | J39: 23 | L39: 29
H40: Emporter (boisson) | I40: 5 | J40: 8 | L40: 14
H41: Epicerie | I41: 5 | J41: 10 | L41: 15
H42: Traiteur | I42: 200 | J42: 300 | L42: 500
H44: Variables | I44: %
H45: Inflation vente | I45: 0.03

Sheet Insights surplace
A2: OFFRE RESTAURATION SUR PLACE ET A EMPORTER | M2: capacité: | N2: 18 assises
C3: Heure-Jour | D3: 2025 | K3: 2026 | R3: 2027
C4: % remplissage horaire | D4: 8h30-10h | E4: 10h-11h30 | F4: 11h30-13 | G4: 13h-14h30 | H4: 14h30-16h | I4: 16h-17h30 | K4: 8h30-10h | L4: 10h-11h30 | M4: 11h30-13 | N4: 13h-14h30 | O4: 14h30-16h | P4: 16h-17h30 | R4: 8h30-10h | S4: 10h-11h30 | T4: 11h30-13 | U4: 13h-14h30 | V4: 14h30-16h | W4: 16h-17h30
C5: client A | D5: 0.3 | E5: 0.1 | G5: 0.05 | H5: 0.3 | I5: 0.4 | K5: 0.3 | L5: 0.1 | N5: 0.05 | O5: 0.3 | P5: 0.4 | R5: 0.3 | S5: 0.1 | U5: 0.05 | V5: 0.3 | W5: 0.4
C6: client B | D6: 0.4 | E6: 0.35 | G6: 0.05 | H6: 0.5 | I6: 0.55 | K6: 0.4 | L6: 0.35 | N6: 0.05 | O6: 0.5 | P6: 0.55 | R6: 0.4 | S6: 0.35 | U6: 0.05 | V6: 0.5 | W6: 0.55
C7: client C | D7: 0.15 | E7: 0.3 | F7: 0.05 | G7: 0 | H7: 0 | I7: 0.05 | K7: 0.15 | L7: 0.3 | M7: 0.05 | N7: 0 | O7: 0 | P7: 0.05 | R7: 0.15 | S7: 0.3 | T7: 0.05 | U7: 0 | V7: 0 | W7: 0.05
C8: client D | D8: 0.15 | E8: 0.15 | F8: 0.55 | G8: 0.6 | H8: 0.1 | I8: 0 | K8: 0.15 | L8: 0.15 | M8: 0.55 | N8: 0.6 | O8: 0.1 | P8: 0 | R8: 0.15 | S8: 0.15 | T8: 0.55 | U8: 0.6 | V8: 0.1 | W8: 0
C9: client E | E9: 0.2 | F9: 0.4 | G9: 0.3 | H9: 0.1 | L9: 0.2 | M9: 0.4 | N9: 0.3 | O9: 0.1 | S9: 0.2 | T9: 0.4 | U9: 0.3 | V9: 0.1
D11: =SUM(D5:D10) -> 1 | E11: =SUM(E5:E10) -> 1.1 | F11: =SUM(F5:F10) -> 1 | G11: =SUM(G5:G10) -> 1 | H11: =SUM(H5:H10) -> 1 | I11: =SUM(I5:I10) -> 1 | K11: =SUM(K5:K10) -> 1 | L11: =SUM(L5:L10) -> 1.1 | M11: =SUM(M5:M10) -> 1 | N11: =SUM(N5:N10) -> 1 | O11: =SUM(O5:O10) -> 1 | P11: =SUM(P5:P10) -> 1 | R11: =SUM(R5:R10) -> 1 | S11: =SUM(S5:S10) -> 1.1 | T11: =SUM(T5:T10) -> 1 | U11: =SUM(U5:U10) -> 1 | V11: =SUM(V5:V10) -> 1 | W11: =SUM(W5:W10) -> 1
C14: Heure-Jour | D14: 2025 | K14: 2026 | R14: 2027
D15: 8h30-10h | E15: 10h-11h30 | F15: 11h30-13 | G15: 13h-14h30 | H15: 14h30-16h | I15: 16h-17h30 | K15: 8h30-10h | L15: 10h-11h30 | M15: 11h30-13 | N15: 13h-14h30 | O15: 14h30-16h | P15: 16h-17h30 | R15: 8h30-10h | S15: 10h-11h30 | T15: 11h30-13 | U15: 13h-14h30 | V15: 14h30-16h | W15: 16h-17h30
C16: Nombre de clients | D16: 10 | E16: 15 | F16: 18 | G16: 20 | H16: 15 | I16: 15 | K16: 11 | L16: 16 | M16: 18 | N16: 18 | O16: 17 | P16: 14 | R16: 11 | S16: 16 | T16: 18 | U16: 18 | V16: 17 | W16: 14
C17: client A | D17: =ROUND( D$16*D5,0) -> 3 | E17: =ROUND( E$16*E5,0) -> 2 | F17: =ROUND( F$16*F5,0) -> 0 | G17: =ROUND( G$16*G5,0) -> 1 | H17: =ROUND( H$16*H5,0) -> 5 | I17: =ROUND( I$16*I5,0) -> 6 | K17: =ROUND( K$16*K5,0) -> 3 | L17: =ROUND( L$16*L5,0) -> 2 | M17: =ROUND( M$16*M5,0) -> 0 | N17: =ROUND( N$16*N5,0) -> 1 | O17: =ROUND( O$16*O5,0) -> 5 | P17: =ROUND( P$16*P5,0) -> 6 | R17: =ROUND( R$16*R5,0) -> 3 | S17: =ROUND( S$16*S5,0) -> 2 | T17: =ROUND( T$16*T5,0) -> 0 | U17: =ROUND( U$16*U5,0) -> 1 | V17: =ROUND( V$16*V5,0) -> 5 | W17: =ROUND( W$16*W5,0) -> 6
C18: client B | D18: =ROUND( D$16*D6,0) -> 4 | E18: =ROUND( E$16*E6,0) -> 5 | F18: =ROUND( F$16*F6,0) -> 0 | G18: =ROUND( G$16*G6,0) -> 1 | H18: =ROUND( H$16*H6,0) -> 8 | I18: =ROUND( I$16*I6,0) -> 8 | K18: =ROUND( K$16*K6,0) -> 4 | L18: =ROUND( L$16*L6,0) -> 6 | M18: =ROUND( M$16*M6,0) -> 0 | N18: =ROUND( N$16*N6,0) -> 1 | O18: =ROUND( O$16*O6,0) -> 9 | P18: 9 | R18: =ROUND( R$16*R6,0) -> 4 | S18: =ROUND( S$16*S6,0) -> 6 | T18: =ROUND( T$16*T6,0) -> 0 | U18: =ROUND( U$16*U6,0) -> 1 | V18: =ROUND( V$16*V6,0) -> 9 | W18: =ROUND( W$16*W6,0) -> 8
C19: client C | D19: =ROUND( D$16*D7,0) -> 2 | E19: =ROUND( E$16*E7,0) -> 5 | F19: =ROUND( F$16*F7,0) -> 1 | G19: =ROUND( G$16*G7,0) -> 0 | H19: =ROUND( H$16*H7,0) -> 0 | I19: =ROUND( I$16*I7,0) -> 1 | K19: =ROUND( K$16*K7,0) -> 2 | L19: =ROUND( L$16*L7,0) -> 5 | M19: =ROUND( M$16*M7,0) -> 1 | N19: =ROUND( N$16*N7,0) -> 0 | O19: =ROUND( O$16*O7,0) -> 0 | P19: 3 | R19: =ROUND( R$16*R7,0) -> 2 | S19: =ROUND( S$16*S7,0) -> 5 | T19: =ROUND( T$16*T7,0) -> 1 | U19: =ROUND( U$16*U7,0) -> 0 | V19: =ROUND( V$16*V7,0) -> 0 | W19: =ROUND( W$16*W7,0) -> 1
C20: client D | D20: =ROUND( D$16*D8,0) -> 2 | E20: =ROUND( E$16*E8,0) -> 2 | F20: =ROUND( F$16*F8,0) -> 10 | G20: =ROUND( G$16*G8,0) -> 12 | H20: =ROUND( H$16*H8,0) -> 2 | I20: =ROUND( I$16*I8,0) -> 0 | K20: =ROUND( K$16*K8,0) -> 2 | L20: =ROUND( L$16*L8,0) -> 2 | M20: =ROUND( M$16*M8,0) -> 10 | N20: =ROUND( N$16*N8,0) -> 11 | O20: =ROUND( O$16*O8,0) -> 2 | P20: =ROUND( P$16*P8,0) -> 0 | R20: =ROUND( R$16*R8,0) -> 2 | S20: =ROUND( S$16*S8,0) -> 2 | T20: =ROUND( T$16*T8,0) -> 10 | U20: =ROUND( U$16*U8,0) -> 11 | V20: =ROUND( V$16*V8,0) -> 2 | W20: =ROUND( W$16*W8,0) -> 0
C21: client E | D21: =ROUND( D$16*D9,0) -> 0 | E21: =ROUND( E$16*E9,0) -> 3 | F21: =ROUND( F$16*F9,0) -> 7 | G21: =ROUND( G$16*G9,0) -> 6 | H21: =ROUND( H$16*H9,0) -> 2 | I21: =ROUND( I$16*I9,0) -> 0 | K21: =ROUND( K$16*K9,0) -> 0 | L21: =ROUND( L$16*L9,0) -> 3 | M21: =ROUND( M$16*M9,0) -> 7 | N21: =ROUND( N$16*N9,0) -> 5 | O21: =ROUND( O$16*O9,0) -> 2 | P21: =ROUND( P$16*P9,0) -> 0 | R21: =ROUND( R$16*R9,0) -> 0 | S21: =ROUND( S$16*S9,0) -> 3 | T21: =ROUND( T$16*T9,0) -> 7 | U21: =ROUND( U$16*U9,0) -> 5 | V21: =ROUND( V$16*V9,0) -> 2 | W21: =ROUND( W$16*W9,0) -> 0
D23: =SUM(D17:D22) -> 11 | E23: =SUM(E17:E21) -> 17 | F23: =SUM(F17:F22) -> 18 | G23: =SUM(G17:G22) -> 20 | H23: =SUM(H17:H22) -> 17 | I23: =SUM(I17:I22) -> 15 | K23: =SUM(K17:K22) -> 11 | L23: =SUM(L17:L22) -> 18 | M23: =SUM(M17:M22) -> 18 | N23: =SUM(N17:N22) -> 18 | O23: =SUM(O17:O22) -> 18 | P23: =SUM(P17:P22) -> 18 | R23: =SUM(R17:R22) -> 11 | S23: =SUM(S17:S22) -> 18 | T23: =SUM(T17:T22) -> 18 | U23: =SUM(U17:U22) -> 18 | V23: =SUM(V17:V22) -> 18 | W23: =SUM(W17:W22) -> 15
D25: 2025 | AC25: 2026 | BB25: 2027
C26: jour/mois | D26: mardi | E26: mercredi | F26: jeudi | G26: vendredi | H26: samedi | I26: dimanche | J26: mardi | K26: mercredi | L26: jeudi | M26: vendredi | N26: samedi | O26: dimanche | P26: mardi | Q26: mercredi | R26: jeudi | S26: vendredi | T26: samedi | U26: dimanche | V26: mardi | W26: mercredi | X26: jeudi | Y26: vendredi | Z26: samedi | AA26: dimanche | AC26: mardi | AD26: mercredi | AE26: jeudi | AF26: vendredi | AG26: samedi | AH26: dimanche | AI26: mardi | AJ26: mercredi | AK26: jeudi | AL26: vendredi | AM26: samedi | AN26: dimanche | AO26: mardi | AP26: mercredi | AQ26: jeudi | AR26: vendredi | AS26: samedi | AT26: dimanche | AU26: mardi | AV26: mercredi | AW26: jeudi | AX26: vendredi | AY26: samedi | AZ26: dimanche | BB26: mardi | BC26: mercredi | BD26: jeudi | BE26: vendredi | BF26: samedi | BG26: dimanche | BH26: mardi | BI26: mercredi | BJ26: jeudi | BK26: vendredi | BL26: samedi | BM26: dimanche | BN26: mardi | BO26: mercredi | BP26: jeudi | BQ26: vendredi | BR26: samedi | BS26: dimanche | BT26: mardi | BU26: mercredi | BV26: jeudi | BW26: vendredi | BX26: samedi | BY26: dimanche
D27: 1 | E27: 2 | F27: 3 | G27: 4 | H27: 5 | I27: 6 | J27: 7 | K27: 8 | L27: 9 | M27: 10 | N27: 11 | O27: 12 | P27: 13 | Q27: 14 | R27: 15 | S27: 16 | T27: 17 | U27: 18 | V27: 19 | W27: 20 | X27: 21 | Y27: 22 | Z27: 23 | AA27: 24 | AC27: 1 | AD27: 2 | AE27: 3 | AF27: 4 | AG27: 5 | AH27: 6 | AI27: 7 | AJ27: 8 | AK27: 9 | AL27: 10 | AM27: 11 | AN27: 12 | AO27: 13 | AP27: 14 | AQ27: 15 | AR27: 16 | AS27: 17 | AT27: 18 | AU27: 19 | AV27: 20 | AW27: 21 | AX27: 22 | AY27: 23 | AZ27: 24 | BB27: 1 | BC27: 2 | BD27: 3 | BE27: 4 | BF27: 5 | BG27: 6 | BH27: 7 | BI27: 8 | BJ27: 9 | BK27: 10 | BL27: 11 | BM27: 12 | BN27: 13 | BO27: 14 | BP27: 15 | BQ27: 16 | BR27: 17 | BS27: 18 | BT27: 19 | BU27: 20 | BV27: 21 | BW27: 22 | BX27: 23 | BY27: 24
C28: % remplissage journalier | D28: 0.5 | E28: 0.5 | F28: 0.6 | G28: 0.7 | H28: 0.85 | I28: 0.9 | J28: 0.6 | K28: 0.7 | L28: 0.7 | M28: 0.75 | N28: 0.85 | O28: 0.95 | P28: 0.6 | Q28: 0.7 | R28: 0.7 | S28: 0.85 | T28: 0.9 | U28: 0.9 | V28: 0.6 | W28: 0.7 | X28: 0.8 | Y28: 0.9 | Z28: 1 | AA28: 1 | AC28: 0.7 | AD28: 0.7 | AE28: 0.7 | AF28: 0.9 | AG28: 1 | AH28: 1 | AI28: 0.7 | AJ28: 0.7 | AK28: 0.7 | AL28: 0.9 | AM28: 1 | AN28: 1 | AO28: 0.7 | AP28: 0.7 | AQ28: 0.7 | AR28: 0.9 | AS28: 1 | AT28: 1 | AU28: 0.7 | AV28: 0.7 | AW28: 0.7 | AX28: 0.9 | AY28: 1 | AZ28: 1 | BB28: 0.7 | BC28: 0.7 | BD28: 0.7 | BE28: 0.9 | BF28: 1 | BG28: 1 | BH28: 0.7 | BI28: 0.7 | BJ28: 0.8 | BK28: 1 | BL28: 1 | BM28: 1 | BN28: 0.8 | BO28: 0.8 | BP28: 0.8 | BQ28: 1 | BR28: 1 | BS28: 1 | BT28: 0.8 | BU28: 0.8 | BV28: 0.8 | BW28: 1 | BX28: 1 | BY28: 1
C29: client A | D29: =ROUND(SUM($D17:$I17)*D$28,0) -> 9 | E29: =ROUND(SUM($D17:$I17)*E$28,0) -> 9 | F29: =ROUND(SUM($D17:$I17)*F$28,0) -> 10 | G29: =ROUND(SUM($D17:$I17)*G$28,0) -> 12 | H29: =ROUND(SUM($D17:$I17)*H$28,0) -> 14 | I29: =ROUND(SUM($D17:$I17)*I$28,0) -> 15 | J29: =ROUND(SUM($D17:$I17)*J$28,0) -> 10 | K29: =ROUND(SUM($D17:$I17)*K$28,0) -> 12 | ... AA29: =ROUND(SUM($D17:$I17)*AA$28,0) -> 17 | AC29: =ROUND(SUM($K17:$P17)*AC$28,0) -> 12 | AD29: =ROUND(SUM($K17:$P17)*AD$28,0) -> 12 | AE29: =ROUND(SUM($K17:$P17)*AE$28,0) -> 12 | AF29: =ROUND(SUM($K17:$P17)*AF$28,0) -> 15 | AG29: =ROUND(SUM($K17:$P17)*AG$28,0) -> 17 | AH29: =ROUND(SUM($K17:$P17)*AH$28,0) -> 17 | AI29: =ROUND(SUM($K17:$P17)*AI$28,0) -> 12 | AJ29: =ROUND(SUM($K17:$P17)*AJ$28,0) -> 12 | ... AZ29: =ROUND(SUM($K17:$P17)*AZ$28,0) -> 17 | BB29: =ROUND(SUM($R17:$W17)*BB$28,0) -> 12 | BC29: =ROUND(SUM($R17:$W17)*BC$28,0) -> 12 | BD29: =ROUND(SUM($R17:$W17)*BD$28,0) -> 12 | BE29: =ROUND(SUM($R17:$W17)*BE$28,0) -> 15 | BF29: =ROUND(SUM($R17:$W17)*BF$28,0) -> 17 | BG29: =ROUND(SUM($R17:$W17)*BG$28,0) -> 17 | BH29: =ROUND(SUM($R17:$W17)*BH$28,0) -> 12 | BI29: =ROUND(SUM($R17:$W17)*BI$28,0) -> 12 | ... BY29: =ROUND(SUM($R17:$W17)*BY$28,0) -> 17
C30: client B | D30: =ROUND(SUM($D18:$I18)*D$28,0) -> 13 | E30: =ROUND(SUM($D18:$I18)*E$28,0) -> 13 | F30: =ROUND(SUM($D18:$I18)*F$28,0) -> 16 | G30: =ROUND(SUM($D18:$I18)*G$28,0) -> 18 | H30: =ROUND(SUM($D18:$I18)*H$28,0) -> 22 | I30: =ROUND(SUM($D18:$I18)*I$28,0) -> 23 | J30: =ROUND(SUM($D18:$I18)*J$28,0) -> 16 | K30: =ROUND(SUM($D18:$I18)*K$28,0) -> 18 | ... AA30: =ROUND(SUM($D18:$I18)*AA$28,0) -> 26 | AC30: =ROUND(SUM($K18:$P18)*AC$28,0) -> 20 | AD30: =ROUND(SUM($K18:$P18)*AD$28,0) -> 20 | AE30: =ROUND(SUM($K18:$P18)*AE$28,0) -> 20 | AF30: =ROUND(SUM($K18:$P18)*AF$28,0) -> 26 | AG30: =ROUND(SUM($K18:$P18)*AG$28,0) -> 29 | AH30: =ROUND(SUM($K18:$P18)*AH$28,0) -> 29 | AI30: =ROUND(SUM($K18:$P18)*AI$28,0) -> 20 | AJ30: =ROUND(SUM($K18:$P18)*AJ$28,0) -> 20 | ... AZ30: =ROUND(SUM($K18:$P18)*AZ$28,0) -> 29 | BB30: =ROUND(SUM($R18:$W18)*BB$28,0) -> 20 | BC30: =ROUND(SUM($R18:$W18)*BC$28,0) -> 20 | BD30: =ROUND(SUM($R18:$W18)*BD$28,0) -> 20 | BE30: =ROUND(SUM($R18:$W18)*BE$28,0) -> 25 | BF30: =ROUND(SUM($R18:$W18)*BF$28,0) -> 28 | BG30: =ROUND(SUM($R18:$W18)*BG$28,0) -> 28 | BH30: =ROUND(SUM($R18:$W18)*BH$28,0) -> 20 | BI30: =ROUND(SUM($R18:$W18)*BI$28,0) -> 20 | ... BY30: =ROUND(SUM($R18:$W18)*BY$28,0) -> 28
C31: client C | D31: =ROUND(SUM($D19:$I19)*D$28,0) -> 5 | E31: =ROUND(SUM($D19:$I19)*E$28,0) -> 5 | F31: =ROUND(SUM($D19:$I19)*F$28,0) -> 5 | G31: =ROUND(SUM($D19:$I19)*G$28,0) -> 6 | H31: =ROUND(SUM($D19:$I19)*H$28,0) -> 8 | I31: =ROUND(SUM($D19:$I19)*I$28,0) -> 8 | J31: =ROUND(SUM($D19:$I19)*J$28,0) -> 5 | K31: =ROUND(SUM($D19:$I19)*K$28,0) -> 6 | ... AA31: =ROUND(SUM($D19:$I19)*AA$28,0) -> 9 | AC31: =ROUND(SUM($K19:$P19)*AC$28,0) -> 8 | AD31: =ROUND(SUM($K19:$P19)*AD$28,0) -> 8 | AE31: =ROUND(SUM($K19:$P19)*AE$28,0) -> 8 | AF31: =ROUND(SUM($K19:$P19)*AF$28,0) -> 10 | AG31: =ROUND(SUM($K19:$P19)*AG$28,0) -> 11 | AH31: =ROUND(SUM($K19:$P19)*AH$28,0) -> 11 | AI31: =ROUND(SUM($K19:$P19)*AI$28,0) -> 8 | AJ31: =ROUND(SUM($K19:$P19)*AJ$28,0) -> 8 | ... AZ31: =ROUND(SUM($K19:$P19)*AZ$28,0) -> 11 | BB31: =ROUND(SUM($R19:$W19)*BB$28,0) -> 6 | BC31: =ROUND(SUM($R19:$W19)*BC$28,0) -> 6 | BD31: =ROUND(SUM($R19:$W19)*BD$28,0) -> 6 | BE31: =ROUND(SUM($R19:$W19)*BE$28,0) -> 8 | BF31: =ROUND(SUM($R19:$W19)*BF$28,0) -> 9 | BG31: =ROUND(SUM($R19:$W19)*BG$28,0) -> 9 | BH31: =ROUND(SUM($R19:$W19)*BH$28,0) -> 6 | BI31: =ROUND(SUM($R19:$W19)*BI$28,0) -> 6 | ... BY31: =ROUND(SUM($R19:$W19)*BY$28,0) -> 9
C32: client D | D32: =ROUND(SUM($D20:$I20)*D$28,0) -> 14 | E32: =ROUND(SUM($D20:$I20)*E$28,0) -> 14 | F32: =ROUND(SUM($D20:$I20)*F$28,0) -> 17 | G32: =ROUND(SUM($D20:$I20)*G$28,0) -> 20 | H32: =ROUND(SUM($D20:$I20)*H$28,0) -> 24 | I32: =ROUND(SUM($D20:$I20)*I$28,0) -> 25 | J32: =ROUND(SUM($D20:$I20)*J$28,0) -> 17 | K32: =ROUND(SUM($D20:$I20)*K$28,0) -> 20 | ... AA32: =ROUND(SUM($D20:$I20)*AA$28,0) -> 28 | AC32: =ROUND(SUM($K20:$P20)*AC$28,0) -> 19 | AD32: =ROUND(SUM($K20:$P20)*AD$28,0) -> 19 | AE32: =ROUND(SUM($K20:$P20)*AE$28,0) -> 19 | AF32: =ROUND(SUM($K20:$P20)*AF$28,0) -> 24 | AG32: =ROUND(SUM($K20:$P20)*AG$28,0) -> 27 | AH32: =ROUND(SUM($K20:$P20)*AH$28,0) -> 27 | AI32: =ROUND(SUM($K20:$P20)*AI$28,0) -> 19 | AJ32: =ROUND(SUM($K20:$P20)*AJ$28,0) -> 19 | ... AZ32: =ROUND(SUM($K20:$P20)*AZ$28,0) -> 27 | BB32: =ROUND(SUM($R20:$W20)*BB$28,0) -> 19 | BC32: =ROUND(SUM($R20:$W20)*BC$28,0) -> 19 | BD32: =ROUND(SUM($R20:$W20)*BD$28,0) -> 19 | BE32: =ROUND(SUM($R20:$W20)*BE$28,0) -> 24 | BF32: =ROUND(SUM($R20:$W20)*BF$28,0) -> 27 | BG32: =ROUND(SUM($R20:$W20)*BG$28,0) -> 27 | BH32: =ROUND(SUM($R20:$W20)*BH$28,0) -> 19 | BI32: =ROUND(SUM($R20:$W20)*BI$28,0) -> 19 | ... BY32: =ROUND(SUM($R20:$W20)*BY$28,0) -> 27
C33: client E | D33: =ROUND(SUM($D21:$I21)*D$28,0) -> 9 | E33: =ROUND(SUM($D21:$I21)*E$28,0) -> 9 | F33: =ROUND(SUM($D21:$I21)*F$28,0) -> 11 | G33: =ROUND(SUM($D21:$I21)*G$28,0) -> 13 | H33: =ROUND(SUM($D21:$I21)*H$28,0) -> 15 | I33: =ROUND(SUM($D21:$I21)*I$28,0) -> 16 | J33: =ROUND(SUM($D21:$I21)*J$28,0) -> 11 | K33: =ROUND(SUM($D21:$I21)*K$28,0) -> 13 | ... AA33: =ROUND(SUM($D21:$I21)*AA$28,0) -> 18 | AC33: =ROUND(SUM($K21:$P21)*AC$28,0) -> 12 | AD33: =ROUND(SUM($K21:$P21)*AD$28,0) -> 12 | AE33: =ROUND(SUM($K21:$P21)*AE$28,0) -> 12 | AF33: =ROUND(SUM($K21:$P21)*AF$28,0) -> 15 | AG33: =ROUND(SUM($K21:$P21)*AG$28,0) -> 17 | AH33: =ROUND(SUM($K21:$P21)*AH$28,0) -> 17 | AI33: =ROUND(SUM($K21:$P21)*AI$28,0) -> 12 | AJ33: =ROUND(SUM($K21:$P21)*AJ$28,0) -> 12 | ... AZ33: =ROUND(SUM($K21:$P21)*AZ$28,0) -> 17 | BB33: =ROUND(SUM($R21:$W21)*BB$28,0) -> 12 | BC33: =ROUND(SUM($R21:$W21)*BC$28,0) -> 12 | BD33: =ROUND(SUM($R21:$W21)*BD$28,0) -> 12 | BE33: =ROUND(SUM($R21:$W21)*BE$28,0) -> 15 | BF33: =ROUND(SUM($R21:$W21)*BF$28,0) -> 17 | BG33: =ROUND(SUM($R21:$W21)*BG$28,0) -> 17 | BH33: =ROUND(SUM($R21:$W21)*BH$28,0) -> 12 | BI33: =ROUND(SUM($R21:$W21)*BI$28,0) -> 12 | ... BY33: =ROUND(SUM($R21:$W21)*BY$28,0) -> 17
AC34: =ROUND(SUM($K22:$P22)*AC$28,0) -> 0 | AD34: =ROUND(SUM($K22:$P22)*AD$28,0) -> 0 | AE34: =ROUND(SUM($K22:$P22)*AE$28,0) -> 0 | AF34: =ROUND(SUM($K22:$P22)*AF$28,0) -> 0 | AG34: =ROUND(SUM($K22:$P22)*AG$28,0) -> 0 | AH34: =ROUND(SUM($K22:$P22)*AH$28,0) -> 0 | AI34: =ROUND(SUM($K22:$P22)*AI$28,0) -> 0 | AJ34: =ROUND(SUM($K22:$P22)*AJ$28,0) -> 0 | ... AZ34: =ROUND(SUM($K22:$P22)*AZ$28,0) -> 0 | BB34: =ROUND(SUM($R22:$W22)*BB$28,0) -> 0 | BC34: =ROUND(SUM($R22:$W22)*BC$28,0) -> 0 | BD34: =ROUND(SUM($R22:$W22)*BD$28,0) -> 0 | BE34: =ROUND(SUM($R22:$W22)*BE$28,0) -> 0 | BF34: =ROUND(SUM($R22:$W22)*BF$28,0) -> 0 | BG34: =ROUND(SUM($R22:$W22)*BG$28,0) -> 0 | BH34: =ROUND(SUM($R22:$W22)*BH$28,0) -> 0 | BI34: =ROUND(SUM($R22:$W22)*BI$28,0) -> 0 | ... BY34: =ROUND(SUM($R22:$W22)*BY$28,0) -> 0
D35: =SUM(D29:D34) -> 50 | E35: =SUM(E29:E34) -> 50 | F35: =SUM(F29:F34) -> 59 | G35: =SUM(G29:G34) -> 69 | H35: =SUM(H29:H34) -> 83 | I35: =SUM(I29:I34) -> 87 | J35: =SUM(J29:J34) -> 59 | K35: =SUM(K29:K34) -> 69 | ... AA35: =SUM(AA29:AA34) -> 98 | AC35: =SUM(AC29:AC34) -> 71 | AD35: =SUM(AD29:AD34) -> 71 | AE35: =SUM(AE29:AE34) -> 71 | AF35: =SUM(AF29:AF34) -> 90 | AG35: =SUM(AG29:AG34) -> 101 | AH35: =SUM(AH29:AH34) -> 101 | AI35: =SUM(AI29:AI34) -> 71 | AJ35: =SUM(AJ29:AJ34) -> 71 | ... AZ35: =SUM(AZ29:AZ34) -> 101 | BB35: =SUM(BB29:BB34) -> 69 | BC35: =SUM(BC29:BC34) -> 69 | BD35: =SUM(BD29:BD34) -> 69 | BE35: =SUM(BE29:BE34) -> 87 | BF35: =SUM(BF29:BF34) -> 98 | BG35: =SUM(BG29:BG34) -> 98 | BH35: =SUM(BH29:BH34) -> 69 | BI35: =SUM(BI29:BI34) -> 69 | ... BY35: =SUM(BY29:BY34) -> 98
C38: Evolution des mois
D39: 2025 | P39: 2026 | AB39: 2027 | AN39: 2028
C40: Mois | D40: 1 | E40: 2 | F40: 3 | G40: 4 | H40: 5 | I40: 6 | J40: 7 | K40: 8 | L40: 9 | M40: 10 | N40: 11 | O40: 12 | P40: 1 | Q40: 2 | R40: 3 | S40: 4 | T40: 5 | U40: 6 | V40: 7 | W40: 8 | X40: 9 | Y40: 10 | Z40: 11 | AA40: 12 | AB40: 1 | AC40: 2 | AD40: 3 | AE40: 4 | AF40: 5 | AG40: 6 | AH40: 7 | AI40: 8 | AJ40: 9 | AK40: 10 | AL40: 11 | AM40: 12 | AN40: 1 | AO40: 2 | AP40: 3 | AQ40: 4 | AR40: 5 | AS40: 6 | AT40: 7 | AU40: 8 | AV40: 9 | AW40: 10 | AX40: 11 | AY40: 12
C41: % remplissage mensuel | D41: 0.5 | E41: 0.6 | F41: 0.65 | G41: 0.7 | H41: 0.85 | I41: 1 | J41: 1.1 | K41: 1.1 | L41: 1 | M41: 0.85 | N41: 0.8 | O41: 0.55 | P41: 0.5 | Q41: 0.5 | R41: 0.55 | S41: 0.7 | T41: 0.7 | U41: 1 | V41: 1.1 | W41: 1.1 | X41: 1 | Y41: 0.7 | Z41: 0.6 | AA41: 0.5 | AB41: 0.5 | AC41: 0.5 | AD41: 0.5 | AE41: 0.7 | AF41: 0.7 | AG41: 1 | AH41: 1.1 | AI41: 1.1 | AJ41: 1 | AK41: 0.7 | AL41: 0.6 | AM41: 0.4 | AN41: 0.6 | AO41: 0.65 | AP41: 0.7 | AQ41: 0.75 | AR41: 0.8 | AS41: 1.1 | AT41: 1.2 | AU41: 1.1 | AV41: 1 | AW41: 0.8 | AX41: 0.65 | AY41: 0.5
C42: client A | D42: =ROUND(SUM($D29:$AA29)*D$41,0) -> 155 | E42: =ROUND(SUM($D29:$AA29)*E$41,0) -> 185 | F42: =ROUND(SUM($D29:$AA29)*F$41,0) -> 201 | G42: =ROUND(SUM($D29:$AA29)*G$41,0) -> 216 | H42: =ROUND(SUM($D29:$AA29)*H$41,0) -> 263 | I42: =ROUND(SUM($D29:$AA29)*I$41,0) -> 309 | J42: =ROUND(SUM($D29:$AA29)*J$41,0) -> 340 | K42: =ROUND(SUM($D29:$AA29)*K$41,0) -> 340 | ... O42: =ROUND(SUM($D29:$AA29)*O$41,0) -> 170 | P42: =ROUND(SUM($AC29:$AZ29)*P$41,0) -> 170 | Q42: =ROUND(SUM($AC29:$AZ29)*Q$41,0) -> 170 | R42: =ROUND(SUM($AC29:$AZ29)*R$41,0) -> 187 | S42: =ROUND(SUM($AC29:$AZ29)*S$41,0) -> 238 | T42: =ROUND(SUM($AC29:$AZ29)*T$41,0) -> 238 | U42: =ROUND(SUM($AC29:$AZ29)*U$41,0) -> 340 | V42: =ROUND(SUM($AC29:$AZ29)*V$41,0) -> 374 | W42: =ROUND(SUM($AC29:$AZ29)*W$41,0) -> 374 | ... AA42: =ROUND(SUM($AC29:$AZ29)*AA$41,0) -> 170 | AB42: =ROUND(SUM($BB29:$BY29)*AB$41,0) -> 180 | AC42: =ROUND(SUM($BB29:$BY29)*AC$41,0) -> 180 | AD42: =ROUND(SUM($BB29:$BY29)*AD$41,0) -> 180 | AE42: =ROUND(SUM($BB29:$BY29)*AE$41,0) -> 252 | AF42: =ROUND(SUM($BB29:$BY29)*AF$41,0) -> 252 | AG42: =ROUND(SUM($BB29:$BY29)*AG$41,0) -> 360 | AH42: =ROUND(SUM($BB29:$BY29)*AH$41,0) -> 396 | AI42: =ROUND(SUM($BB29:$BY29)*AI$41,0) -> 396 | ... AY42: =ROUND(SUM($BB29:$BY29)*AY$41,0) -> 180
C43: client B | D43: =ROUND(SUM($D30:$AA30)*D$41,0) -> 237 | E43: =ROUND(SUM($D30:$AA30)*E$41,0) -> 284 | F43: =ROUND(SUM($D30:$AA30)*F$41,0) -> 308 | G43: =ROUND(SUM($D30:$AA30)*G$41,0) -> 332 | H43: =ROUND(SUM($D30:$AA30)*H$41,0) -> 403 | I43: =ROUND(SUM($D30:$AA30)*I$41,0) -> 474 | J43: =ROUND(SUM($D30:$AA30)*J$41,0) -> 521 | K43: =ROUND(SUM($D30:$AA30)*K$41,0) -> 521 | ... O43: =ROUND(SUM($D30:$AA30)*O$41,0) -> 261 | P43: =ROUND(SUM($AC30:$AZ30)*P$41,0) -> 288 | Q43: =ROUND(SUM($AC30:$AZ30)*Q$41,0) -> 288 | R43: =ROUND(SUM($AC30:$AZ30)*R$41,0) -> 317 | S43: =ROUND(SUM($AC30:$AZ30)*S$41,0) -> 403 | T43: =ROUND(SUM($AC30:$AZ30)*T$41,0) -> 403 | U43: =ROUND(SUM($AC30:$AZ30)*U$41,0) -> 576 | V43: =ROUND(SUM($AC30:$AZ30)*V$41,0) -> 634 | W43: =ROUND(SUM($AC30:$AZ30)*W$41,0) -> 634 | ... AA43: =ROUND(SUM($AC30:$AZ30)*AA$41,0) -> 288 | AB43: =ROUND(SUM($BB30:$BY30)*AB$41,0) -> 294 | AC43: =ROUND(SUM($BB30:$BY30)*AC$41,0) -> 294 | AD43: =ROUND(SUM($BB30:$BY30)*AD$41,0) -> 294 | AE43: =ROUND(SUM($BB30:$BY30)*AE$41,0) -> 411 | AF43: =ROUND(SUM($BB30:$BY30)*AF$41,0) -> 411 | AG43: =ROUND(SUM($BB30:$BY30)*AG$41,0) -> 587 | AH43: =ROUND(SUM($BB30:$BY30)*AH$41,0) -> 646 | AI43: =ROUND(SUM($BB30:$BY30)*AI$41,0) -> 646 | ... AY43: =ROUND(SUM($BB30:$BY30)*AY$41,0) -> 294
C44: client C | D44: =ROUND(SUM($D31:$AA31)*D$41,0) -> 82 | E44: =ROUND(SUM($D31:$AA31)*E$41,0) -> 98 | F44: =ROUND(SUM($D31:$AA31)*F$41,0) -> 106 | G44: =ROUND(SUM($D31:$AA31)*G$41,0) -> 114 | H44: =ROUND(SUM($D31:$AA31)*H$41,0) -> 139 | I44: =ROUND(SUM($D31:$AA31)*I$41,0) -> 163 | J44: =ROUND(SUM($D31:$AA31)*J$41,0) -> 179 | K44: =ROUND(SUM($D31:$AA31)*K$41,0) -> 179 | ... O44: =ROUND(SUM($D31:$AA31)*O$41,0) -> 90 | P44: =ROUND(SUM($AC31:$AZ31)*P$41,0) -> 112 | Q44: =ROUND(SUM($AC31:$AZ31)*Q$41,0) -> 112 | R44: =ROUND(SUM($AC31:$AZ31)*R$41,0) -> 123 | S44: =ROUND(SUM($AC31:$AZ31)*S$41,0) -> 157 | T44: =ROUND(SUM($AC31:$AZ31)*T$41,0) -> 157 | U44: =ROUND(SUM($AC31:$AZ31)*U$41,0) -> 224 | V44: =ROUND(SUM($AC31:$AZ31)*V$41,0) -> 246 | W44: =ROUND(SUM($AC31:$AZ31)*W$41,0) -> 246 | ... AA44: =ROUND(SUM($AC31:$AZ31)*AA$41,0) -> 112 | AB44: =ROUND(SUM($BB31:$BY31)*AB$41,0) -> 93 | AC44: =ROUND(SUM($BB31:$BY31)*AC$41,0) -> 93 | AD44: =ROUND(SUM($BB31:$BY31)*AD$41,0) -> 93 | AE44: =ROUND(SUM($BB31:$BY31)*AE$41,0) -> 130 | AF44: =ROUND(SUM($BB31:$BY31)*AF$41,0) -> 130 | AG44: =ROUND(SUM($BB31:$BY31)*AG$41,0) -> 186 | AH44: =ROUND(SUM($BB31:$BY31)*AH$41,0) -> 205 | AI44: =ROUND(SUM($BB31:$BY31)*AI$41,0) -> 205 | ... AY44: =ROUND(SUM($BB31:$BY31)*AY$41,0) -> 93
C45: client D | D45: =ROUND(SUM($D32:$AA32)*D$41,0) -> 257 | E45: =ROUND(SUM($D32:$AA32)*E$41,0) -> 308 | F45: =ROUND(SUM($D32:$AA32)*F$41,0) -> 334 | G45: =ROUND(SUM($D32:$AA32)*G$41,0) -> 360 | H45: =ROUND(SUM($D32:$AA32)*H$41,0) -> 437 | I45: =ROUND(SUM($D32:$AA32)*I$41,0) -> 514 | J45: =ROUND(SUM($D32:$AA32)*J$41,0) -> 565 | K45: =ROUND(SUM($D32:$AA32)*K$41,0) -> 565 | ... O45: =ROUND(SUM($D32:$AA32)*O$41,0) -> 283 | P45: =ROUND(SUM($AC32:$AZ32)*P$41,0) -> 270 | Q45: =ROUND(SUM($AC32:$AZ32)*Q$41,0) -> 270 | R45: =ROUND(SUM($AC32:$AZ32)*R$41,0) -> 297 | S45: =ROUND(SUM($AC32:$AZ32)*S$41,0) -> 378 | T45: =ROUND(SUM($AC32:$AZ32)*T$41,0) -> 378 | U45: =ROUND(SUM($AC32:$AZ32)*U$41,0) -> 540 | V45: =ROUND(SUM($AC32:$AZ32)*V$41,0) -> 594 | W45: =ROUND(SUM($AC32:$AZ32)*W$41,0) -> 594 | ... AA45: =ROUND(SUM($AC32:$AZ32)*AA$41,0) -> 270 | AB45: =ROUND(SUM($BB32:$BY32)*AB$41,0) -> 285 | AC45: =ROUND(SUM($BB32:$BY32)*AC$41,0) -> 285 | AD45: =ROUND(SUM($BB32:$BY32)*AD$41,0) -> 285 | AE45: =ROUND(SUM($BB32:$BY32)*AE$41,0) -> 399 | AF45: =ROUND(SUM($BB32:$BY32)*AF$41,0) -> 399 | AG45: =ROUND(SUM($BB32:$BY32)*AG$41,0) -> 570 | AH45: =ROUND(SUM($BB32:$BY32)*AH$41,0) -> 627 | AI45: =ROUND(SUM($BB32:$BY32)*AI$41,0) -> 627 | ... AY45: =ROUND(SUM($BB32:$BY32)*AY$41,0) -> 285
C46: client E | D46: =ROUND(SUM($D33:$AA33)*D$41,0) -> 165 | E46: =ROUND(SUM($D33:$AA33)*E$41,0) -> 198 | F46: =ROUND(SUM($D33:$AA33)*F$41,0) -> 215 | G46: =ROUND(SUM($D33:$AA33)*G$41,0) -> 231 | H46: =ROUND(SUM($D33:$AA33)*H$41,0) -> 281 | I46: =ROUND(SUM($D33:$AA33)*I$41,0) -> 330 | J46: =ROUND(SUM($D33:$AA33)*J$41,0) -> 363 | K46: =ROUND(SUM($D33:$AA33)*K$41,0) -> 363 | ... O46: =ROUND(SUM($D33:$AA33)*O$41,0) -> 182 | P46: =ROUND(SUM($AC33:$AZ33)*P$41,0) -> 170 | Q46: =ROUND(SUM($AC33:$AZ33)*Q$41,0) -> 170 | R46: =ROUND(SUM($AC33:$AZ33)*R$41,0) -> 187 | S46: =ROUND(SUM($AC33:$AZ33)*S$41,0) -> 238 | T46: =ROUND(SUM($AC33:$AZ33)*T$41,0) -> 238 | U46: =ROUND(SUM($AC33:$AZ33)*U$41,0) -> 340 | V46: =ROUND(SUM($AC33:$AZ33)*V$41,0) -> 374 | W46: =ROUND(SUM($AC33:$AZ33)*W$41,0) -> 374 | ... AA46: =ROUND(SUM($AC33:$AZ33)*AA$41,0) -> 170 | AB46: =ROUND(SUM($BB33:$BY33)*AB$41,0) -> 180 | AC46: =ROUND(SUM($BB33:$BY33)*AC$41,0) -> 180 | AD46: =ROUND(SUM($BB33:$BY33)*AD$41,0) -> 180 | AE46: =ROUND(SUM($BB33:$BY33)*AE$41,0) -> 252 | AF46: =ROUND(SUM($BB33:$BY33)*AF$41,0) -> 252 | AG46: =ROUND(SUM($BB33:$BY33)*AG$41,0) -> 360 | AH46: =ROUND(SUM($BB33:$BY33)*AH$41,0) -> 396 | AI46: =ROUND(SUM($BB33:$BY33)*AI$41,0) -> 396 | ... AY46: =ROUND(SUM($BB33:$BY33)*AY$41,0) -> 180
D47: =ROUND(SUM($D34:$AA34)*D$41,0) -> 0 | E47: =ROUND(SUM($D34:$AA34)*E$41,0) -> 0 | F47: =ROUND(SUM($D34:$AA34)*F$41,0) -> 0 | G47: =ROUND(SUM($D34:$AA34)*G$41,0) -> 0 | H47: =ROUND(SUM($D34:$AA34)*H$41,0) -> 0 | I47: =ROUND(SUM($D34:$AA34)*I$41,0) -> 0 | J47: =ROUND(SUM($D34:$AA34)*J$41,0) -> 0 | K47: =ROUND(SUM($D34:$AA34)*K$41,0) -> 0 | ... O47: =ROUND(SUM($D34:$AA34)*O$41,0) -> 0 | P47: =ROUND(SUM($AC34:$AZ34)*P$41,0) -> 0 | Q47: =ROUND(SUM($AC34:$AZ34)*Q$41,0) -> 0 | R47: =ROUND(SUM($AC34:$AZ34)*R$41,0) -> 0 | S47: =ROUND(SUM($AC34:$AZ34)*S$41,0) -> 0 | T47: =ROUND(SUM($AC34:$AZ34)*T$41,0) -> 0 | U47: =ROUND(SUM($AC34:$AZ34)*U$41,0) -> 0 | V47: =ROUND(SUM($AC34:$AZ34)*V$41,0) -> 0 | W47: =ROUND(SUM($AC34:$AZ34)*W$41,0) -> 0 | ... AA47: =ROUND(SUM($AC34:$AZ34)*AA$41,0) -> 0 | AB47: =ROUND(SUM($BB34:$BY34)*AB$41,0) -> 0 | AC47: =ROUND(SUM($BB34:$BY34)*AC$41,0) -> 0 | AD47: =ROUND(SUM($BB34:$BY34)*AD$41,0) -> 0 | AE47: =ROUND(SUM($BB34:$BY34)*AE$41,0) -> 0 | AF47: =ROUND(SUM($BB34:$BY34)*AF$41,0) -> 0 | AG47: =ROUND(SUM($BB34:$BY34)*AG$41,0) -> 0 | AH47: =ROUND(SUM($BB34:$BY34)*AH$41,0) -> 0 | AI47: =ROUND(SUM($BB34:$BY34)*AI$41,0) -> 0 | ... AY47: =ROUND(SUM($BB34:$BY34)*AY$41,0) -> 0
C48: Nombre de client mensuel | D48: =SUM(D42:D47) -> 896 | E48: =SUM(E42:E47) -> 1073 | F48: =SUM(F42:F47) -> 1164 | G48: =SUM(G42:G47) -> 1253 | H48: =SUM(H42:H47) -> 1523 | I48: =SUM(I42:I47) -> 1790 | J48: =SUM(J42:J47) -> 1968 | K48: =SUM(K42:K47) -> 1968 | ... AY48: =SUM(AY42:AY47) -> 1032
C49: clients moyen / jour | D49: =D48/24 -> 37.333333 | E49: =E48/24 -> 44.708333 | F49: =F48/24 -> 48.5 | G49: =G48/24 -> 52.208333 | H49: =H48/24 -> 63.458333 | I49: =I48/24 -> 74.583333 | J49: =J48/24 -> 82 | K49: =K48/24 -> 82 | ... AY49: =AY48/24 -> 43
C51: CA jour/mois
D52: 2025 | P52: 2026 | AB52: 2027 | AN52: 2028
C53: Mois | D53: 1 | E53: 2 | F53: 3 | G53: 4 | H53: 5 | I53: 6 | J53: 7 | K53: 8 | L53: 9 | M53: 10 | N53: 11 | O53: 12 | P53: 1 | Q53: 2 | R53: 3 | S53: 4 | T53: 5 | U53: 6 | V53: 7 | W53: 8 | X53: 9 | Y53: 10 | Z53: 11 | AA53: 12 | AB53: 1 | AC53: 2 | AD53: 3 | AE53: 4 | AF53: 5 | AG53: 6 | AH53: 7 | AI53: 8 | AJ53: 9 | AK53: 10 | AL53: 11 | AM53: 12 | AN53: 1 | AO53: 2 | AP53: 3 | AQ53: 4 | AR53: 5 | AS53: 6 | AT53: 7 | AU53: 8 | AV53: 9 | AW53: 10 | AX53: 11 | AY53: 12
C54: CA moyen journalier | D54: =D55/24 -> 483.23674 | E54: =E55/24 -> 579.03788 | F54: =F55/24 -> 628.10795 | G54: =G55/24 -> 676.11174 | H54: =H55/24 -> 821.72159 | I54: =I55/24 -> 965.73485 | J54: =J55/24 -> 1061.7443 | K54: =K55/24 -> 1061.7443 | ... AY54: =AY55/24 -> 598.86407
C55: CA mensuel | D55: =SUM(D56:D61) -> 11597.682 | E55: =SUM(E56:E61) -> 13896.909 | F55: =SUM(F56:F61) -> 15074.591 | G55: =SUM(G56:G61) -> 16226.682 | H55: =SUM(H56:H61) -> 19721.318 | I55: =SUM(I56:I61) -> 23177.636 | J55: =SUM(J56:J61) -> 25481.864 | K55: =SUM(K56:K61) -> 25481.864 | ... AY55: =SUM(AY56:AY61) -> 14372.738
B56: =UNIT_PRICE_CLIENT_A -> 5 | C56: client A | D56: =D42*$B56 -> 775 | E56: =E42*$B56 -> 925 | F56: =F42*$B56 -> 1005 | G56: =G42*$B56 -> 1080 | H56: =H42*$B56 -> 1315 | I56: =I42*$B56 -> 1545 | J56: =J42*$B56 -> 1700 | K56: =K42*$B56 -> 1700 | ... O56: =O42*$B56 -> 850 | P56: =P42*$B56*(1+inflation_vente) -> 875.5 | Q56: =Q42*$B56*(1+inflation_vente) -> 875.5 | R56: =R42*$B56*(1+inflation_vente) -> 963.05 | S56: =S42*$B56*(1+inflation_vente) -> 1225.7 | T56: =T42*$B56*(1+inflation_vente) -> 1225.7 | U56: =U42*$B56*(1+inflation_vente) -> 1751 | V56: =V42*$B56*(1+inflation_vente) -> 1926.1 | W56: =W42*$B56*(1+inflation_vente) -> 1926.1 | ... AA56: =AA42*$B56*(1+inflation_vente) -> 875.5 | AB56: =AB42*$B56*(1+inflation_vente)^2 -> 954.81 | AC56: =AC42*$B56*(1+inflation_vente)^2 -> 954.81 | AD56: =AD42*$B56*(1+inflation_vente)^2 -> 954.81 | AE56: =AE42*$B56*(1+inflation_vente)^2 -> 1336.734 | AF56: =AF42*$B56*(1+inflation_vente)^2 -> 1336.734 | AG56: =AG42*$B56*(1+inflation_vente)^2 -> 1909.62 | AH56: =AH42*$B56*(1+inflation_vente)^2 -> 2100.582 | AI56: =AI42*$B56*(1+inflation_vente)^2 -> 2100.582 | ... AM56: =AM42*$B56*(1+inflation_vente)^2 -> 763.848 | AN56: =AN42*$B56*(1+inflation_vente)^3 -> 1180.1452 | AO56: =AO42*$B56*(1+inflation_vente)^3 -> 1278.4906 | AP56: =AP42*$B56*(1+inflation_vente)^3 -> 1376.836 | AQ56: =AQ42*$B56*(1+inflation_vente)^3 -> 1475.1815 | AR56: =AR42*$B56*(1+inflation_vente)^3 -> 1573.5269 | AS56: =AS42*$B56*(1+inflation_vente)^3 -> 2163.5995 | AT56: =AT42*$B56*(1+inflation_vente)^3 -> 2360.2903 | AU56: =AU42*$B56*(1+inflation_vente)^3 -> 2163.5995 | ... AY56: =AY42*$B56*(1+inflation_vente)^3 -> 983.4543
B57: =UNIT_PRICE_CLIENT_B -> 9.1818182 | C57: client B | D57: =D43*$B57 -> 2176.0909 | E57: =E43*$B57 -> 2607.6364 | F57: =F43*$B57 -> 2828 | G57: =G43*$B57 -> 3048.3636 | H57: =H43*$B57 -> 3700.2727 | I57: =I43*$B57 -> 4352.1818 | J57: =J43*$B57 -> 4783.7273 | K57: =K43*$B57 -> 4783.7273 | ... O57: =O43*$B57 -> 2396.4545 | P57: =P43*$B57*(1+inflation_vente) -> 2723.6945 | Q57: =Q43*$B57*(1+inflation_vente) -> 2723.6945 | R57: =R43*$B57*(1+inflation_vente) -> 2997.9555 | S57: =S43*$B57*(1+inflation_vente) -> 3811.2809 | T57: =T43*$B57*(1+inflation_vente) -> 3811.2809 | U57: =U43*$B57*(1+inflation_vente) -> 5447.3891 | V57: =V43*$B57*(1+inflation_vente) -> 5995.9109 | W57: =W43*$B57*(1+inflation_vente) -> 5995.9109 | ... AA57: =AA43*$B57*(1+inflation_vente) -> 2723.6945 | AB57: =AB43*$B57*(1+inflation_vente)^2 -> 2863.8513 | AC57: =AC43*$B57*(1+inflation_vente)^2 -> 2863.8513 | AD57: =AD43*$B57*(1+inflation_vente)^2 -> 2863.8513 | AE57: =AE43*$B57*(1+inflation_vente)^2 -> 4003.5473 | AF57: =AF43*$B57*(1+inflation_vente)^2 -> 4003.5473 | AG57: =AG43*$B57*(1+inflation_vente)^2 -> 5717.9617 | AH57: =AH43*$B57*(1+inflation_vente)^2 -> 6292.6801 | AI57: =AI43*$B57*(1+inflation_vente)^2 -> 6292.6801 | ... AM57: =AM43*$B57*(1+inflation_vente)^2 -> 2289.1329 | AN57: =AN43*$B57*(1+inflation_vente)^3 -> 3531.6937 | AO57: =AO43*$B57*(1+inflation_vente)^3 -> 3832.6903 | AP57: =AP43*$B57*(1+inflation_vente)^3 -> 4123.6537 | AQ57: =AQ43*$B57*(1+inflation_vente)^3 -> 4414.6171 | AR57: =AR43*$B57*(1+inflation_vente)^3 -> 4715.6137 | AS57: =AS43*$B57*(1+inflation_vente)^3 -> 6481.4605 | AT57: =AT43*$B57*(1+inflation_vente)^3 -> 7063.3873 | AU57: =AU43*$B57*(1+inflation_vente)^3 -> 6481.4605 | ... AY57: =AY43*$B57*(1+inflation_vente)^3 -> 2949.7669
B58: =UNIT_PRICE_CLIENT_C -> 12.727273 | C58: client C | D58: =D44*$B58 -> 1043.6364 | E58: =E44*$B58 -> 1247.2727 | F58: =F44*$B58 -> 1349.0909 | G58: =G44*$B58 -> 1450.9091 | H58: =H44*$B58 -> 1769.0909 | I58: =I44*$B58 -> 2074.5455 | J58: =J44*$B58 -> 2278.1818 | K58: =K44*$B58 -> 2278.1818 | ... O58: =O44*$B58 -> 1145.4545 | P58: =P44*$B58*(1+inflation_vente) -> 1468.2182 | Q58: =Q44*$B58*(1+inflation_vente) -> 1468.2182 | R58: =R44*$B58*(1+inflation_vente) -> 1612.4182 | S58: =S44*$B58*(1+inflation_vente) -> 2058.1273 | T58: =T44*$B58*(1+inflation_vente) -> 2058.1273 | U58: =U44*$B58*(1+inflation_vente) -> 2936.4364 | V58: =V44*$B58*(1+inflation_vente) -> 3224.8364 | W58: =W44*$B58*(1+inflation_vente) -> 3224.8364 | ... AA58: =AA44*$B58*(1+inflation_vente) -> 1468.2182 | AB58: =AB44*$B58*(1+inflation_vente)^2 -> 1255.7198 | AC58: =AC44*$B58*(1+inflation_vente)^2 -> 1255.7198 | AD58: =AD44*$B58*(1+inflation_vente)^2 -> 1255.7198 | AE58: =AE44*$B58*(1+inflation_vente)^2 -> 1755.3073 | AF58: =AF44*$B58*(1+inflation_vente)^2 -> 1755.3073 | AG58: =AG44*$B58*(1+inflation_vente)^2 -> 2511.4396 | AH58: =AH44*$B58*(1+inflation_vente)^2 -> 2767.9845 | AI58: =AI44*$B58*(1+inflation_vente)^2 -> 2767.9845 | ... AM58: =AM44*$B58*(1+inflation_vente)^2 -> 999.17491 | AN58: =AN44*$B58*(1+inflation_vente)^3 -> 1557.6327 | AO58: =AO44*$B58*(1+inflation_vente)^3 -> 1682.7996 | AP58: =AP44*$B58*(1+inflation_vente)^3 -> 1807.9665 | AQ58: =AQ44*$B58*(1+inflation_vente)^3 -> 1947.0408 | AR58: =AR44*$B58*(1+inflation_vente)^3 -> 2072.2077 | AS58: =AS44*$B58*(1+inflation_vente)^3 -> 2851.0241 | AT58: =AT44*$B58*(1+inflation_vente)^3 -> 3101.3579 | AU58: =AU44*$B58*(1+inflation_vente)^3 -> 2851.0241 | ... AY58: =AY44*$B58*(1+inflation_vente)^3 -> 1293.3914
B59: =UNIT_PRICE_CLIENT_D -> 16.363636 | C59: client D | D59: =D45*$B59 -> 4205.4545 | E59: =E45*$B59 -> 5040 | F59: =F45*$B59 -> 5465.4545 | G59: =G45*$B59 -> 5890.9091 | H59: =H45*$B59 -> 7150.9091 | I59: =I45*$B59 -> 8410.9091 | J59: =J45*$B59 -> 9245.4545 | K59: =K45*$B59 -> 9245.4545 | ... O59: =O45*$B59 -> 4630.9091 | P59: =P45*$B59*(1+inflation_vente) -> 4550.7273 | Q59: =Q45*$B59*(1+inflation_vente) -> 4550.7273 | R59: =R45*$B59*(1+inflation_vente) -> 5005.8 | S59: =S45*$B59*(1+inflation_vente) -> 6371.0182 | T59: =T45*$B59*(1+inflation_vente) -> 6371.0182 | U59: =U45*$B59*(1+inflation_vente) -> 9101.4545 | V59: =V45*$B59*(1+inflation_vente) -> 10011.6 | W59: =W45*$B59*(1+inflation_vente) -> 10011.6 | ... AA59: =AA45*$B59*(1+inflation_vente) -> 4550.7273 | AB59: =AB45*$B59*(1+inflation_vente)^2 -> 4947.6518 | AC59: =AC45*$B59*(1+inflation_vente)^2 -> 4947.6518 | AD59: =AD45*$B59*(1+inflation_vente)^2 -> 4947.6518 | AE59: =AE45*$B59*(1+inflation_vente)^2 -> 6926.7125 | AF59: =AF45*$B59*(1+inflation_vente)^2 -> 6926.7125 | AG59: =AG45*$B59*(1+inflation_vente)^2 -> 9895.3036 | AH59: =AH45*$B59*(1+inflation_vente)^2 -> 10884.834 | AI59: =AI45*$B59*(1+inflation_vente)^2 -> 10884.834 | ... AM59: =AM45*$B59*(1+inflation_vente)^2 -> 3958.1215 | AN59: =AN45*$B59*(1+inflation_vente)^3 -> 6115.2976 | AO59: =AO45*$B59*(1+inflation_vente)^3 -> 6633.8463 | AP59: =AP45*$B59*(1+inflation_vente)^3 -> 7134.5139 | AQ59: =AQ45*$B59*(1+inflation_vente)^3 -> 7653.0626 | AR59: =AR45*$B59*(1+inflation_vente)^3 -> 8153.7302 | AS59: =AS45*$B59*(1+inflation_vente)^3 -> 11211.379 | AT59: =AT45*$B59*(1+inflation_vente)^3 -> 12230.595 | AU59: =AU45*$B59*(1+inflation_vente)^3 -> 11211.379 | ... AY59: =AY45*$B59*(1+inflation_vente)^3 -> 5096.0814
B60: =UNIT_PRICE_CLIENT_E -> 20.590909 | C60: client E | D60: =D46*$B60 -> 3397.5 | E60: =E46*$B60 -> 4077 | F60: =F46*$B60 -> 4427.0455 | G60: =G46*$B60 -> 4756.5 | H60: =H46*$B60 -> 5786.0455 | I60: =I46*$B60 -> 6795 | J60: =J46*$B60 -> 7474.5 | K60: =K46*$B60 -> 7474.5 | ... O60: =O46*$B60 -> 3747.5455 | P60: =P46*$B60*(1+inflation_vente) -> 3605.4682 | Q60: =Q46*$B60*(1+inflation_vente) -> 3605.4682 | R60: =R46*$B60*(1+inflation_vente) -> 3966.015 | S60: =S46*$B60*(1+inflation_vente) -> 5047.6555 | T60: =T46*$B60*(1+inflation_vente) -> 5047.6555 | U60: =U46*$B60*(1+inflation_vente) -> 7210.9364 | V60: =V46*$B60*(1+inflation_vente) -> 7932.03 | W60: =W46*$B60*(1+inflation_vente) -> 7932.03 | ... AA60: =AA46*$B60*(1+inflation_vente) -> 3605.4682 | AB60: =AB46*$B60*(1+inflation_vente)^2 -> 3932.0812 | AC60: =AC46*$B60*(1+inflation_vente)^2 -> 3932.0812 | AD60: =AD46*$B60*(1+inflation_vente)^2 -> 3932.0812 | AE60: =AE46*$B60*(1+inflation_vente)^2 -> 5504.9137 | AF60: =AF46*$B60*(1+inflation_vente)^2 -> 5504.9137 | AG60: =AG46*$B60*(1+inflation_vente)^2 -> 7864.1624 | AH60: =AH46*$B60*(1+inflation_vente)^2 -> 8650.5786 | AI60: =AI46*$B60*(1+inflation_vente)^2 -> 8650.5786 | ... AM60: =AM46*$B60*(1+inflation_vente)^2 -> 3145.6649 | AN60: =AN46*$B60*(1+inflation_vente)^3 -> 4860.0523 | AO60: =AO46*$B60*(1+inflation_vente)^3 -> 5265.0567 | AP60: =AP46*$B60*(1+inflation_vente)^3 -> 5670.0611 | AQ60: =AQ46*$B60*(1+inflation_vente)^3 -> 6075.0654 | AR60: =AR46*$B60*(1+inflation_vente)^3 -> 6480.0698 | AS60: =AS46*$B60*(1+inflation_vente)^3 -> 8910.096 | AT60: =AT46*$B60*(1+inflation_vente)^3 -> 9720.1047 | AU60: =AU46*$B60*(1+inflation_vente)^3 -> 8910.096 | ... AY60: =AY46*$B60*(1+inflation_vente)^3 -> 4050.0436
D61: =D47*$B61 -> 0 | E61: =E47*$B61 -> 0 | F61: =F47*$B61 -> 0 | G61: =G47*$B61 -> 0 | H61: =H47*$B61 -> 0 | I61: =I47*$B61 -> 0 | J61: =J47*$B61 -> 0 | K61: =K47*$B61 -> 0 | ... O61: =O47*$B61 -> 0 | P61: =P47*$B61*(1+inflation_vente) -> 0 | Q61: =Q47*$B61*(1+inflation_vente) -> 0 | R61: =R47*$B61*(1+inflation_vente) -> 0 | S61: =S47*$B61*(1+inflation_vente) -> 0 | T61: =T47*$B61*(1+inflation_vente) -> 0 | U61: =U47*$B61*(1+inflation_vente) -> 0 | V61: =V47*$B61*(1+inflation_vente) -> 0 | W61: =W47*$B61*(1+inflation_vente) -> 0 | ... AA61: =AA47*$B61*(1+inflation_vente) -> 0 | AB61: =AB47*$B61*(1+inflation_vente)^2 -> 0 | AC61: =AC47*$B61*(1+inflation_vente)^2 -> 0 | AD61: =AD47*$B61*(1+inflation_vente)^2 -> 0 | AE61: =AE47*$B61*(1+inflation_vente)^2 -> 0 | AF61: =AF47*$B61*(1+inflation_vente)^2 -> 0 | AG61: =AG47*$B61*(1+inflation_vente)^2 -> 0 | AH61: =AH47*$B61*(1+inflation_vente)^2 -> 0 | AI61: =AI47*$B61*(1+inflation_vente)^2 -> 0 | ... AM61: =AM47*$B61*(1+inflation_vente)^2 -> 0 | AN61: =AN47*$B61*(1+inflation_vente)^3 -> 0 | AO61: =AO47*$B61*(1+inflation_vente)^3 -> 0 | AP61: =AP47*$B61*(1+inflation_vente)^3 -> 0 | AQ61: =AQ47*$B61*(1+inflation_vente)^3 -> 0 | AR61: =AR47*$B61*(1+inflation_vente)^3 -> 0 | AS61: =AS47*$B61*(1+inflation_vente)^3 -> 0 | AT61: =AT47*$B61*(1+inflation_vente)^3 -> 0 | AU61: =AU47*$B61*(1+inflation_vente)^3 -> 0 | ... AY61: =AY47*$B61*(1+inflation_vente)^3 -> 0
D62: =SUM(D55:O55) -> 224858.77 | P62: =SUM(P55:AA55) -> 236699.67 | AB62: =SUM(AB55:AM55) -> 245532.77 | AN62: =SUM(AN55:AY55) -> 283117.92
H64: Démarrage | O64: =(P62-D62)/D62 -> 0.052659241 | T64: Stabilisation | AA64: =(AB62-P62)/P62 -> 0.037317763 | AF64: Déploiement | AM64: =(AN62-AB62)/AB62 -> 0.1530759 | AR64: Objectif
C67: Insights
F68: 2025 | H68: 2026 | J68: 2027 | L68: 2028
C69: CA Annuel | F69: =D62 -> 224858.77 | H69: =P62 -> 236699.67 | J69: =AB62 -> 245532.77 | L69: =AN62 -> 283117.92
C70: CA Mensuel moyen | F70: =F69/12 -> 18738.231 | H70: =H69/12 -> 19724.972 | J70: =J69/12 -> 20461.064 | L70: =L69/12 -> 23593.16
C71: CA journalier moyen | F71: =F70/24 -> 780.75963 | H71: =H70/24 -> 821.87384 | J71: =J70/24 -> 852.54433 | L71: =L70/24 -> 983.04832
C72: Nombre de clients annuel | F72: =SUM(D48:O48) -> 17365 | H72: =SUM(P48:AA48) -> 18079 | J72: =SUM(AB48:AM48) -> 18157 | L72: =SUM(AN48:AY48) -> 20326
C73: Nombre de clients moyen / jour | F73: =F72/Variables!$I$24 -> 60.295139 | H73: =H72/Variables!$I$24 -> 62.774306 | J73: =J72/Variables!$I$24 -> 63.045139 | L73: =L72/Variables!$I$24 -> 70.576389
C74: Panier Moyen | F74: =F69/F72 -> 12.948965 | H74: =H69/H72 -> 13.09252 | J74: =J69/J72 -> 13.522761 | L74: =L69/L72 -> 13.928855
B130: =UNIT_PRICE_CLIENT_A -> 5
B131: =UNIT_PRICE_CLIENT_B -> 9.1818182
B132: =UNIT_PRICE_CLIENT_C -> 12.727273
B133: =UNIT_PRICE_CLIENT_D -> 16.363636
B134: =UNIT_PRICE_CLIENT_E -> 20.590909
B135: =UNIT_PRICE_CLIENT_F -> 0
B144: panier moyen | C144: Produits | D144: 2024 | E144: 2025 | F144: 2026
A145: EPICERIE
B146: 8 | C146: Confiture maison-pate à tartiner | D146: 10 | E146: 25 | F146: 30
B147: 20 | C147: teeshirt-hoodie | D147: 0 | E147: 10 | F147: 30
B148: 15 | C148: mug | D148: 0 | E148: 0 | F148: 10
B149: 10 | C149: granola-café | D149: 10 | E149: 25 | F149: 30
B150: 30 | C150: Coffret occasionnel | D150: 0 | E150: 0 | F150: 5

Sheet Insights Livraison
A2: Restauration - Platefore de livraison
C3: Heure-Jour | D3: 2025 | K3: 2026 | R3: 2027
C4: % remplissage horaire | D4: 8h30-10h | E4: 10h-11h30 | F4: 11h30-13 | G4: 13h-14h30 | H4: 14h30-16h | I4: 16h-17h30 | K4: 8h30-10h | L4: 10h-11h30 | M4: 11h30-13 | N4: 13h-14h30 | O4: 14h30-16h | P4: 16h-17h30 | R4: 8h30-10h | S4: 10h-11h30 | T4: 11h30-13 | U4: 13h-14h30 | V4: 14h30-16h | W4: 16h-17h30
B5: 5.5 | C5: client A
B6: 10.1 | C6: client B | F6: 0.05 | H6: 0.3 | I6: 1 | M6: 0.05 | O6: 0.3 | P6: 1 | T6: 0.05 | V6: 0.3 | W6: 1
B7: 14 | C7: client C | F7: 0.05 | M7: 0.05 | T7: 0.05
B8: 18 | C8: client D | F8: 0.7 | G8: 0.8 | H8: 0.5 | M8: 0.7 | N8: 0.8 | O8: 0.5 | T8: 0.7 | U8: 0.8 | V8: 0.5
B9: 22.65 | C9: client E | F9: 0.2 | G9: 0.2 | H9: 0.2 | M9: 0.2 | N9: 0.2 | O9: 0.2 | T9: 0.2 | U9: 0.2 | V9: 0.2
D11: =SUM(D5:D10) -> 0 | E11: =SUM(E5:E10) -> 0 | F11: =SUM(F5:F10) -> 1 | G11: =SUM(G5:G10) -> 1 | H11: =SUM(H5:H10) -> 1 | I11: =SUM(I5:I10) -> 1 | K11: =SUM(K5:K10) -> 0 | L11: =SUM(L5:L10) -> 0 | M11: =SUM(M5:M10) -> 1 | N11: =SUM(N5:N10) -> 1 | O11: =SUM(O5:O10) -> 1 | P11: =SUM(P5:P10) -> 1 | R11: =SUM(R5:R10) -> 0 | S11: =SUM(S5:S10) -> 0 | T11: =SUM(T5:T10) -> 1 | U11: =SUM(U5:U10) -> 1 | V11: =SUM(V5:V10) -> 1 | W11: =SUM(W5:W10) -> 1
C14: Heure-Jour | D14: 2025 | K14: 2026 | R14: 2027
D15: 8h30-10h | E15: 10h-11h30 | F15: 11h30-13 | G15: 13h-14h30 | H15: 14h30-16h | I15: 16h-17h30 | K15: 8h30-10h | L15: 10h-11h30 | M15: 11h30-13 | N15: 13h-14h30 | O15: 14h30-16h | P15: 16h-17h30 | R15: 8h30-10h | S15: 10h-11h30 | T15: 11h30-13 | U15: 13h-14h30 | V15: 14h30-16h | W15: 16h-17h30
C16: Nombre de clients | F16: 10 | G16: 9 | H16: 9 | I16: 5 | M16: 12 | N16: 12 | O16: 10 | P16: 5 | T16: 13 | U16: 12 | V16: 10 | W16: 5
C17: client A | D17: =ROUND( D$16*D5,0) -> 0 | E17: =ROUND( E$16*E5,0) -> 0 | F17: =ROUND( F$16*F5,0) -> 0 | G17: =ROUND( G$16*G5,0) -> 0 | H17: =ROUND( H$16*H5,0) -> 0 | I17: =ROUND( I$16*I5,0) -> 0 | K17: =ROUND( K$16*K5,0) -> 0 | L17: =ROUND( L$16*L5,0) -> 0 | M17: =ROUND( M$16*M5,0) -> 0 | N17: =ROUND( N$16*N5,0) -> 0 | O17: =ROUND( O$16*O5,0) -> 0 | P17: =ROUND( P$16*P5,0) -> 0 | R17: =ROUND( R$16*R5,0) -> 0 | S17: =ROUND( S$16*S5,0) -> 0 | T17: =ROUND( T$16*T5,0) -> 0 | U17: =ROUND( U$16*U5,0) -> 0 | V17: =ROUND( V$16*V5,0) -> 0 | W17: =ROUND( W$16*W5,0) -> 0
C18: client B | D18: =ROUND( D$16*D6,0) -> 0 | E18: =ROUND( E$16*E6,0) -> 0 | F18: =ROUND( F$16*F6,0) -> 1 | G18: =ROUND( G$16*G6,0) -> 0 | H18: =ROUND( H$16*H6,0) -> 3 | I18: =ROUND( I$16*I6,0) -> 5 | K18: =ROUND( K$16*K6,0) -> 0 | L18: =ROUND( L$16*L6,0) -> 0 | M18: =ROUND( M$16*M6,0) -> 1 | N18: =ROUND( N$16*N6,0) -> 0 | O18: =ROUND( O$16*O6,0) -> 3 | P18: =ROUND( P$16*P6,0) -> 5 | R18: =ROUND( R$16*R6,0) -> 0 | S18: =ROUND( S$16*S6,0) -> 0 | T18: =ROUND( T$16*T6,0) -> 1 | U18: =ROUND( U$16*U6,0) -> 0 | V18: =ROUND( V$16*V6,0) -> 3 | W18: =ROUND( W$16*W6,0) -> 5
C19: client C | D19: =ROUND( D$16*D7,0) -> 0 | E19: =ROUND( E$16*E7,0) -> 0 | F19: =ROUND( F$16*F7,0) -> 1 | G19: =ROUND( G$16*G7,0) -> 0 | H19: =ROUND( H$16*H7,0) -> 0 | I19: =ROUND( I$16*I7,0) -> 0 | K19: =ROUND( K$16*K7,0) -> 0 | L19: =ROUND( L$16*L7,0) -> 0 | M19: =ROUND( M$16*M7,0) -> 1 | N19: =ROUND( N$16*N7,0) -> 0 | O19: =ROUND( O$16*O7,0) -> 0 | P19: =ROUND( P$16*P7,0) -> 0 | R19: =ROUND( R$16*R7,0) -> 0 | S19: =ROUND( S$16*S7,0) -> 0 | T19: =ROUND( T$16*T7,0) -> 1 | U19: =ROUND( U$16*U7,0) -> 0 | V19: =ROUND( V$16*V7,0) -> 0 | W19: =ROUND( W$16*W7,0) -> 0
C20: client D | D20: =ROUND( D$16*D8,0) -> 0 | E20: =ROUND( E$16*E8,0) -> 0 | F20: =ROUND( F$16*F8,0) -> 7 | G20: =ROUND( G$16*G8,0) -> 7 | H20: =ROUND( H$16*H8,0) -> 5 | I20: =ROUND( I$16*I8,0) -> 0 | K20: =ROUND( K$16*K8,0) -> 0 | L20: =ROUND( L$16*L8,0) -> 0 | M20: =ROUND( M$16*M8,0) -> 8 | N20: =ROUND( N$16*N8,0) -> 10 | O20: =ROUND( O$16*O8,0) -> 5 | P20: =ROUND( P$16*P8,0) -> 0 | R20: =ROUND( R$16*R8,0) -> 0 | S20: =ROUND( S$16*S8,0) -> 0 | T20: =ROUND( T$16*T8,0) -> 9 | U20: =ROUND( U$16*U8,0) -> 10 | V20: =ROUND( V$16*V8,0) -> 5 | W20: =ROUND( W$16*W8,0) -> 0
C21: client E | D21: =ROUND( D$16*D9,0) -> 0 | E21: =ROUND( E$16*E9,0) -> 0 | F21: =ROUND( F$16*F9,0) -> 2 | G21: =ROUND( G$16*G9,0) -> 2 | H21: =ROUND( H$16*H9,0) -> 2 | I21: =ROUND( I$16*I9,0) -> 0 | K21: =ROUND( K$16*K9,0) -> 0 | L21: =ROUND( L$16*L9,0) -> 0 | M21: =ROUND( M$16*M9,0) -> 2 | N21: =ROUND( N$16*N9,0) -> 2 | O21: =ROUND( O$16*O9,0) -> 2 | P21: =ROUND( P$16*P9,0) -> 0 | R21: =ROUND( R$16*R9,0) -> 0 | S21: =ROUND( S$16*S9,0) -> 0 | T21: =ROUND( T$16*T9,0) -> 3 | U21: =ROUND( U$16*U9,0) -> 2 | V21: =ROUND( V$16*V9,0) -> 2 | W21: =ROUND( W$16*W9,0) -> 0
D22: =ROUND( D$16*D10,0) -> 0 | E22: =ROUND( E$16*E10,0) -> 0 | F22: =ROUND( F$16*F10,0) -> 0 | G22: =ROUND( G$16*G10,0) -> 0 | H22: =ROUND( H$16*H10,0) -> 0 | I22: =ROUND( I$16*I10,0) -> 0 | K22: =ROUND( K$16*K10,0) -> 0 | L22: =ROUND( L$16*L10,0) -> 0 | M22: =ROUND( M$16*M10,0) -> 0 | N22: =ROUND( N$16*N10,0) -> 0 | O22: =ROUND( O$16*O10,0) -> 0 | P22: =ROUND( P$16*P10,0) -> 0 | R22: =ROUND( R$16*R10,0) -> 0 | S22: =ROUND( S$16*S10,0) -> 0 | T22: =ROUND( T$16*T10,0) -> 0 | U22: =ROUND( U$16*U10,0) -> 0 | V22: =ROUND( V$16*V10,0) -> 0 | W22: =ROUND( W$16*W10,0) -> 0
D23: =SUM(D17:D22) -> 0 | E23: =SUM(E17:E22) -> 0 | F23: =SUM(F17:F22) -> 11 | G23: =SUM(G17:G22) -> 9 | H23: =SUM(H17:H22) -> 10 | I23: =SUM(I17:I22) -> 5 | K23: =SUM(K17:K22) -> 0 | L23: =SUM(L17:L22) -> 0 | M23: =SUM(M17:M22) -> 12 | N23: =SUM(N17:N22) -> 12 | O23: =SUM(O17:O22) -> 10 | P23: =SUM(P17:P22) -> 5 | R23: =SUM(R17:R22) -> 0 | S23: =SUM(S17:S22) -> 0 | T23: =SUM(T17:T22) -> 14 | U23: =SUM(U17:U22) -> 12 | V23: =SUM(V17:V22) -> 10 | W23: =SUM(W17:W22) -> 5
D25: 2025 | AC25: 2026 | BB25: 2027
C26: jour/mois | D26: mardi | E26: mercredi | F26: jeudi | G26: vendredi | H26: samedi | I26: dimanche | J26: mardi | K26: mercredi | L26: jeudi | M26: vendredi | N26: samedi | O26: dimanche | P26: mardi | Q26: mercredi | R26: jeudi | S26: vendredi | T26: samedi | U26: dimanche | V26: mardi | W26: mercredi | X26: jeudi | Y26: vendredi | Z26: samedi | AA26: dimanche | AC26: mardi | AD26: mercredi | AE26: jeudi | AF26: vendredi | AG26: samedi | AH26: dimanche | AI26: mardi | AJ26: mercredi | AK26: jeudi | AL26: vendredi | AM26: samedi | AN26: dimanche | AO26: mardi | AP26: mercredi | AQ26: jeudi | AR26: vendredi | AS26: samedi | AT26: dimanche | AU26: mardi | AV26: mercredi | AW26: jeudi | AX26: vendredi | AY26: samedi | AZ26: dimanche | BB26: mardi | BC26: mercredi | BD26: jeudi | BE26: vendredi | BF26: samedi | BG26: dimanche | BH26: mardi | BI26: mercredi | BJ26: jeudi | BK26: vendredi | BL26: samedi | BM26: dimanche | BN26: mardi | BO26: mercredi | BP26: jeudi | BQ26: vendredi | BR26: samedi | BS26: dimanche | BT26: mardi | BU26: mercredi | BV26: jeudi | BW26: vendredi | BX26: samedi | BY26: dimanche
D27: 1 | E27: 2 | F27: 3 | G27: 4 | H27: 5 | I27: 6 | J27: 7 | K27: 8 | L27: 9 | M27: 10 | N27: 11 | O27: 12 | P27: 13 | Q27: 14 | R27: 15 | S27: 16 | T27: 17 | U27: 18 | V27: 19 | W27: 20 | X27: 21 | Y27: 22 | Z27: 23 | AA27: 24 | AC27: 1 | AD27: 2 | AE27: 3 | AF27: 4 | AG27: 5 | AH27: 6 | AI27: 7 | AJ27: 8 | AK27: 9 | AL27: 10 | AM27: 11 | AN27: 12 | AO27: 13 | AP27: 14 | AQ27: 15 | AR27: 16 | AS27: 17 | AT27: 18 | AU27: 19 | AV27: 20 | AW27: 21 | AX27: 22 | AY27: 23 | AZ27: 24 | BB27: 1 | BC27: 2 | BD27: 3 | BE27: 4 | BF27: 5 | BG27: 6 | BH27: 7 | BI27: 8 | BJ27: 9 | BK27: 10 | BL27: 11 | BM27: 12 | BN27: 13 | BO27: 14 | BP27: 15 | BQ27: 16 | BR27: 17 | BS27: 18 | BT27: 19 | BU27: 20 | BV27: 21 | BW27: 22 | BX27: 23 | BY27: 24
C28: % remplissage journalier | D28: 0.5 | E28: 0.5 | F28: 0.7 | G28: 0.7 | H28: 0.7 | I28: 0.7 | J28: 0.5 | K28: 0.5 | L28: 0.7 | M28: 0.7 | N28: 0.7 | O28: 0.7 | P28: 0.5 | Q28: 0.5 | R28: 0.7 | S28: 0.7 | T28: 0.7 | U28: 0.7 | V28: 0.5 | W28: 0.5 | X28: 0.7 | Y28: 0.7 | Z28: 0.7 | AA28: 0.7 | AC28: 0.4 | AD28: 0.4 | AE28: 0.4 | AF28: 0.5 | AG28: 0.5 | AH28: 0.5 | AI28: 0.4 | AJ28: 0.4 | AK28: 0.4 | AL28: 0.5 | AM28: 0.5 | AN28: 0.5 | AO28: 0.4 | AP28: 0.4 | AQ28: 0.4 | AR28: 0.5 | AS28: 0.5 | AT28: 0.5 | AU28: 0.4 | AV28: 0.4 | AW28: 0.4 | AX28: 0.5 | AY28: 0.5 | AZ28: 0.5 | BB28: 0.4 | BC28: 0.4 | BD28: 0.5 | BE28: 0.5 | BF28: 0.5 | BG28: 0.5 | BH28: 0.4 | BI28: 0.4 | BJ28: 0.4 | BK28: 0.5 | BL28: 0.5 | BM28: 0.5 | BN28: 0.4 | BO28: 0.4 | BP28: 0.4 | BQ28: 0.5 | BR28: 0.5 | BS28: 0.5 | BT28: 0.4 | BU28: 0.4 | BV28: 0.4 | BW28: 0.5 | BX28: 0.5 | BY28: 0.5
C29: client A | D29: =ROUND(SUM($D17:$I17)*D$28,0) -> 0 | E29: =ROUND(SUM($D17:$I17)*E$28,0) -> 0 | F29: =ROUND(SUM($D17:$I17)*F$28,0) -> 0 | G29: =ROUND(SUM($D17:$I17)*G$28,0) -> 0 | H29: =ROUND(SUM($D17:$I17)*H$28,0) -> 0 | I29: =ROUND(SUM($D17:$I17)*I$28,0) -> 0 | J29: =ROUND(SUM($D17:$I17)*J$28,0) -> 0 | K29: =ROUND(SUM($D17:$I17)*K$28,0) -> 0 | ... AA29: =ROUND(SUM($D17:$I17)*AA$28,0) -> 0 | AC29: =ROUND(SUM($K17:$P17)*AC$28,0) -> 0 | AD29: =ROUND(SUM($K17:$P17)*AD$28,0) -> 0 | AE29: =ROUND(SUM($K17:$P17)*AE$28,0) -> 0 | AF29: =ROUND(SUM($K17:$P17)*AF$28,0) -> 0 | AG29: =ROUND(SUM($K17:$P17)*AG$28,0) -> 0 | AH29: =ROUND(SUM($K17:$P17)*AH$28,0) -> 0 | AI29: =ROUND(SUM($K17:$P17)*AI$28,0) -> 0 | AJ29: =ROUND(SUM($K17:$P17)*AJ$28,0) -> 0 | ... AZ29: =ROUND(SUM($K17:$P17)*AZ$28,0) -> 0 | BB29: =ROUND(SUM($R17:$W17)*BB$28,0) -> 0 | BC29: =ROUND(SUM($R17:$W17)*BC$28,0) -> 0 | BD29: =ROUND(SUM($R17:$W17)*BD$28,0) -> 0 | BE29: =ROUND(SUM($R17:$W17)*BE$28,0) -> 0 | BF29: =ROUND(SUM($R17:$W17)*BF$28,0) -> 0 | BG29: =ROUND(SUM($R17:$W17)*BG$28,0) -> 0 | BH29: =ROUND(SUM($R17:$W17)*BH$28,0) -> 0 | BI29: =ROUND(SUM($R17:$W17)*BI$28,0) -> 0 | ... BY29: =ROUND(SUM($R17:$W17)*BY$28,0) -> 0
C30: client B | D30: =ROUND(SUM($D18:$I18)*D$28,0) -> 5 | E30: =ROUND(SUM($D18:$I18)*E$28,0) -> 5 | F30: =ROUND(SUM($D18:$I18)*F$28,0) -> 6 | G30: =ROUND(SUM($D18:$I18)*G$28,0) -> 6 | H30: =ROUND(SUM($D18:$I18)*H$28,0) -> 6 | I30: =ROUND(SUM($D18:$I18)*I$28,0) -> 6 | J30: =ROUND(SUM($D18:$I18)*J$28,0) -> 5 | K30: =ROUND(SUM($D18:$I18)*K$28,0) -> 5 | ... AA30: =ROUND(SUM($D18:$I18)*AA$28,0) -> 6 | AC30: =ROUND(SUM($K18:$P18)*AC$28,0) -> 4 | AD30: =ROUND(SUM($K18:$P18)*AD$28,0) -> 4 | AE30: =ROUND(SUM($K18:$P18)*AE$28,0) -> 4 | AF30: =ROUND(SUM($K18:$P18)*AF$28,0) -> 5 | AG30: =ROUND(SUM($K18:$P18)*AG$28,0) -> 5 | AH30: =ROUND(SUM($K18:$P18)*AH$28,0) -> 5 | AI30: =ROUND(SUM($K18:$P18)*AI$28,0) -> 4 | AJ30: =ROUND(SUM($K18:$P18)*AJ$28,0) -> 4 | ... AZ30: =ROUND(SUM($K18:$P18)*AZ$28,0) -> 5 | BB30: =ROUND(SUM($R18:$W18)*BB$28,0) -> 4 | BC30: =ROUND(SUM($R18:$W18)*BC$28,0) -> 4 | BD30: =ROUND(SUM($R18:$W18)*BD$28,0) -> 5 | BE30: =ROUND(SUM($R18:$W18)*BE$28,0) -> 5 | BF30: =ROUND(SUM($R18:$W18)*BF$28,0) -> 5 | BG30: =ROUND(SUM($R18:$W18)*BG$28,0) -> 5 | BH30: =ROUND(SUM($R18:$W18)*BH$28,0) -> 4 | BI30: =ROUND(SUM($R18:$W18)*BI$28,0) -> 4 | ... BY30: =ROUND(SUM($R18:$W18)*BY$28,0) -> 5
C31: client C | D31: =ROUND(SUM($D19:$I19)*D$28,0) -> 1 | E31: =ROUND(SUM($D19:$I19)*E$28,0) -> 1 | F31: =ROUND(SUM($D19:$I19)*F$28,0) -> 1 | G31: =ROUND(SUM($D19:$I19)*G$28,0) -> 1 | H31: =ROUND(SUM($D19:$I19)*H$28,0) -> 1 | I31: =ROUND(SUM($D19:$I19)*I$28,0) -> 1 | J31: =ROUND(SUM($D19:$I19)*J$28,0) -> 1 | K31: =ROUND(SUM($D19:$I19)*K$28,0) -> 1 | ... AA31: =ROUND(SUM($D19:$I19)*AA$28,0) -> 1 | AC31: =ROUND(SUM($K19:$P19)*AC$28,0) -> 0 | AD31: =ROUND(SUM($K19:$P19)*AD$28,0) -> 0 | AE31: =ROUND(SUM($K19:$P19)*AE$28,0) -> 0 | AF31: =ROUND(SUM($K19:$P19)*AF$28,0) -> 1 | AG31: =ROUND(SUM($K19:$P19)*AG$28,0) -> 1 | AH31: =ROUND(SUM($K19:$P19)*AH$28,0) -> 1 | AI31: =ROUND(SUM($K19:$P19)*AI$28,0) -> 0 | AJ31: =ROUND(SUM($K19:$P19)*AJ$28,0) -> 0 | ... AZ31: =ROUND(SUM($K19:$P19)*AZ$28,0) -> 1 | BB31: =ROUND(SUM($R19:$W19)*BB$28,0) -> 0 | BC31: =ROUND(SUM($R19:$W19)*BC$28,0) -> 0 | BD31: =ROUND(SUM($R19:$W19)*BD$28,0) -> 1 | BE31: =ROUND(SUM($R19:$W19)*BE$28,0) -> 1 | BF31: =ROUND(SUM($R19:$W19)*BF$28,0) -> 1 | BG31: =ROUND(SUM($R19:$W19)*BG$28,0) -> 1 | BH31: =ROUND(SUM($R19:$W19)*BH$28,0) -> 0 | BI31: =ROUND(SUM($R19:$W19)*BI$28,0) -> 0 | ... BY31: =ROUND(SUM($R19:$W19)*BY$28,0) -> 1
C32: client D | D32: =ROUND(SUM($D20:$I20)*D$28,0) -> 10 | E32: =ROUND(SUM($D20:$I20)*E$28,0) -> 10 | F32: =ROUND(SUM($D20:$I20)*F$28,0) -> 13 | G32: =ROUND(SUM($D20:$I20)*G$28,0) -> 13 | H32: =ROUND(SUM($D20:$I20)*H$28,0) -> 13 | I32: =ROUND(SUM($D20:$I20)*I$28,0) -> 13 | J32: =ROUND(SUM($D20:$I20)*J$28,0) -> 10 | K32: =ROUND(SUM($D20:$I20)*K$28,0) -> 10 | ... AA32: =ROUND(SUM($D20:$I20)*AA$28,0) -> 13 | AC32: =ROUND(SUM($K20:$P20)*AC$28,0) -> 9 | AD32: =ROUND(SUM($K20:$P20)*AD$28,0) -> 9 | AE32: =ROUND(SUM($K20:$P20)*AE$28,0) -> 9 | AF32: =ROUND(SUM($K20:$P20)*AF$28,0) -> 12 | AG32: =ROUND(SUM($K20:$P20)*AG$28,0) -> 12 | AH32: =ROUND(SUM($K20:$P20)*AH$28,0) -> 12 | AI32: =ROUND(SUM($K20:$P20)*AI$28,0) -> 9 | AJ32: =ROUND(SUM($K20:$P20)*AJ$28,0) -> 9 | ... AZ32: =ROUND(SUM($K20:$P20)*AZ$28,0) -> 12 | BB32: =ROUND(SUM($R20:$W20)*BB$28,0) -> 10 | BC32: =ROUND(SUM($R20:$W20)*BC$28,0) -> 10 | BD32: =ROUND(SUM($R20:$W20)*BD$28,0) -> 12 | BE32: =ROUND(SUM($R20:$W20)*BE$28,0) -> 12 | BF32: =ROUND(SUM($R20:$W20)*BF$28,0) -> 12 | BG32: =ROUND(SUM($R20:$W20)*BG$28,0) -> 12 | BH32: =ROUND(SUM($R20:$W20)*BH$28,0) -> 10 | BI32: =ROUND(SUM($R20:$W20)*BI$28,0) -> 10 | ... BY32: =ROUND(SUM($R20:$W20)*BY$28,0) -> 12
C33: client E | D33: =ROUND(SUM($D21:$I21)*D$28,0) -> 3 | E33: =ROUND(SUM($D21:$I21)*E$28,0) -> 3 | F33: =ROUND(SUM($D21:$I21)*F$28,0) -> 4 | G33: =ROUND(SUM($D21:$I21)*G$28,0) -> 4 | H33: =ROUND(SUM($D21:$I21)*H$28,0) -> 4 | I33: =ROUND(SUM($D21:$I21)*I$28,0) -> 4 | J33: =ROUND(SUM($D21:$I21)*J$28,0) -> 3 | K33: =ROUND(SUM($D21:$I21)*K$28,0) -> 3 | ... AA33: =ROUND(SUM($D21:$I21)*AA$28,0) -> 4 | AC33: =ROUND(SUM($K21:$P21)*AC$28,0) -> 2 | AD33: =ROUND(SUM($K21:$P21)*AD$28,0) -> 2 | AE33: =ROUND(SUM($K21:$P21)*AE$28,0) -> 2 | AF33: =ROUND(SUM($K21:$P21)*AF$28,0) -> 3 | AG33: =ROUND(SUM($K21:$P21)*AG$28,0) -> 3 | AH33: =ROUND(SUM($K21:$P21)*AH$28,0) -> 3 | AI33: =ROUND(SUM($K21:$P21)*AI$28,0) -> 2 | AJ33: =ROUND(SUM($K21:$P21)*AJ$28,0) -> 2 | ... AZ33: =ROUND(SUM($K21:$P21)*AZ$28,0) -> 3 | BB33: =ROUND(SUM($R21:$W21)*BB$28,0) -> 3 | BC33: =ROUND(SUM($R21:$W21)*BC$28,0) -> 3 | BD33: =ROUND(SUM($R21:$W21)*BD$28,0) -> 4 | BE33: =ROUND(SUM($R21:$W21)*BE$28,0) -> 4 | BF33: =ROUND(SUM($R21:$W21)*BF$28,0) -> 4 | BG33: =ROUND(SUM($R21:$W21)*BG$28,0) -> 4 | BH33: =ROUND(SUM($R21:$W21)*BH$28,0) -> 3 | BI33: =ROUND(SUM($R21:$W21)*BI$28,0) -> 3 | ... BY33: =ROUND(SUM($R21:$W21)*BY$28,0) -> 4
D34: =ROUND(SUM($D22:$I22)*D$28,0) -> 0 | E34: =ROUND(SUM($D22:$I22)*E$28,0) -> 0 | F34: =ROUND(SUM($D22:$I22)*F$28,0) -> 0 | G34: =ROUND(SUM($D22:$I22)*G$28,0) -> 0 | H34: =ROUND(SUM($D22:$I22)*H$28,0) -> 0 | I34: =ROUND(SUM($D22:$I22)*I$28,0) -> 0 | J34: =ROUND(SUM($D22:$I22)*J$28,0) -> 0 | K34: =ROUND(SUM($D22:$I22)*K$28,0) -> 0 | ... AA34: =ROUND(SUM($D22:$I22)*AA$28,0) -> 0 | AC34: =ROUND(SUM($K22:$P22)*AC$28,0) -> 0 | AD34: =ROUND(SUM($K22:$P22)*AD$28,0) -> 0 | AE34: =ROUND(SUM($K22:$P22)*AE$28,0) -> 0 | AF34: =ROUND(SUM($K22:$P22)*AF$28,0) -> 0 | AG34: =ROUND(SUM($K22:$P22)*AG$28,0) -> 0 | AH34: =ROUND(SUM($K22:$P22)*AH$28,0) -> 0 | AI34: =ROUND(SUM($K22:$P22)*AI$28,0) -> 0 | AJ34: =ROUND(SUM($K22:$P22)*AJ$28,0) -> 0 | ... AZ34: =ROUND(SUM($K22:$P22)*AZ$28,0) -> 0 | BB34: =ROUND(SUM($R22:$W22)*BB$28,0) -> 0 | BC34: =ROUND(SUM($R22:$W22)*BC$28,0) -> 0 | BD34: =ROUND(SUM($R22:$W22)*BD$28,0) -> 0 | BE34: =ROUND(SUM($R22:$W22)*BE$28,0) -> 0 | BF34: =ROUND(SUM($R22:$W22)*BF$28,0) -> 0 | BG34: =ROUND(SUM($R22:$W22)*BG$28,0) -> 0 | BH34: =ROUND(SUM($R22:$W22)*BH$28,0) -> 0 | BI34: =ROUND(SUM($R22:$W22)*BI$28,0) -> 0 | ... BY34: =ROUND(SUM($R22:$W22)*BY$28,0) -> 0
D35: =SUM(D29:D34) -> 19 | E35: =SUM(E29:E34) -> 19 | F35: =SUM(F29:F34) -> 24 | G35: =SUM(G29:G34) -> 24 | H35: =SUM(H29:H34) -> 24 | I35: =SUM(I29:I34) -> 24 | J35: =SUM(J29:J34) -> 19 | K35: =SUM(K29:K34) -> 19 | ... AA35: =SUM(AA29:AA34) -> 24 | AC35: =SUM(AC29:AC34) -> 15 | AD35: =SUM(AD29:AD34) -> 15 | AE35: =SUM(AE29:AE34) -> 15 | AF35: =SUM(AF29:AF34) -> 21 | AG35: =SUM(AG29:AG34) -> 21 | AH35: =SUM(AH29:AH34) -> 21 | AI35: =SUM(AI29:AI34) -> 15 | AJ35: =SUM(AJ29:AJ34) -> 15 | ... AZ35: =SUM(AZ29:AZ34) -> 21 | BB35: =SUM(BB29:BB34) -> 17 | BC35: =SUM(BC29:BC34) -> 17 | BD35: =SUM(BD29:BD34) -> 22 | BE35: =SUM(BE29:BE34) -> 22 | BF35: =SUM(BF29:BF34) -> 22 | BG35: =SUM(BG29:BG34) -> 22 | BH35: =SUM(BH29:BH34) -> 17 | BI35: =SUM(BI29:BI34) -> 17 | ... BY35: =SUM(BY29:BY34) -> 22
C38: Evolution des mois
D39: 2025 | P39: 2026 | AB39: 2027 | AN39: 2028
C40: Mois | D40: 1 | E40: 2 | F40: 3 | G40: 4 | H40: 5 | I40: 6 | J40: 7 | K40: 8 | L40: 9 | M40: 10 | N40: 11 | O40: 12 | P40: 1 | Q40: 2 | R40: 3 | S40: 4 | T40: 5 | U40: 6 | V40: 7 | W40: 8 | X40: 9 | Y40: 10 | Z40: 11 | AA40: 12 | AB40: 1 | AC40: 2 | AD40: 3 | AE40: 4 | AF40: 5 | AG40: 6 | AH40: 7 | AI40: 8 | AJ40: 9 | AK40: 10 | AL40: 11 | AM40: 12 | AN40: 1 | AO40: 2 | AP40: 3 | AQ40: 4 | AR40: 5 | AS40: 6 | AT40: 7 | AU40: 8 | AV40: 9 | AW40: 10 | AX40: 11 | AY40: 12
C41: % remplissage mensuel | D41: 0 | E41: 0 | F41: 0 | G41: 0.4 | H41: 0.6 | I41: 0.6 | J41: 0.7 | K41: 0.7 | L41: 0.7 | M41: 0.7 | N41: 0.5 | O41: 0.3 | P41: 0.5 | Q41: 0.5 | R41: 0.5 | S41: 0.5 | T41: 0.6 | U41: 0.6 | V41: 0.6 | W41: 0.6 | X41: 0.7 | Y41: 0.5 | Z41: 0.6 | AA41: 0.5 | AB41: 0.4 | AC41: 0.4 | AD41: 0.4 | AE41: 0.5 | AF41: 0.6 | AG41: 0.6 | AH41: 0.6 | AI41: 0.6 | AJ41: 0.7 | AK41: 0.5 | AL41: 0.6 | AM41: 0.5 | AN41: 0.6 | AO41: 0.6 | AP41: 0.6 | AQ41: 0.6 | AR41: 0.6 | AS41: 0.6 | AT41: 0.6 | AU41: 0.7 | AV41: 0.7 | AW41: 0.5 | AX41: 0.3 | AY41: 0.3
C42: client A | D42: =ROUND(SUM($D29:$AA29)*D$41,0) -> 0 | E42: =ROUND(SUM($D29:$AA29)*E$41,0) -> 0 | F42: =ROUND(SUM($D29:$AA29)*F$41,0) -> 0 | G42: =ROUND(SUM($D29:$AA29)*G$41,0) -> 0 | H42: =ROUND(SUM($D29:$AA29)*H$41,0) -> 0 | I42: =ROUND(SUM($D29:$AA29)*I$41,0) -> 0 | J42: =ROUND(SUM($D29:$AA29)*J$41,0) -> 0 | K42: =ROUND(SUM($D29:$AA29)*K$41,0) -> 0 | ... O42: =ROUND(SUM($D29:$AA29)*O$41,0) -> 0 | P42: =ROUND(SUM($AC29:$AZ29)*P$41,0) -> 0 | Q42: =ROUND(SUM($AC29:$AZ29)*Q$41,0) -> 0 | R42: =ROUND(SUM($AC29:$AZ29)*R$41,0) -> 0 | S42: =ROUND(SUM($AC29:$AZ29)*S$41,0) -> 0 | T42: =ROUND(SUM($AC29:$AZ29)*T$41,0) -> 0 | U42: =ROUND(SUM($AC29:$AZ29)*U$41,0) -> 0 | V42: =ROUND(SUM($AC29:$AZ29)*V$41,0) -> 0 | W42: =ROUND(SUM($AC29:$AZ29)*W$41,0) -> 0 | ... AA42: =ROUND(SUM($AC29:$AZ29)*AA$41,0) -> 0 | AB42: =ROUND(SUM($BB29:$BY29)*AB$41,0) -> 0 | AC42: =ROUND(SUM($BB29:$BY29)*AC$41,0) -> 0 | AD42: =ROUND(SUM($BB29:$BY29)*AD$41,0) -> 0 | AE42: =ROUND(SUM($BB29:$BY29)*AE$41,0) -> 0 | AF42: =ROUND(SUM($BB29:$BY29)*AF$41,0) -> 0 | AG42: =ROUND(SUM($BB29:$BY29)*AG$41,0) -> 0 | AH42: =ROUND(SUM($BB29:$BY29)*AH$41,0) -> 0 | AI42: =ROUND(SUM($BB29:$BY29)*AI$41,0) -> 0 | ... AY42: =ROUND(SUM($BB29:$BY29)*AY$41,0) -> 0
C43: client B | D43: =ROUND(SUM($D30:$AA30)*D$41,0) -> 0 | E43: =ROUND(SUM($D30:$AA30)*E$41,0) -> 0 | F43: =ROUND(SUM($D30:$AA30)*F$41,0) -> 0 | G43: =ROUND(SUM($D30:$AA30)*G$41,0) -> 54 | H43: =ROUND(SUM($D30:$AA30)*H$41,0) -> 82 | I43: =ROUND(SUM($D30:$AA30)*I$41,0) -> 82 | J43: =ROUND(SUM($D30:$AA30)*J$41,0) -> 95 | K43: =ROUND(SUM($D30:$AA30)*K$41,0) -> 95 | ... O43: =ROUND(SUM($D30:$AA30)*O$41,0) -> 41 | P43: =ROUND(SUM($AC30:$AZ30)*P$41,0) -> 54 | Q43: =ROUND(SUM($AC30:$AZ30)*Q$41,0) -> 54 | R43: =ROUND(SUM($AC30:$AZ30)*R$41,0) -> 54 | S43: =ROUND(SUM($AC30:$AZ30)*S$41,0) -> 54 | T43: =ROUND(SUM($AC30:$AZ30)*T$41,0) -> 65 | U43: =ROUND(SUM($AC30:$AZ30)*U$41,0) -> 65 | V43: =ROUND(SUM($AC30:$AZ30)*V$41,0) -> 65 | W43: =ROUND(SUM($AC30:$AZ30)*W$41,0) -> 65 | ... AA43: =ROUND(SUM($AC30:$AZ30)*AA$41,0) -> 54 | AB43: =ROUND(SUM($BB30:$BY30)*AB$41,0) -> 44 | AC43: =ROUND(SUM($BB30:$BY30)*AC$41,0) -> 44 | AD43: =ROUND(SUM($BB30:$BY30)*AD$41,0) -> 44 | AE43: =ROUND(SUM($BB30:$BY30)*AE$41,0) -> 55 | AF43: =ROUND(SUM($BB30:$BY30)*AF$41,0) -> 65 | AG43: =ROUND(SUM($BB30:$BY30)*AG$41,0) -> 65 | AH43: =ROUND(SUM($BB30:$BY30)*AH$41,0) -> 65 | AI43: =ROUND(SUM($BB30:$BY30)*AI$41,0) -> 65 | ... AY43: =ROUND(SUM($BB30:$BY30)*AY$41,0) -> 33
C44: client C | D44: =ROUND(SUM($D31:$AA31)*D$41,0) -> 0 | E44: =ROUND(SUM($D31:$AA31)*E$41,0) -> 0 | F44: =ROUND(SUM($D31:$AA31)*F$41,0) -> 0 | G44: =ROUND(SUM($D31:$AA31)*G$41,0) -> 10 | H44: =ROUND(SUM($D31:$AA31)*H$41,0) -> 14 | I44: =ROUND(SUM($D31:$AA31)*I$41,0) -> 14 | J44: =ROUND(SUM($D31:$AA31)*J$41,0) -> 17 | K44: =ROUND(SUM($D31:$AA31)*K$41,0) -> 17 | ... O44: =ROUND(SUM($D31:$AA31)*O$41,0) -> 7 | P44: =ROUND(SUM($AC31:$AZ31)*P$41,0) -> 6 | Q44: =ROUND(SUM($AC31:$AZ31)*Q$41,0) -> 6 | R44: =ROUND(SUM($AC31:$AZ31)*R$41,0) -> 6 | S44: =ROUND(SUM($AC31:$AZ31)*S$41,0) -> 6 | T44: =ROUND(SUM($AC31:$AZ31)*T$41,0) -> 7 | U44: =ROUND(SUM($AC31:$AZ31)*U$41,0) -> 7 | V44: =ROUND(SUM($AC31:$AZ31)*V$41,0) -> 7 | W44: =ROUND(SUM($AC31:$AZ31)*W$41,0) -> 7 | ... AA44: =ROUND(SUM($AC31:$AZ31)*AA$41,0) -> 6 | AB44: =ROUND(SUM($BB31:$BY31)*AB$41,0) -> 5 | AC44: =ROUND(SUM($BB31:$BY31)*AC$41,0) -> 5 | AD44: =ROUND(SUM($BB31:$BY31)*AD$41,0) -> 5 | AE44: =ROUND(SUM($BB31:$BY31)*AE$41,0) -> 7 | AF44: =ROUND(SUM($BB31:$BY31)*AF$41,0) -> 8 | AG44: =ROUND(SUM($BB31:$BY31)*AG$41,0) -> 8 | AH44: =ROUND(SUM($BB31:$BY31)*AH$41,0) -> 8 | AI44: =ROUND(SUM($BB31:$BY31)*AI$41,0) -> 8 | ... AY44: =ROUND(SUM($BB31:$BY31)*AY$41,0) -> 4
C45: client D | D45: =ROUND(SUM($D32:$AA32)*D$41,0) -> 0 | E45: =ROUND(SUM($D32:$AA32)*E$41,0) -> 0 | F45: =ROUND(SUM($D32:$AA32)*F$41,0) -> 0 | G45: =ROUND(SUM($D32:$AA32)*G$41,0) -> 115 | H45: =ROUND(SUM($D32:$AA32)*H$41,0) -> 173 | I45: =ROUND(SUM($D32:$AA32)*I$41,0) -> 173 | J45: =ROUND(SUM($D32:$AA32)*J$41,0) -> 202 | K45: =ROUND(SUM($D32:$AA32)*K$41,0) -> 202 | ... O45: =ROUND(SUM($D32:$AA32)*O$41,0) -> 86 | P45: =ROUND(SUM($AC32:$AZ32)*P$41,0) -> 126 | Q45: =ROUND(SUM($AC32:$AZ32)*Q$41,0) -> 126 | R45: =ROUND(SUM($AC32:$AZ32)*R$41,0) -> 126 | S45: =ROUND(SUM($AC32:$AZ32)*S$41,0) -> 126 | T45: =ROUND(SUM($AC32:$AZ32)*T$41,0) -> 151 | U45: =ROUND(SUM($AC32:$AZ32)*U$41,0) -> 151 | V45: =ROUND(SUM($AC32:$AZ32)*V$41,0) -> 151 | W45: =ROUND(SUM($AC32:$AZ32)*W$41,0) -> 151 | ... AA45: =ROUND(SUM($AC32:$AZ32)*AA$41,0) -> 126 | AB45: =ROUND(SUM($BB32:$BY32)*AB$41,0) -> 106 | AC45: =ROUND(SUM($BB32:$BY32)*AC$41,0) -> 106 | AD45: =ROUND(SUM($BB32:$BY32)*AD$41,0) -> 106 | AE45: =ROUND(SUM($BB32:$BY32)*AE$41,0) -> 133 | AF45: =ROUND(SUM($BB32:$BY32)*AF$41,0) -> 160 | AG45: =ROUND(SUM($BB32:$BY32)*AG$41,0) -> 160 | AH45: =ROUND(SUM($BB32:$BY32)*AH$41,0) -> 160 | AI45: =ROUND(SUM($BB32:$BY32)*AI$41,0) -> 160 | ... AY45: =ROUND(SUM($BB32:$BY32)*AY$41,0) -> 80
C46: client E | D46: =ROUND(SUM($D33:$AA33)*D$41,0) -> 0 | E46: =ROUND(SUM($D33:$AA33)*E$41,0) -> 0 | F46: =ROUND(SUM($D33:$AA33)*F$41,0) -> 0 | G46: =ROUND(SUM($D33:$AA33)*G$41,0) -> 35 | H46: =ROUND(SUM($D33:$AA33)*H$41,0) -> 53 | I46: =ROUND(SUM($D33:$AA33)*I$41,0) -> 53 | J46: =ROUND(SUM($D33:$AA33)*J$41,0) -> 62 | K46: =ROUND(SUM($D33:$AA33)*K$41,0) -> 62 | ... O46: =ROUND(SUM($D33:$AA33)*O$41,0) -> 26 | P46: =ROUND(SUM($AC33:$AZ33)*P$41,0) -> 30 | Q46: =ROUND(SUM($AC33:$AZ33)*Q$41,0) -> 30 | R46: =ROUND(SUM($AC33:$AZ33)*R$41,0) -> 30 | S46: =ROUND(SUM($AC33:$AZ33)*S$41,0) -> 30 | T46: =ROUND(SUM($AC33:$AZ33)*T$41,0) -> 36 | U46: =ROUND(SUM($AC33:$AZ33)*U$41,0) -> 36 | V46: =ROUND(SUM($AC33:$AZ33)*V$41,0) -> 36 | W46: =ROUND(SUM($AC33:$AZ33)*W$41,0) -> 36 | ... AA46: =ROUND(SUM($AC33:$AZ33)*AA$41,0) -> 30 | AB46: =ROUND(SUM($BB33:$BY33)*AB$41,0) -> 34 | AC46: =ROUND(SUM($BB33:$BY33)*AC$41,0) -> 34 | AD46: =ROUND(SUM($BB33:$BY33)*AD$41,0) -> 34 | AE46: =ROUND(SUM($BB33:$BY33)*AE$41,0) -> 43 | AF46: =ROUND(SUM($BB33:$BY33)*AF$41,0) -> 51 | AG46: =ROUND(SUM($BB33:$BY33)*AG$41,0) -> 51 | AH46: =ROUND(SUM($BB33:$BY33)*AH$41,0) -> 51 | AI46: =ROUND(SUM($BB33:$BY33)*AI$41,0) -> 51 | ... AY46: =ROUND(SUM($BB33:$BY33)*AY$41,0) -> 26
D47: =ROUND(SUM($D34:$AA34)*D$41,0) -> 0 | E47: =ROUND(SUM($D34:$AA34)*E$41,0) -> 0 | F47: =ROUND(SUM($D34:$AA34)*F$41,0) -> 0 | G47: =ROUND(SUM($D34:$AA34)*G$41,0) -> 0 | H47: =ROUND(SUM($D34:$AA34)*H$41,0) -> 0 | I47: =ROUND(SUM($D34:$AA34)*I$41,0) -> 0 | J47: =ROUND(SUM($D34:$AA34)*J$41,0) -> 0 | K47: =ROUND(SUM($D34:$AA34)*K$41,0) -> 0 | ... O47: =ROUND(SUM($D34:$AA34)*O$41,0) -> 0 | P47: =ROUND(SUM($AC34:$AZ34)*P$41,0) -> 0 | Q47: =ROUND(SUM($AC34:$AZ34)*Q$41,0) -> 0 | R47: =ROUND(SUM($AC34:$AZ34)*R$41,0) -> 0 | S47: =ROUND(SUM($AC34:$AZ34)*S$41,0) -> 0 | T47: =ROUND(SUM($AC34:$AZ34)*T$41,0) -> 0 | U47: =ROUND(SUM($AC34:$AZ34)*U$41,0) -> 0 | V47: =ROUND(SUM($AC34:$AZ34)*V$41,0) -> 0 | W47: =ROUND(SUM($AC34:$AZ34)*W$41,0) -> 0 | ... AA47: =ROUND(SUM($AC34:$AZ34)*AA$41,0) -> 0 | AB47: =ROUND(SUM($BB34:$BY34)*AB$41,0) -> 0 | AC47: =ROUND(SUM($BB34:$BY34)*AC$41,0) -> 0 | AD47: =ROUND(SUM($BB34:$BY34)*AD$41,0) -> 0 | AE47: =ROUND(SUM($BB34:$BY34)*AE$41,0) -> 0 | AF47: =ROUND(SUM($BB34:$BY34)*AF$41,0) -> 0 | AG47: =ROUND(SUM($BB34:$BY34)*AG$41,0) -> 0 | AH47: =ROUND(SUM($BB34:$BY34)*AH$41,0) -> 0 | AI47: =ROUND(SUM($BB34:$BY34)*AI$41,0) -> 0 | ... AY47: =ROUND(SUM($BB34:$BY34)*AY$41,0) -> 0
C48: Nombre de client mensuel | D48: =SUM(D42:D47) -> 0 | E48: =SUM(E42:E47) -> 0 | F48: =SUM(F42:F47) -> 0 | G48: =SUM(G42:G47) -> 214 | H48: =SUM(H42:H47) -> 322 | I48: =SUM(I42:I47) -> 322 | J48: =SUM(J42:J47) -> 376 | K48: =SUM(K42:K47) -> 376 | ... AY48: =SUM(AY42:AY47) -> 143
C49: clients moyen / jour | D49: =D48/24 -> 0 | E49: =E48/24 -> 0 | F49: =F48/24 -> 0 | G49: =G48/24 -> 8.9166667 | H49: =H48/24 -> 13.416667 | I49: =I48/24 -> 13.416667 | J49: =J48/24 -> 15.666667 | K49: =K48/24 -> 15.666667 | ... AY49: =AY48/24 -> 5.9583333
C51: CA jour/mois
D52: 2025 | P52: 2026 | AB52: 2027 | AN52: 2028
C53: Mois | D53: 1 | E53: 2 | F53: 3 | G53: 4 | H53: 5 | I53: 6 | J53: 7 | K53: 8 | L53: 9 | M53: 10 | N53: 11 | O53: 12 | P53: 1 | Q53: 2 | R53: 3 | S53: 4 | T53: 5 | U53: 6 | V53: 7 | W53: 8 | X53: 9 | Y53: 10 | Z53: 11 | AA53: 12 | AB53: 1 | AC53: 2 | AD53: 3 | AE53: 4 | AF53: 5 | AG53: 6 | AH53: 7 | AI53: 8 | AJ53: 9 | AK53: 10 | AL53: 11 | AM53: 12 | AN53: 1 | AO53: 2 | AP53: 3 | AQ53: 4 | AR53: 5 | AS53: 6 | AT53: 7 | AU53: 8 | AV53: 9 | AW53: 10 | AX53: 11 | AY53: 12
C54: CA moyen journalier | D54: =D55/24 -> 0 | E54: =E55/24 -> 0 | F54: =F55/24 -> 0 | G54: =G55/24 -> 147.83958 | H54: =H55/24 -> 222.44375 | I54: =I55/24 -> 222.44375 | J54: =J55/24 -> 259.90833 | K54: =K55/24 -> 259.90833 | ... AY54: =AY55/24 -> 110.10135
C55: CA mensuel | D55: =SUM(D56:D61) -> 0 | E55: =SUM(E56:E61) -> 0 | F55: =SUM(F56:F61) -> 0 | G55: =SUM(G56:G61) -> 3548.15 | H55: =SUM(H56:H61) -> 5338.65 | I55: =SUM(I56:I61) -> 5338.65 | J55: =SUM(J56:J61) -> 6237.8 | K55: =SUM(K56:K61) -> 6237.8 | ... AY55: =SUM(AY56:AY61) -> 2642.4324
B56: 5.5 | C56: client A | D56: =D42*$B56 -> 0 | E56: =E42*$B56 -> 0 | F56: =F42*$B56 -> 0 | G56: =G42*$B56 -> 0 | H56: =H42*$B56 -> 0 | I56: =I42*$B56 -> 0 | J56: =J42*$B56 -> 0 | K56: =K42*$B56 -> 0 | ... O56: =O42*$B56 -> 0 | P56: =P42*$B56*(1+inflation_vente) -> 0 | Q56: =Q42*$B56*(1+inflation_vente) -> 0 | R56: =R42*$B56*(1+inflation_vente) -> 0 | S56: =S42*$B56*(1+inflation_vente) -> 0 | T56: =T42*$B56*(1+inflation_vente) -> 0 | U56: =U42*$B56*(1+inflation_vente) -> 0 | V56: =V42*$B56*(1+inflation_vente) -> 0 | W56: =W42*$B56*(1+inflation_vente) -> 0 | ... AA56: =AA42*$B56*(1+inflation_vente) -> 0 | AB56: =AB42*$B56*(1+inflation_vente)^2 -> 0 | AC56: =AC42*$B56*(1+inflation_vente)^2 -> 0 | AD56: =AD42*$B56*(1+inflation_vente)^2 -> 0 | AE56: =AE42*$B56*(1+inflation_vente)^2 -> 0 | AF56: =AF42*$B56*(1+inflation_vente)^2 -> 0 | AG56: =AG42*$B56*(1+inflation_vente)^2 -> 0 | AH56: =AH42*$B56*(1+inflation_vente)^2 -> 0 | AI56: =AI42*$B56*(1+inflation_vente)^2 -> 0 | ... AM56: =AM42*$B56*(1+inflation_vente)^2 -> 0 | AN56: =AN42*$B56*(1+inflation_vente)^3 -> 0 | AO56: =AO42*$B56*(1+inflation_vente)^3 -> 0 | AP56: =AP42*$B56*(1+inflation_vente)^3 -> 0 | AQ56: =AQ42*$B56*(1+inflation_vente)^3 -> 0 | AR56: =AR42*$B56*(1+inflation_vente)^3 -> 0 | AS56: =AS42*$B56*(1+inflation_vente)^3 -> 0 | AT56: =AT42*$B56*(1+inflation_vente)^3 -> 0 | AU56: =AU42*$B56*(1+inflation_vente)^3 -> 0 | ... AY56: =AY42*$B56*(1+inflation_vente)^3 -> 0
B57: 10.1 | C57: client B | D57: =D43*$B57 -> 0 | E57: =E43*$B57 -> 0 | F57: =F43*$B57 -> 0 | G57: =G43*$B57 -> 545.4 | H57: =H43*$B57 -> 828.2 | I57: =I43*$B57 -> 828.2 | J57: =J43*$B57 -> 959.5 | K57: =K43*$B57 -> 959.5 | ... O57: =O43*$B57 -> 414.1 | P57: =P43*$B57*(1+inflation_vente) -> 561.762 | Q57: =Q43*$B57*(1+inflation_vente) -> 561.762 | R57: =R43*$B57*(1+inflation_vente) -> 561.762 | S57: =S43*$B57*(1+inflation_vente) -> 561.762 | T57: =T43*$B57*(1+inflation_vente) -> 676.195 | U57: =U43*$B57*(1+inflation_vente) -> 676.195 | V57: =V43*$B57*(1+inflation_vente) -> 676.195 | W57: =W43*$B57*(1+inflation_vente) -> 676.195 | ... AA57: =AA43*$B57*(1+inflation_vente) -> 561.762 | AB57: =AB43*$B57*(1+inflation_vente)^2 -> 471.46396 | AC57: =AC43*$B57*(1+inflation_vente)^2 -> 471.46396 | AD57: =AD43*$B57*(1+inflation_vente)^2 -> 471.46396 | AE57: =AE43*$B57*(1+inflation_vente)^2 -> 589.32995 | AF57: =AF43*$B57*(1+inflation_vente)^2 -> 696.48085 | AG57: =AG43*$B57*(1+inflation_vente)^2 -> 696.48085 | AH57: =AH43*$B57*(1+inflation_vente)^2 -> 696.48085 | AI57: =AI43*$B57*(1+inflation_vente)^2 -> 696.48085 | ... AM57: =AM43*$B57*(1+inflation_vente)^2 -> 589.32995 | AN57: =AN43*$B57*(1+inflation_vente)^3 -> 717.37528 | AO57: =AO43*$B57*(1+inflation_vente)^3 -> 717.37528 | AP57: =AP43*$B57*(1+inflation_vente)^3 -> 717.37528 | AQ57: =AQ43*$B57*(1+inflation_vente)^3 -> 717.37528 | AR57: =AR43*$B57*(1+inflation_vente)^3 -> 717.37528 | AS57: =AS43*$B57*(1+inflation_vente)^3 -> 717.37528 | AT57: =AT43*$B57*(1+inflation_vente)^3 -> 717.37528 | AU57: =AU43*$B57*(1+inflation_vente)^3 -> 838.77725 | ... AY57: =AY43*$B57*(1+inflation_vente)^3 -> 364.20591
B58: 14 | C58: client C | D58: =D44*$B58 -> 0 | E58: =E44*$B58 -> 0 | F58: =F44*$B58 -> 0 | G58: =G44*$B58 -> 140 | H58: =H44*$B58 -> 196 | I58: =I44*$B58 -> 196 | J58: =J44*$B58 -> 238 | K58: =K44*$B58 -> 238 | ... O58: =O44*$B58 -> 98 | P58: =P44*$B58*(1+inflation_vente) -> 86.52 | Q58: =Q44*$B58*(1+inflation_vente) -> 86.52 | R58: =R44*$B58*(1+inflation_vente) -> 86.52 | S58: =S44*$B58*(1+inflation_vente) -> 86.52 | T58: =T44*$B58*(1+inflation_vente) -> 100.94 | U58: =U44*$B58*(1+inflation_vente) -> 100.94 | V58: =V44*$B58*(1+inflation_vente) -> 100.94 | W58: =W44*$B58*(1+inflation_vente) -> 100.94 | ... AA58: =AA44*$B58*(1+inflation_vente) -> 86.52 | AB58: =AB44*$B58*(1+inflation_vente)^2 -> 74.263 | AC58: =AC44*$B58*(1+inflation_vente)^2 -> 74.263 | AD58: =AD44*$B58*(1+inflation_vente)^2 -> 74.263 | AE58: =AE44*$B58*(1+inflation_vente)^2 -> 103.9682 | AF58: =AF44*$B58*(1+inflation_vente)^2 -> 118.8208 | AG58: =AG44*$B58*(1+inflation_vente)^2 -> 118.8208 | AH58: =AH44*$B58*(1+inflation_vente)^2 -> 118.8208 | AI58: =AI44*$B58*(1+inflation_vente)^2 -> 118.8208 | ... AM58: =AM44*$B58*(1+inflation_vente)^2 -> 103.9682 | AN58: =AN44*$B58*(1+inflation_vente)^3 -> 122.38542 | AO58: =AO44*$B58*(1+inflation_vente)^3 -> 122.38542 | AP58: =AP44*$B58*(1+inflation_vente)^3 -> 122.38542 | AQ58: =AQ44*$B58*(1+inflation_vente)^3 -> 122.38542 | AR58: =AR44*$B58*(1+inflation_vente)^3 -> 122.38542 | AS58: =AS44*$B58*(1+inflation_vente)^3 -> 122.38542 | AT58: =AT44*$B58*(1+inflation_vente)^3 -> 122.38542 | AU58: =AU44*$B58*(1+inflation_vente)^3 -> 137.6836 | ... AY58: =AY44*$B58*(1+inflation_vente)^3 -> 61.192712
B59: 18 | C59: client D | D59: =D45*$B59 -> 0 | E59: =E45*$B59 -> 0 | F59: =F45*$B59 -> 0 | G59: =G45*$B59 -> 2070 | H59: =H45*$B59 -> 3114 | I59: =I45*$B59 -> 3114 | J59: =J45*$B59 -> 3636 | K59: =K45*$B59 -> 3636 | ... O59: =O45*$B59 -> 1548 | P59: =P45*$B59*(1+inflation_vente) -> 2336.04 | Q59: =Q45*$B59*(1+inflation_vente) -> 2336.04 | R59: =R45*$B59*(1+inflation_vente) -> 2336.04 | S59: =S45*$B59*(1+inflation_vente) -> 2336.04 | T59: =T45*$B59*(1+inflation_vente) -> 2799.54 | U59: =U45*$B59*(1+inflation_vente) -> 2799.54 | V59: =V45*$B59*(1+inflation_vente) -> 2799.54 | W59: =W45*$B59*(1+inflation_vente) -> 2799.54 | ... AA59: =AA45*$B59*(1+inflation_vente) -> 2336.04 | AB59: =AB45*$B59*(1+inflation_vente)^2 -> 2024.1972 | AC59: =AC45*$B59*(1+inflation_vente)^2 -> 2024.1972 | AD59: =AD45*$B59*(1+inflation_vente)^2 -> 2024.1972 | AE59: =AE45*$B59*(1+inflation_vente)^2 -> 2539.7946 | AF59: =AF45*$B59*(1+inflation_vente)^2 -> 3055.392 | AG59: =AG45*$B59*(1+inflation_vente)^2 -> 3055.392 | AH59: =AH45*$B59*(1+inflation_vente)^2 -> 3055.392 | AI59: =AI45*$B59*(1+inflation_vente)^2 -> 3055.392 | ... AM59: =AM45*$B59*(1+inflation_vente)^2 -> 2539.7946 | AN59: =AN45*$B59*(1+inflation_vente)^3 -> 3147.0538 | AO59: =AO45*$B59*(1+inflation_vente)^3 -> 3147.0538 | AP59: =AP45*$B59*(1+inflation_vente)^3 -> 3147.0538 | AQ59: =AQ45*$B59*(1+inflation_vente)^3 -> 3147.0538 | AR59: =AR45*$B59*(1+inflation_vente)^3 -> 3147.0538 | AS59: =AS45*$B59*(1+inflation_vente)^3 -> 3147.0538 | AT59: =AT45*$B59*(1+inflation_vente)^3 -> 3147.0538 | AU59: =AU45*$B59*(1+inflation_vente)^3 -> 3658.45 | ... AY59: =AY45*$B59*(1+inflation_vente)^3 -> 1573.5269
B60: 22.65 | C60: client E | D60: =D46*$B60 -> 0 | E60: =E46*$B60 -> 0 | F60: =F46*$B60 -> 0 | G60: =G46*$B60 -> 792.75 | H60: =H46*$B60 -> 1200.45 | I60: =I46*$B60 -> 1200.45 | J60: =J46*$B60 -> 1404.3 | K60: =K46*$B60 -> 1404.3 | ... O60: =O46*$B60 -> 588.9 | P60: =P46*$B60*(1+inflation_vente) -> 699.885 | Q60: =Q46*$B60*(1+inflation_vente) -> 699.885 | R60: =R46*$B60*(1+inflation_vente) -> 699.885 | S60: =S46*$B60*(1+inflation_vente) -> 699.885 | T60: =T46*$B60*(1+inflation_vente) -> 839.862 | U60: =U46*$B60*(1+inflation_vente) -> 839.862 | V60: =V46*$B60*(1+inflation_vente) -> 839.862 | W60: =W46*$B60*(1+inflation_vente) -> 839.862 | ... AA60: =AA46*$B60*(1+inflation_vente) -> 699.885 | AB60: =AB46*$B60*(1+inflation_vente)^2 -> 816.99909 | AC60: =AC46*$B60*(1+inflation_vente)^2 -> 816.99909 | AD60: =AD46*$B60*(1+inflation_vente)^2 -> 816.99909 | AE60: =AE46*$B60*(1+inflation_vente)^2 -> 1033.2636 | AF60: =AF46*$B60*(1+inflation_vente)^2 -> 1225.4986 | AG60: =AG46*$B60*(1+inflation_vente)^2 -> 1225.4986 | AH60: =AH46*$B60*(1+inflation_vente)^2 -> 1225.4986 | AI60: =AI46*$B60*(1+inflation_vente)^2 -> 1225.4986 | ... AM60: =AM46*$B60*(1+inflation_vente)^2 -> 1033.2636 | AN60: =AN46*$B60*(1+inflation_vente)^3 -> 1262.2636 | AO60: =AO46*$B60*(1+inflation_vente)^3 -> 1262.2636 | AP60: =AP46*$B60*(1+inflation_vente)^3 -> 1262.2636 | AQ60: =AQ46*$B60*(1+inflation_vente)^3 -> 1262.2636 | AR60: =AR46*$B60*(1+inflation_vente)^3 -> 1262.2636 | AS60: =AS46*$B60*(1+inflation_vente)^3 -> 1262.2636 | AT60: =AT46*$B60*(1+inflation_vente)^3 -> 1262.2636 | AU60: =AU46*$B60*(1+inflation_vente)^3 -> 1485.016 | ... AY60: =AY46*$B60*(1+inflation_vente)^3 -> 643.50693
D61: =D47*$B61 -> 0 | E61: =E47*$B61 -> 0 | F61: =F47*$B61 -> 0 | G61: =G47*$B61 -> 0 | H61: =H47*$B61 -> 0 | I61: =I47*$B61 -> 0 | J61: =J47*$B61 -> 0 | K61: =K47*$B61 -> 0 | ... O61: =O47*$B61 -> 0 | P61: =P47*$B61*(1+inflation_vente) -> 0 | Q61: =Q47*$B61*(1+inflation_vente) -> 0 | R61: =R47*$B61*(1+inflation_vente) -> 0 | S61: =S47*$B61*(1+inflation_vente) -> 0 | T61: =T47*$B61*(1+inflation_vente) -> 0 | U61: =U47*$B61*(1+inflation_vente) -> 0 | V61: =V47*$B61*(1+inflation_vente) -> 0 | W61: =W47*$B61*(1+inflation_vente) -> 0 | ... AA61: =AA47*$B61*(1+inflation_vente) -> 0 | AB61: =AB47*$B61*(1+inflation_vente)^2 -> 0 | AC61: =AC47*$B61*(1+inflation_vente)^2 -> 0 | AD61: =AD47*$B61*(1+inflation_vente)^2 -> 0 | AE61: =AE47*$B61*(1+inflation_vente)^2 -> 0 | AF61: =AF47*$B61*(1+inflation_vente)^2 -> 0 | AG61: =AG47*$B61*(1+inflation_vente)^2 -> 0 | AH61: =AH47*$B61*(1+inflation_vente)^2 -> 0 | AI61: =AI47*$B61*(1+inflation_vente)^2 -> 0 | ... AM61: =AM47*$B61*(1+inflation_vente)^2 -> 0 | AN61: =AN47*$B61*(1+inflation_vente)^3 -> 0 | AO61: =AO47*$B61*(1+inflation_vente)^3 -> 0 | AP61: =AP47*$B61*(1+inflation_vente)^3 -> 0 | AQ61: =AQ47*$B61*(1+inflation_vente)^3 -> 0 | AR61: =AR47*$B61*(1+inflation_vente)^3 -> 0 | AS61: =AS47*$B61*(1+inflation_vente)^3 -> 0 | AT61: =AT47*$B61*(1+inflation_vente)^3 -> 0 | AU61: =AU47*$B61*(1+inflation_vente)^3 -> 0 | ... AY61: =AY47*$B61*(1+inflation_vente)^3 -> 0
D62: =SUM(D55:O55) -> 46269.05 | P62: =SUM(P55:AA55) -> 49336.794 | AB62: =SUM(AB55:AM55) -> 54382.477 | AN62: =SUM(AN55:AY55) -> 58662.612
H64: Démarrage | O64: =(P62-D62)/D62 -> 0.066302291 | T64: Stabilisation | AA64: =(AB62-P62)/P62 -> 0.10227018 | AF64: Déploiement | AM64: =(AN62-AB62)/AB62 -> 0.07870431 | AR64: Objectif
C67: Insights
F68: 2025 | H68: 2026 | J68: 2027 | L68: 2028
C69: CA Annuel | F69: =D62 -> 46269.05 | H69: =P62 -> 49336.794 | J69: =AB62 -> 54382.477 | L69: =AN62 -> 58662.612
C70: CA Mensuel moyen | F70: =F69/12 -> 3855.7542 | H70: =H69/12 -> 4111.3995 | J70: =J69/12 -> 4531.8731 | L70: =L69/12 -> 4888.551
C71: CA journalier moyen | F71: =F70/24 -> 160.65642 | H71: =H70/24 -> 171.30831 | J71: =J70/24 -> 188.82804 | L71: =L70/24 -> 203.68962
C72: Nombre de clients annuel | F72: =SUM(D48:O48) -> 2790 | H72: =SUM(P48:AA48) -> 2893 | J72: =SUM(AB48:AM48) -> 3032 | L72: =SUM(AN48:AY48) -> 3174
C73: Nombre de clients moyen / jour | F73: =F72/Variables!$I$24 -> 9.6875 | H73: =H72/Variables!$I$24 -> 10.045139 | J73: =J72/Variables!$I$24 -> 10.527778 | L73: =L72/Variables!$I$24 -> 11.020833
C74: Panier Moyen | F74: =F69/F72 -> 16.583889 | H74: =H69/H72 -> 17.053852 | J74: =J69/J72 -> 17.936173 | L74: =L69/L72 -> 18.482234

Sheet CA
B2: CHIFFRE D'AFFAIRES ET COUTS DE PRODUCTION
C4: =YEAR(EDATE(date_début,-12)) -> 2024 | D4: =YEAR(date_début) -> 2025 | Q4: =YEAR(EDATE(date_début,12)) -> 2026 | AD4: =YEAR(EDATE(date_début,24)) -> 2027 | AE4: =YEAR(EDATE(date_début,36)) -> 2028
D5: Jan | E5: Fév | F5: Mar | G5: Avr | H5: Mai | I5: Juin | J5: Juil | K5: Aout | L5: Sept | M5: Oct | N5: Nov | O5: Déc | Q5: Jan | R5: Fév | S5: Mar | T5: Avr | U5: Mai | V5: Juin | W5: Juil | X5: Aout | Y5: Sept | Z5: Oct | AA5: Nov | AB5: Déc
B6: CHIFFRE D'AFFAIRES
B7: Restauration
B8: CA - client A | D8: ='Insights surplace'!D56 -> 775 | E8: ='Insights surplace'!E56 -> 925 | F8: ='Insights surplace'!F56 -> 1005 | G8: ='Insights surplace'!G56 -> 1080 | H8: ='Insights surplace'!H56 -> 1315 | I8: ='Insights surplace'!I56 -> 1545 | J8: ='Insights surplace'!J56 -> 1700 | K8: ='Insights surplace'!K56 -> 1700 | ... O8: ='Insights surplace'!O56 -> 850 | P8: =SUM(D8:O8) -> 14990 | Q8: ='Insights surplace'!P56 -> 875.5 | R8: ='Insights surplace'!Q56 -> 875.5 | S8: ='Insights surplace'!R56 -> 963.05 | T8: ='Insights surplace'!S56 -> 1225.7 | U8: ='Insights surplace'!T56 -> 1225.7 | V8: ='Insights surplace'!U56 -> 1751 | W8: ='Insights surplace'!V56 -> 1926.1 | X8: ='Insights surplace'!W56 -> 1926.1 | ... AB8: ='Insights surplace'!AA56 -> 875.5 | AC8: =SUM(Q8:AB8) -> 15671.45 | AD8: =SUM('Insights surplace'!AB56:AM56) -> 16804.656 | AE8: =SUM('Insights surplace'!AN56:AY56) -> 19374.05
B9: Nombre de client A | D9: ='Insights surplace'!D42 -> 155 | E9: ='Insights surplace'!E42 -> 185 | F9: ='Insights surplace'!F42 -> 201 | G9: ='Insights surplace'!G42 -> 216 | H9: ='Insights surplace'!H42 -> 263 | I9: ='Insights surplace'!I42 -> 309 | J9: ='Insights surplace'!J42 -> 340 | K9: ='Insights surplace'!K42 -> 340 | ... O9: ='Insights surplace'!O42 -> 170 | P9: =SUM(D9:O9) -> 2998 | Q9: ='Insights surplace'!P42 -> 170 | R9: ='Insights surplace'!Q42 -> 170 | S9: ='Insights surplace'!R42 -> 187 | T9: ='Insights surplace'!S42 -> 238 | U9: ='Insights surplace'!T42 -> 238 | V9: ='Insights surplace'!U42 -> 340 | W9: ='Insights surplace'!V42 -> 374 | X9: ='Insights surplace'!W42 -> 374 | ... AB9: ='Insights surplace'!AA42 -> 170 | AC9: =SUM(Q9:AB9) -> 3043 | AD9: =SUM('Insights surplace'!AB42:AM42) -> 3168 | AE9: =SUM('Insights surplace'!AC42:AN42) -> 3204
B10: CA - client B | D10: ='Insights surplace'!D57 -> 2176.0909 | E10: ='Insights surplace'!E57 -> 2607.6364 | F10: ='Insights surplace'!F57 -> 2828 | G10: ='Insights surplace'!G57 -> 3048.3636 | H10: ='Insights surplace'!H57 -> 3700.2727 | I10: ='Insights surplace'!I57 -> 4352.1818 | J10: ='Insights surplace'!J57 -> 4783.7273 | K10: ='Insights surplace'!K57 -> 4783.7273 | ... O10: ='Insights surplace'!O57 -> 2396.4545 | P10: =SUM(D10:O10) -> 42208.818 | Q10: ='Insights surplace'!P57 -> 2723.6945 | R10: ='Insights surplace'!Q57 -> 2723.6945 | S10: ='Insights surplace'!R57 -> 2997.9555 | T10: ='Insights surplace'!S57 -> 3811.2809 | U10: ='Insights surplace'!T57 -> 3811.2809 | V10: ='Insights surplace'!U57 -> 5447.3891 | W10: ='Insights surplace'!V57 -> 5995.9109 | X10: ='Insights surplace'!W57 -> 5995.9109 | ... AB10: ='Insights surplace'!AA57 -> 2723.6945 | AC10: =SUM(Q10:AB10) -> 48761.698 | AD10: =SUM('Insights surplace'!AB57:AM57) -> 50341.441 | AE10: =SUM('Insights surplace'!AN57:AY57) -> 58032.148
B11: Nombre de client B | D11: ='Insights surplace'!D43 -> 237 | E11: ='Insights surplace'!E43 -> 284 | F11: ='Insights surplace'!F43 -> 308 | G11: ='Insights surplace'!G43 -> 332 | H11: ='Insights surplace'!H43 -> 403 | I11: ='Insights surplace'!I43 -> 474 | J11: ='Insights surplace'!J43 -> 521 | K11: ='Insights surplace'!K43 -> 521 | ... O11: ='Insights surplace'!O43 -> 261 | P11: =SUM(D11:O11) -> 4597 | Q11: ='Insights surplace'!P43 -> 288 | R11: ='Insights surplace'!Q43 -> 288 | S11: ='Insights surplace'!R43 -> 317 | T11: ='Insights surplace'!S43 -> 403 | U11: ='Insights surplace'!T43 -> 403 | V11: ='Insights surplace'!U43 -> 576 | W11: ='Insights surplace'!V43 -> 634 | X11: ='Insights surplace'!W43 -> 634 | ... AB11: ='Insights surplace'!AA43 -> 288 | AC11: =SUM(Q11:AB11) -> 5156 | AD11: =SUM('Insights surplace'!AB43:AM43) -> 5168 | AE11: =SUM('Insights surplace'!AC43:AN43) -> 5226
B12: CA - client C | D12: ='Insights surplace'!D58 -> 1043.6364 | E12: ='Insights surplace'!E58 -> 1247.2727 | F12: ='Insights surplace'!F58 -> 1349.0909 | G12: ='Insights surplace'!G58 -> 1450.9091 | H12: ='Insights surplace'!H58 -> 1769.0909 | I12: ='Insights surplace'!I58 -> 2074.5455 | J12: ='Insights surplace'!J58 -> 2278.1818 | K12: ='Insights surplace'!K58 -> 2278.1818 | ... O12: ='Insights surplace'!O58 -> 1145.4545 | P12: =SUM(D12:O12) -> 20134.545 | Q12: ='Insights surplace'!P58 -> 1468.2182 | R12: ='Insights surplace'!Q58 -> 1468.2182 | S12: ='Insights surplace'!R58 -> 1612.4182 | T12: ='Insights surplace'!S58 -> 2058.1273 | U12: ='Insights surplace'!T58 -> 2058.1273 | V12: ='Insights surplace'!U58 -> 2936.4364 | W12: ='Insights surplace'!V58 -> 3224.8364 | X12: ='Insights surplace'!W58 -> 3224.8364 | ... AB12: ='Insights surplace'!AA58 -> 1468.2182 | AC12: =SUM(Q12:AB12) -> 26270.618 | AD12: =SUM('Insights surplace'!AB58:AM58) -> 22103.369 | AE12: =SUM('Insights surplace'!AN58:AY58) -> 25506.235
B13: Nombre de client C | D13: ='Insights surplace'!D44 -> 82 | E13: ='Insights surplace'!E44 -> 98 | F13: ='Insights surplace'!F44 -> 106 | G13: ='Insights surplace'!G44 -> 114 | H13: ='Insights surplace'!H44 -> 139 | I13: ='Insights surplace'!I44 -> 163 | J13: ='Insights surplace'!J44 -> 179 | K13: ='Insights surplace'!K44 -> 179 | ... O13: ='Insights surplace'!O44 -> 90 | P13: =SUM(D13:O13) -> 1582 | Q13: ='Insights surplace'!P44 -> 112 | R13: ='Insights surplace'!Q44 -> 112 | S13: ='Insights surplace'!R44 -> 123 | T13: ='Insights surplace'!S44 -> 157 | U13: ='Insights surplace'!T44 -> 157 | V13: ='Insights surplace'!U44 -> 224 | W13: ='Insights surplace'!V44 -> 246 | X13: ='Insights surplace'!W44 -> 246 | ... AB13: ='Insights surplace'!AA44 -> 112 | AC13: =SUM(Q13:AB13) -> 2004 | AD13: =SUM('Insights surplace'!AB44:AM44) -> 1637 | AE13: =SUM('Insights surplace'!AC44:AN44) -> 1656
B14: CA - client D | D14: ='Insights surplace'!D59 -> 4205.4545 | E14: ='Insights surplace'!E59 -> 5040 | F14: ='Insights surplace'!F59 -> 5465.4545 | G14: ='Insights surplace'!G59 -> 5890.9091 | H14: ='Insights surplace'!H59 -> 7150.9091 | I14: ='Insights surplace'!I59 -> 8410.9091 | J14: ='Insights surplace'!J59 -> 9245.4545 | K14: ='Insights surplace'!K59 -> 9245.4545 | ... O14: ='Insights surplace'!O59 -> 4630.9091 | P14: =SUM(D14:O14) -> 81572.727 | Q14: ='Insights surplace'!P59 -> 4550.7273 | R14: ='Insights surplace'!Q59 -> 4550.7273 | S14: ='Insights surplace'!R59 -> 5005.8 | T14: ='Insights surplace'!S59 -> 6371.0182 | U14: ='Insights surplace'!T59 -> 6371.0182 | V14: ='Insights surplace'!U59 -> 9101.4545 | W14: ='Insights surplace'!V59 -> 10011.6 | X14: ='Insights surplace'!W59 -> 10011.6 | ... AB14: ='Insights surplace'!AA59 -> 4550.7273 | AC14: =SUM(Q14:AB14) -> 81458.018 | AD14: =SUM('Insights surplace'!AB59:AM59) -> 87078.672 | AE14: =SUM('Insights surplace'!AN59:AY59) -> 100419.62
B15: Nombre de client D | D15: ='Insights surplace'!D45 -> 257 | E15: ='Insights surplace'!E45 -> 308 | F15: ='Insights surplace'!F45 -> 334 | G15: ='Insights surplace'!G45 -> 360 | H15: ='Insights surplace'!H45 -> 437 | I15: ='Insights surplace'!I45 -> 514 | J15: ='Insights surplace'!J45 -> 565 | K15: ='Insights surplace'!K45 -> 565 | ... O15: ='Insights surplace'!O45 -> 283 | P15: =SUM(D15:O15) -> 4985 | Q15: ='Insights surplace'!P45 -> 270 | R15: ='Insights surplace'!Q45 -> 270 | S15: ='Insights surplace'!R45 -> 297 | T15: ='Insights surplace'!S45 -> 378 | U15: ='Insights surplace'!T45 -> 378 | V15: ='Insights surplace'!U45 -> 540 | W15: ='Insights surplace'!V45 -> 594 | X15: ='Insights surplace'!W45 -> 594 | ... AB15: ='Insights surplace'!AA45 -> 270 | AC15: =SUM(Q15:AB15) -> 4833 | AD15: =SUM('Insights surplace'!AB45:AM45) -> 5016 | AE15: =SUM('Insights surplace'!AC45:AN45) -> 5073
B16: CA - client E | D16: ='Insights surplace'!D60 -> 3397.5 | E16: ='Insights surplace'!E60 -> 4077 | F16: ='Insights surplace'!F60 -> 4427.0455 | G16: ='Insights surplace'!G60 -> 4756.5 | H16: ='Insights surplace'!H60 -> 5786.0455 | I16: ='Insights surplace'!I60 -> 6795 | J16: ='Insights surplace'!J60 -> 7474.5 | K16: ='Insights surplace'!K60 -> 7474.5 | ... O16: ='Insights surplace'!O60 -> 3747.5455 | P16: =SUM(D16:O16) -> 65952.682 | Q16: ='Insights surplace'!P60 -> 3605.4682 | R16: ='Insights surplace'!Q60 -> 3605.4682 | S16: ='Insights surplace'!R60 -> 3966.015 | T16: ='Insights surplace'!S60 -> 5047.6555 | U16: ='Insights surplace'!T60 -> 5047.6555 | V16: ='Insights surplace'!U60 -> 7210.9364 | W16: ='Insights surplace'!V60 -> 7932.03 | X16: ='Insights surplace'!W60 -> 7932.03 | ... AB16: ='Insights surplace'!AA60 -> 3605.4682 | AC16: =SUM(Q16:AB16) -> 64537.88 | AD16: =SUM('Insights surplace'!AB60:AM60) -> 69204.629 | AE16: =SUM('Insights surplace'!AN60:AY60) -> 79785.859
B17: Nombre de client E | D17: ='Insights surplace'!D46 -> 165 | E17: ='Insights surplace'!E46 -> 198 | F17: ='Insights surplace'!F46 -> 215 | G17: ='Insights surplace'!G46 -> 231 | H17: ='Insights surplace'!H46 -> 281 | I17: ='Insights surplace'!I46 -> 330 | J17: ='Insights surplace'!J46 -> 363 | K17: ='Insights surplace'!K46 -> 363 | ... O17: ='Insights surplace'!O46 -> 182 | P17: =SUM(D17:O17) -> 3203 | Q17: ='Insights surplace'!P46 -> 170 | R17: ='Insights surplace'!Q46 -> 170 | S17: ='Insights surplace'!R46 -> 187 | T17: ='Insights surplace'!S46 -> 238 | U17: ='Insights surplace'!T46 -> 238 | V17: ='Insights surplace'!U46 -> 340 | W17: ='Insights surplace'!V46 -> 374 | X17: ='Insights surplace'!W46 -> 374 | ... AB17: ='Insights surplace'!AA46 -> 170 | AC17: =SUM(Q17:AB17) -> 3043 | AD17: =SUM('Insights surplace'!AB46:AM46) -> 3168 | AE17: =SUM('Insights surplace'!AC46:AN46) -> 3204
B18: CA - client F | D18: ='Insights surplace'!D61 -> 0 | E18: ='Insights surplace'!E61 -> 0 | F18: ='Insights surplace'!F61 -> 0 | G18: ='Insights surplace'!G61 -> 0 | H18: ='Insights surplace'!H61 -> 0 | I18: ='Insights surplace'!I61 -> 0 | J18: ='Insights surplace'!J61 -> 0 | K18: ='Insights surplace'!K61 -> 0 | ... O18: ='Insights surplace'!O61 -> 0 | P18: =SUM(D18:O18) -> 0 | Q18: ='Insights surplace'!P61 -> 0 | R18: ='Insights surplace'!Q61 -> 0 | S18: ='Insights surplace'!R61 -> 0 | T18: ='Insights surplace'!S61 -> 0 | U18: ='Insights surplace'!T61 -> 0 | V18: ='Insights surplace'!U61 -> 0 | W18: ='Insights surplace'!V61 -> 0 | X18: ='Insights surplace'!W61 -> 0 | ... AB18: ='Insights surplace'!AA61 -> 0 | AC18: =SUM(Q18:AB18) -> 0 | AD18: =SUM('Insights surplace'!AB61:AM61) -> 0 | AE18: =SUM('Insights surplace'!AN61:AY61) -> 0
B19: Nombre de client F | D19: ='Insights surplace'!D47 -> 0 | E19: ='Insights surplace'!E47 -> 0 | F19: ='Insights surplace'!F47 -> 0 | G19: ='Insights surplace'!G47 -> 0 | H19: ='Insights surplace'!H47 -> 0 | I19: ='Insights surplace'!I47 -> 0 | J19: ='Insights surplace'!J47 -> 0 | K19: ='Insights surplace'!K47 -> 0 | ... O19: ='Insights surplace'!O47 -> 0 | P19: =SUM(D19:O19) -> 0 | Q19: ='Insights surplace'!P47 -> 0 | R19: ='Insights surplace'!Q47 -> 0 | S19: ='Insights surplace'!R47 -> 0 | T19: ='Insights surplace'!S47 -> 0 | U19: ='Insights surplace'!T47 -> 0 | V19: ='Insights surplace'!U47 -> 0 | W19: ='Insights surplace'!V47 -> 0 | X19: ='Insights surplace'!W47 -> 0 | ... AB19: ='Insights surplace'!AA47 -> 0 | AC19: =SUM(Q19:AB19) -> 0 | AD19: =SUM('Insights surplace'!AB47:AM47) -> 0 | AE19: =SUM('Insights surplace'!AC47:AN47) -> 0
B21: Nombre de clients | D21: =D9+D11+D13+D15+D17+D19 -> 896 | E21: =E9+E11+E13+E15+E17+E19 -> 1073 | F21: =F9+F11+F13+F15+F17+F19 -> 1164 | G21: =G9+G11+G13+G15+G17+G19 -> 1253 | H21: =H9+H11+H13+H15+H17+H19 -> 1523 | I21: =I9+I11+I13+I15+I17+I19 -> 1790 | J21: =J9+J11+J13+J15+J17+J19 -> 1968 | K21: =K9+K11+K13+K15+K17+K19 -> 1968 | ... O21: =O9+O11+O13+O15+O17+O19 -> 986 | P21: =SUM(D21:O21) -> 17365 | Q21: =Q9+Q11+Q13+Q15+Q17+Q19 -> 1010 | R21: =R9+R11+R13+R15+R17+R19 -> 1010 | S21: =S9+S11+S13+S15+S17+S19 -> 1111 | T21: =T9+T11+T13+T15+T17+T19 -> 1414 | U21: =U9+U11+U13+U15+U17+U19 -> 1414 | V21: =V9+V11+V13+V15+V17+V19 -> 2020 | W21: =W9+W11+W13+W15+W17+W19 -> 2222 | X21: =X9+X11+X13+X15+X17+X19 -> 2222 | ... AB21: =AB9+AB11+AB13+AB15+AB17+AB19 -> 1010 | AC21: =SUM(Q21:AB21) -> 18079 | AD21: =AD9+AD11+AD13+AD15+AD17+AD19 -> 18157 | AE21: =AE9+AE11+AE13+AE15+AE17+AE19 -> 18363
B22: =CONCAT("Chiffre d'Affaires - ",B7) -> Chiffre d'Affaires - Restauration | D22: =D8+D10+D12+D14+D16+D18 -> 11597.682 | E22: =E8+E10+E12+E14+E16+E18 -> 13896.909 | F22: =F8+F10+F12+F14+F16+F18 -> 15074.591 | G22: =G8+G10+G12+G14+G16+G18 -> 16226.682 | H22: =H8+H10+H12+H14+H16+H18 -> 19721.318 | I22: =I8+I10+I12+I14+I16+I18 -> 23177.636 | J22: =J8+J10+J12+J14+J16+J18 -> 25481.864 | K22: =K8+K10+K12+K14+K16+K18 -> 25481.864 | ... O22: =O8+O10+O12+O14+O16+O18 -> 12770.364 | P22: =SUM(D22:O22) -> 224858.77 | Q22: =Q8+Q10+Q12+Q14+Q16+Q18 -> 13223.608 | R22: =R8+R10+R12+R14+R16+R18 -> 13223.608 | S22: =S8+S10+S12+S14+S16+S18 -> 14545.239 | T22: =T8+T10+T12+T14+T16+T18 -> 18513.782 | U22: =U8+U10+U12+U14+U16+U18 -> 18513.782 | V22: =V8+V10+V12+V14+V16+V18 -> 26447.216 | W22: =W8+W10+W12+W14+W16+W18 -> 29090.477 | X22: =X8+X10+X12+X14+X16+X18 -> 29090.477 | ... AB22: =AB8+AB10+AB12+AB14+AB16+AB18 -> 13223.608 | AC22: =SUM(Q22:AB22) -> 236699.67 | AD22: =AD8+AD10+AD12+AD14+AD16+AD18 -> 245532.77 | AE22: =AE8+AE10+AE12+AE14+AE16+AE18 -> 283117.92
B24: Vente-platforme
B25: CA - client A | D25: ='Insights Livraison'!D56 -> 0 | E25: ='Insights Livraison'!E56 -> 0 | F25: ='Insights Livraison'!F56 -> 0 | G25: ='Insights Livraison'!G56 -> 0 | H25: ='Insights Livraison'!H56 -> 0 | I25: ='Insights Livraison'!I56 -> 0 | J25: ='Insights Livraison'!J56 -> 0 | K25: ='Insights Livraison'!K56 -> 0 | ... O25: ='Insights Livraison'!O56 -> 0 | P25: =SUM(D25:O25) -> 0 | Q25: ='Insights Livraison'!P56 -> 0 | R25: ='Insights Livraison'!Q56 -> 0 | S25: ='Insights Livraison'!R56 -> 0 | T25: ='Insights Livraison'!S56 -> 0 | U25: ='Insights Livraison'!T56 -> 0 | V25: ='Insights Livraison'!U56 -> 0 | W25: ='Insights Livraison'!V56 -> 0 | X25: ='Insights Livraison'!W56 -> 0 | ... AB25: ='Insights Livraison'!AA56 -> 0 | AC25: =SUM(Q25:AB25) -> 0 | AD25: =SUM('Insights Livraison'!AB56:AM56) -> 0 | AE25: =SUM('Insights Livraison'!AN56:AY56) -> 0
B26: Nombre de client A | D26: ='Insights Livraison'!D42 -> 0 | E26: ='Insights Livraison'!E42 -> 0 | F26: ='Insights Livraison'!F42 -> 0 | G26: ='Insights Livraison'!G42 -> 0 | H26: ='Insights Livraison'!H42 -> 0 | I26: ='Insights Livraison'!I42 -> 0 | J26: ='Insights Livraison'!J42 -> 0 | K26: ='Insights Livraison'!K42 -> 0 | ... O26: ='Insights Livraison'!O42 -> 0 | P26: =SUM(D26:O26) -> 0 | Q26: ='Insights Livraison'!P42 -> 0 | R26: ='Insights Livraison'!Q42 -> 0 | S26: ='Insights Livraison'!R42 -> 0 | T26: ='Insights Livraison'!S42 -> 0 | U26: ='Insights Livraison'!T42 -> 0 | V26: ='Insights Livraison'!U42 -> 0 | W26: ='Insights Livraison'!V42 -> 0 | X26: ='Insights Livraison'!W42 -> 0 | ... AB26: ='Insights Livraison'!AA42 -> 0 | AC26: =SUM(Q26:AB26) -> 0 | AD26: =SUM('Insights Livraison'!AB42:AM42) -> 0 | AE26: =SUM('Insights Livraison'!AN42:AY42) -> 0
B27: CA - client B | D27: ='Insights Livraison'!D57 -> 0 | E27: ='Insights Livraison'!E57 -> 0 | F27: ='Insights Livraison'!F57 -> 0 | G27: ='Insights Livraison'!G57 -> 545.4 | H27: ='Insights Livraison'!H57 -> 828.2 | I27: ='Insights Livraison'!I57 -> 828.2 | J27: ='Insights Livraison'!J57 -> 959.5 | K27: ='Insights Livraison'!K57 -> 959.5 | ... O27: ='Insights Livraison'!O57 -> 414.1 | P27: =SUM(D27:O27) -> 7140.7 | Q27: ='Insights Livraison'!P57 -> 561.762 | R27: ='Insights Livraison'!Q57 -> 561.762 | S27: ='Insights Livraison'!R57 -> 561.762 | T27: ='Insights Livraison'!S57 -> 561.762 | U27: ='Insights Livraison'!T57 -> 676.195 | V27: ='Insights Livraison'!U57 -> 676.195 | W27: ='Insights Livraison'!V57 -> 676.195 | X27: ='Insights Livraison'!W57 -> 676.195 | ... AB27: ='Insights Livraison'!AA57 -> 561.762 | AC27: =SUM(Q27:AB27) -> 7542.175 | AD27: =SUM('Insights Livraison'!AB57:AM57) -> 7479.1328 | AE27: =SUM('Insights Livraison'!AN57:AY57) -> 8034.6031
B28: Nombre de client B | D28: ='Insights Livraison'!D43 -> 0 | E28: ='Insights Livraison'!E43 -> 0 | F28: ='Insights Livraison'!F43 -> 0 | G28: ='Insights Livraison'!G43 -> 54 | H28: ='Insights Livraison'!H43 -> 82 | I28: ='Insights Livraison'!I43 -> 82 | J28: ='Insights Livraison'!J43 -> 95 | K28: ='Insights Livraison'!K43 -> 95 | ... O28: ='Insights Livraison'!O43 -> 41 | P28: =SUM(D28:O28) -> 707 | Q28: ='Insights Livraison'!P43 -> 54 | R28: ='Insights Livraison'!Q43 -> 54 | S28: ='Insights Livraison'!R43 -> 54 | T28: ='Insights Livraison'!S43 -> 54 | U28: ='Insights Livraison'!T43 -> 65 | V28: ='Insights Livraison'!U43 -> 65 | W28: ='Insights Livraison'!V43 -> 65 | X28: ='Insights Livraison'!W43 -> 65 | ... AB28: ='Insights Livraison'!AA43 -> 54 | AC28: =SUM(Q28:AB28) -> 725 | AD28: =SUM('Insights Livraison'!AB43:AM43) -> 698 | AE28: =SUM('Insights Livraison'!AN43:AY43) -> 728
B29: CA - client C | D29: ='Insights Livraison'!D58 -> 0 | E29: ='Insights Livraison'!E58 -> 0 | F29: ='Insights Livraison'!F58 -> 0 | G29: ='Insights Livraison'!G58 -> 140 | H29: ='Insights Livraison'!H58 -> 196 | I29: ='Insights Livraison'!I58 -> 196 | J29: ='Insights Livraison'!J58 -> 238 | K29: ='Insights Livraison'!K58 -> 238 | ... O29: ='Insights Livraison'!O58 -> 98 | P29: =SUM(D29:O29) -> 1750 | Q29: ='Insights Livraison'!P58 -> 86.52 | R29: ='Insights Livraison'!Q58 -> 86.52 | S29: ='Insights Livraison'!R58 -> 86.52 | T29: ='Insights Livraison'!S58 -> 86.52 | U29: ='Insights Livraison'!T58 -> 100.94 | V29: ='Insights Livraison'!U58 -> 100.94 | W29: ='Insights Livraison'!V58 -> 100.94 | X29: ='Insights Livraison'!W58 -> 100.94 | ... AB29: ='Insights Livraison'!AA58 -> 86.52 | AC29: =SUM(Q29:AB29) -> 1139.18 | AD29: =SUM('Insights Livraison'!AB58:AM58) -> 1262.471 | AE29: =SUM('Insights Livraison'!AN58:AY58) -> 1361.5378
B30: Nombre de client C | D30: ='Insights Livraison'!D44 -> 0 | E30: ='Insights Livraison'!E44 -> 0 | F30: ='Insights Livraison'!F44 -> 0 | G30: ='Insights Livraison'!G44 -> 10 | H30: ='Insights Livraison'!H44 -> 14 | I30: ='Insights Livraison'!I44 -> 14 | J30: ='Insights Livraison'!J44 -> 17 | K30: ='Insights Livraison'!K44 -> 17 | ... O30: ='Insights Livraison'!O44 -> 7 | P30: =SUM(D30:O30) -> 125 | Q30: ='Insights Livraison'!P44 -> 6 | R30: ='Insights Livraison'!Q44 -> 6 | S30: ='Insights Livraison'!R44 -> 6 | T30: ='Insights Livraison'!S44 -> 6 | U30: ='Insights Livraison'!T44 -> 7 | V30: ='Insights Livraison'!U44 -> 7 | W30: ='Insights Livraison'!V44 -> 7 | X30: ='Insights Livraison'!W44 -> 7 | ... AB30: ='Insights Livraison'!AA44 -> 6 | AC30: =SUM(Q30:AB30) -> 79 | AD30: =SUM('Insights Livraison'!AB44:AM44) -> 85 | AE30: =SUM('Insights Livraison'!AN44:AY44) -> 89
B31: CA - client D | D31: ='Insights Livraison'!D59 -> 0 | E31: ='Insights Livraison'!E59 -> 0 | F31: ='Insights Livraison'!F59 -> 0 | G31: ='Insights Livraison'!G59 -> 2070 | H31: ='Insights Livraison'!H59 -> 3114 | I31: ='Insights Livraison'!I59 -> 3114 | J31: ='Insights Livraison'!J59 -> 3636 | K31: ='Insights Livraison'!K59 -> 3636 | ... O31: ='Insights Livraison'!O59 -> 1548 | P31: =SUM(D31:O31) -> 26982 | Q31: ='Insights Livraison'!P59 -> 2336.04 | R31: ='Insights Livraison'!Q59 -> 2336.04 | S31: ='Insights Livraison'!R59 -> 2336.04 | T31: ='Insights Livraison'!S59 -> 2336.04 | U31: ='Insights Livraison'!T59 -> 2799.54 | V31: ='Insights Livraison'!U59 -> 2799.54 | W31: ='Insights Livraison'!V59 -> 2799.54 | X31: ='Insights Livraison'!W59 -> 2799.54 | ... AB31: ='Insights Livraison'!AA59 -> 2336.04 | AC31: =SUM(Q31:AB31) -> 31276.98 | AD31: =SUM('Insights Livraison'!AB59:AM59) -> 32520.829 | AE31: =SUM('Insights Livraison'!AN59:AY59) -> 35109.319
B32: Nombre de client D | D32: ='Insights Livraison'!D45 -> 0 | E32: ='Insights Livraison'!E45 -> 0 | F32: ='Insights Livraison'!F45 -> 0 | G32: ='Insights Livraison'!G45 -> 115 | H32: ='Insights Livraison'!H45 -> 173 | I32: ='Insights Livraison'!I45 -> 173 | J32: ='Insights Livraison'!J45 -> 202 | K32: ='Insights Livraison'!K45 -> 202 | ... O32: ='Insights Livraison'!O45 -> 86 | P32: =SUM(D32:O32) -> 1499 | Q32: ='Insights Livraison'!P45 -> 126 | R32: ='Insights Livraison'!Q45 -> 126 | S32: ='Insights Livraison'!R45 -> 126 | T32: ='Insights Livraison'!S45 -> 126 | U32: ='Insights Livraison'!T45 -> 151 | V32: ='Insights Livraison'!U45 -> 151 | W32: ='Insights Livraison'!V45 -> 151 | X32: ='Insights Livraison'!W45 -> 151 | ... AB32: ='Insights Livraison'!AA45 -> 126 | AC32: =SUM(Q32:AB32) -> 1687 | AD32: =SUM('Insights Livraison'!AB45:AM45) -> 1703 | AE32: =SUM('Insights Livraison'!AN45:AY45) -> 1785
B33: CA - client E | D33: ='Insights Livraison'!D60 -> 0 | E33: ='Insights Livraison'!E60 -> 0 | F33: ='Insights Livraison'!F60 -> 0 | G33: ='Insights Livraison'!G60 -> 792.75 | H33: ='Insights Livraison'!H60 -> 1200.45 | I33: ='Insights Livraison'!I60 -> 1200.45 | J33: ='Insights Livraison'!J60 -> 1404.3 | K33: ='Insights Livraison'!K60 -> 1404.3 | ... O33: ='Insights Livraison'!O60 -> 588.9 | P33: =SUM(D33:O33) -> 10396.35 | Q33: ='Insights Livraison'!P60 -> 699.885 | R33: ='Insights Livraison'!Q60 -> 699.885 | S33: ='Insights Livraison'!R60 -> 699.885 | T33: ='Insights Livraison'!S60 -> 699.885 | U33: ='Insights Livraison'!T60 -> 839.862 | V33: ='Insights Livraison'!U60 -> 839.862 | W33: ='Insights Livraison'!V60 -> 839.862 | X33: ='Insights Livraison'!W60 -> 839.862 | ... AB33: ='Insights Livraison'!AA60 -> 699.885 | AC33: =SUM(Q33:AB33) -> 9378.459 | AD33: =SUM('Insights Livraison'!AB60:AM60) -> 13120.044 | AE33: =SUM('Insights Livraison'!AN60:AY60) -> 14157.152
B34: Nombre de client E | D34: ='Insights Livraison'!D46 -> 0 | E34: ='Insights Livraison'!E46 -> 0 | F34: ='Insights Livraison'!F46 -> 0 | G34: ='Insights Livraison'!G46 -> 35 | H34: ='Insights Livraison'!H46 -> 53 | I34: ='Insights Livraison'!I46 -> 53 | J34: ='Insights Livraison'!J46 -> 62 | K34: ='Insights Livraison'!K46 -> 62 | ... O34: ='Insights Livraison'!O46 -> 26 | P34: =SUM(D34:O34) -> 459 | Q34: ='Insights Livraison'!P46 -> 30 | R34: ='Insights Livraison'!Q46 -> 30 | S34: ='Insights Livraison'!R46 -> 30 | T34: ='Insights Livraison'!S46 -> 30 | U34: ='Insights Livraison'!T46 -> 36 | V34: ='Insights Livraison'!U46 -> 36 | W34: ='Insights Livraison'!V46 -> 36 | X34: ='Insights Livraison'!W46 -> 36 | ... AB34: ='Insights Livraison'!AA46 -> 30 | AC34: =SUM(Q34:AB34) -> 402 | AD34: =SUM('Insights Livraison'!AB46:AM46) -> 546 | AE34: =SUM('Insights Livraison'!AN46:AY46) -> 572
B35: CA - client F | D35: ='Insights Livraison'!D61 -> 0 | E35: ='Insights Livraison'!E61 -> 0 | F35: ='Insights Livraison'!F61 -> 0 | G35: ='Insights Livraison'!G61 -> 0 | H35: ='Insights Livraison'!H61 -> 0 | I35: ='Insights Livraison'!I61 -> 0 | J35: ='Insights Livraison'!J61 -> 0 | K35: ='Insights Livraison'!K61 -> 0 | ... O35: ='Insights Livraison'!O61 -> 0 | P35: =SUM(D35:O35) -> 0 | Q35: ='Insights Livraison'!P61 -> 0 | R35: ='Insights Livraison'!Q61 -> 0 | S35: ='Insights Livraison'!R61 -> 0 | T35: ='Insights Livraison'!S61 -> 0 | U35: ='Insights Livraison'!T61 -> 0 | V35: ='Insights Livraison'!U61 -> 0 | W35: ='Insights Livraison'!V61 -> 0 | X35: ='Insights Livraison'!W61 -> 0 | ... AB35: ='Insights Livraison'!AA61 -> 0 | AC35: =SUM(Q35:AB35) -> 0 | AD35: =SUM('Insights Livraison'!AB61:AM61) -> 0 | AE35: =SUM('Insights Livraison'!AN61:AY61) -> 0
B36: Nombre de client F | D36: ='Insights Livraison'!D47 -> 0 | E36: ='Insights Livraison'!E47 -> 0 | F36: ='Insights Livraison'!F47 -> 0 | G36: ='Insights Livraison'!G47 -> 0 | H36: ='Insights Livraison'!H47 -> 0 | I36: ='Insights Livraison'!I47 -> 0 | J36: ='Insights Livraison'!J47 -> 0 | K36: ='Insights Livraison'!K47 -> 0 | ... O36: ='Insights Livraison'!O47 -> 0 | P36: =SUM(D36:O36) -> 0 | Q36: ='Insights Livraison'!P47 -> 0 | R36: ='Insights Livraison'!Q47 -> 0 | S36: ='Insights Livraison'!R47 -> 0 | T36: ='Insights Livraison'!S47 -> 0 | U36: ='Insights Livraison'!T47 -> 0 | V36: ='Insights Livraison'!U47 -> 0 | W36: ='Insights Livraison'!V47 -> 0 | X36: ='Insights Livraison'!W47 -> 0 | ... AB36: ='Insights Livraison'!AA47 -> 0 | AC36: =SUM(Q36:AB36) -> 0 | AD36: =SUM('Insights Livraison'!AB47:AM47) -> 0 | AE36: =SUM('Insights Livraison'!AN47:AY47) -> 0
B38: Nombre de plats vendues | D38: =D26+D28+D30+D32+D34+D36 -> 0 | E38: =E26+E28+E30+E32+E34+E36 -> 0 | F38: =F26+F28+F30+F32+F34+F36 -> 0 | G38: =G26+G28+G30+G32+G34+G36 -> 214 | H38: =H26+H28+H30+H32+H34+H36 -> 322 | I38: =I26+I28+I30+I32+I34+I36 -> 322 | J38: =J26+J28+J30+J32+J34+J36 -> 376 | K38: =K26+K28+K30+K32+K34+K36 -> 376 | ... O38: =O26+O28+O30+O32+O34+O36 -> 160 | P38: =SUM(D38:O38) -> 2790 | Q38: =Q26+Q28+Q30+Q32+Q34+Q36 -> 216 | R38: =R26+R28+R30+R32+R34+R36 -> 216 | S38: =S26+S28+S30+S32+S34+S36 -> 216 | T38: =T26+T28+T30+T32+T34+T36 -> 216 | U38: =U26+U28+U30+U32+U34+U36 -> 259 | V38: =V26+V28+V30+V32+V34+V36 -> 259 | W38: =W26+W28+W30+W32+W34+W36 -> 259 | X38: =X26+X28+X30+X32+X34+X36 -> 259 | ... AB38: =AB26+AB28+AB30+AB32+AB34+AB36 -> 216 | AC38: =SUM(Q38:AB38) -> 2893 | AD38: =AD26+AD28+AD30+AD32+AD34+AD36 -> 3032 | AE38: =AE26+AE28+AE30+AE32+AE34+AE36 -> 3174
B39: =CONCAT("Chiffre d'Affaires - ",B24) -> Chiffre d'Affaires - Vente-platforme | D39: =D25+D27+D29+D31+D33+D35 -> 0 | E39: =E25+E27+E29+E31+E33+E35 -> 0 | F39: =F25+F27+F29+F31+F33+F35 -> 0 | G39: =G25+G27+G29+G31+G33+G35 -> 3548.15 | H39: =H25+H27+H29+H31+H33+H35 -> 5338.65 | I39: =I25+I27+I29+I31+I33+I35 -> 5338.65 | J39: =J25+J27+J29+J31+J33+J35 -> 6237.8 | K39: =K25+K27+K29+K31+K33+K35 -> 6237.8 | ... O39: =O25+O27+O29+O31+O33+O35 -> 2649 | P39: =SUM(D39:O39) -> 46269.05 | Q39: =Q25+Q27+Q29+Q31+Q33+Q35 -> 3684.207 | R39: =R25+R27+R29+R31+R33+R35 -> 3684.207 | S39: =S25+S27+S29+S31+S33+S35 -> 3684.207 | T39: =T25+T27+T29+T31+T33+T35 -> 3684.207 | U39: =U25+U27+U29+U31+U33+U35 -> 4416.537 | V39: =V25+V27+V29+V31+V33+V35 -> 4416.537 | W39: =W25+W27+W29+W31+W33+W35 -> 4416.537 | X39: =X25+X27+X29+X31+X33+X35 -> 4416.537 | ... AB39: =AB25+AB27+AB29+AB31+AB33+AB35 -> 3684.207 | AC39: =SUM(Q39:AB39) -> 49336.794 | AD39: =AD25+AD27+AD29+AD31+AD33+AD35 -> 54382.477 | AE39: =AE25+AE27+AE29+AE31+AE33+AE35 -> 58662.612
B41: Epicerie
B42: Article | I42: 6500 | P42: =SUM(D42:O42) -> 6500 | V42: 8550 | AC42: =SUM(Q42:AB42) -> 8550 | AD42: 15700 | AE42: 15700
B43: =CONCAT("Chiffre d'Affaires - ",B41) -> Chiffre d'Affaires - Epicerie | D43: =D42 | E43: =E42 | F43: =F42 | G43: =G42 | H43: =H42 | I43: =I42 -> 6500 | J43: =J42 | K43: =K42 | ... O43: =O42 | P43: =SUM(D43:O43) -> 6500 | Q43: =Q42 | R43: =R42 | S43: =S42 | T43: =T42 | U43: =U42 | V43: =V42 -> 8550 | W43: =W42 | X43: =X42 | ... AB43: =AB42 | AC43: =SUM(Q43:AB43) -> 8550 | AD43: =AD42 -> 15700 | AE43: =AE42 -> 15700
A44: ²
B45: Traiteur
B46: Article | N46: 3500 | O46: 3500 | P46: =SUM(D46:O46) -> 7000 | R46: 3125 | U46: 3125 | X46: 3125 | AA46: 3125 | AC46: =SUM(Q46:AB46) -> 12500 | AD46: 12500 | AE46: 13000
B47: =CONCAT("Chiffre d'Affaires - ",B45) -> Chiffre d'Affaires - Traiteur | D47: =D46 | E47: =E46 | F47: =F46 | G47: =G46 | H47: =H46 | I47: =I46 | J47: =J46 | K47: =K46 | ... O47: =O46 -> 3500 | P47: =SUM(D47:O47) -> 7000 | Q47: =Q46 | R47: =R46 -> 3125 | S47: =S46 | T47: =T46 | U47: =U46 -> 3125 | V47: =V46 | W47: =W46 | X47: =X46 -> 3125 | ... AB47: =AB46 | AC47: =SUM(Q47:AB47) -> 12500 | AD47: =AD46 -> 12500 | AE47: =AE46 -> 13000
B49: % couts vs CA Produit A | E49: =(E50-D50)/D50 -> 0.19824887 | F49: =(F50-E50)/E50 -> 0.084744155 | G49: =(G50-F50)/F50 -> 0.3117989 | H49: =(H50-G50)/G50 -> 0.26726581 | I49: =(I50-H50)/H50 -> 0.39729971 | J49: =(J50-I50)/I50 -> -0.094145413 | K49: =(K50-J50)/J50 -> 0 | L49: =(L50-K50)/K50 -> -0.072643496 | ... O49: =(O50-N50)/N50 -> -0.28536894 | R49: =(R50-Q50)/Q50 -> 0.18482577 | S49: =(S50-R50)/R50 -> -0.090020775 | T49: =(T50-S50)/S50 -> 0.21769961 | U49: =(U50-T50)/T50 -> 0.17376935 | V49: =(V50-U50)/U50 -> 0.51269511 | W49: =(W50-V50)/V50 -> -0.14986492 | X49: =(X50-W50)/W50 -> 0.093264054 | Y49: =(Y50-X50)/X50 -> -0.13747349 | ... AB49: =(AB50-AA50)/AA50 -> -0.27770327 | AC49: =(AC50-P50)/P50 -> 0.078905274 | AD49: =(AD50-AC50)/AC50 -> 0.068478385 | AE49: =(AE50-AD50)/AD50 -> 0.12911709
B50: TOTAL CHIFFRE D'AFFAIRES | D50: =D22+D39+D47+D43 -> 11597.682 | E50: =E22+E39+E47+E43 -> 13896.909 | F50: =F22+F39+F47+F43 -> 15074.591 | G50: =G22+G39+G47+G43 -> 19774.832 | H50: =H22+H39+H47+H43 -> 25059.968 | I50: =I22+I39+I47+I43 -> 35016.286 | J50: =J22+J39+J47+J43 -> 31719.664 | K50: =K22+K39+K47+K43 -> 31719.664 | ... AB50: =AB22+AB39+AB47+AB43 -> 16907.815 | AC50: =AC22+AC39+AC43+AC47 -> 307086.46 | AD50: =AD22+AD39+AD43+AD47 -> 328115.24 | AE50: =AE22+AE39+AE43+AE47 -> 370480.53
B51: check % evolution | P51: =IF(SUM(D50:O50)=P50,0,P50-SUM(D50:O50)) -> 0 | AC51: =IF(SUM(Q50:AB50)=AC50,0,AC50-SUM(Q50:AB50)) -> 0
B52: COUTS ACHATS PRODUCTION
B53: Restauration
B54: % Prix final - client A | D54: 0.3 | E54: 0.3 | F54: 0.3 | G54: 0.3 | H54: 0.3 | I54: 0.3 | J54: 0.25 | K54: 0.25 | L54: 0.25 | M54: 0.25 | N54: 0.25 | O54: 0.25 | P54: =AVERAGE(D54:O54) -> 0.275 | Q54: 0.25 | R54: 0.25 | S54: 0.25 | T54: 0.25 | U54: 0.25 | V54: 0.25 | W54: 0.25 | X54: 0.25 | Y54: 0.25 | Z54: 0.25 | AA54: 0.25 | AB54: 0.25 | AC54: =AVERAGE(Q54:AB54) -> 0.25 | AD54: 0.2 | AE54: 0.2
B55: Cout d'achat production | D55: =D8*D54 -> 232.5 | E55: =E8*E54 -> 277.5 | F55: =F8*F54 -> 301.5 | G55: =G8*G54 -> 324 | H55: =H8*H54 -> 394.5 | I55: =I8*I54 -> 463.5 | J55: =J8*J54 -> 425 | K55: =K8*K54 -> 425 | ... O55: =O8*O54 -> 212.5 | P55: =SUM(D55:O55) -> 4079.75 | Q55: =Q8*Q54 -> 218.875 | R55: =R8*R54 -> 218.875 | S55: =S8*S54 -> 240.7625 | T55: =T8*T54 -> 306.425 | U55: =U8*U54 -> 306.425 | V55: =V8*V54 -> 437.75 | W55: =W8*W54 -> 481.525 | X55: =X8*X54 -> 481.525 | ... AB55: =AB8*AB54 -> 218.875 | AC55: =SUM(Q55:AB55) -> 3917.8625 | AD55: =AD8*AD54 -> 3360.9312 | AE55: =AE8*AE54 -> 3874.8099
B56: % Prix final - client B | D56: 0.3 | E56: 0.3 | F56: 0.3 | G56: 0.3 | H56: 0.3 | I56: 0.3 | J56: 0.25 | K56: 0.25 | L56: 0.25 | M56: 0.25 | N56: 0.25 | O56: 0.25 | P56: =AVERAGE(D56:O56) -> 0.275 | Q56: 0.25 | R56: 0.25 | S56: 0.25 | T56: 0.25 | U56: 0.25 | V56: 0.25 | W56: 0.25 | X56: 0.25 | Y56: 0.25 | Z56: 0.25 | AA56: 0.25 | AB56: 0.25 | AC56: =AVERAGE(Q56:AB56) -> 0.25 | AD56: 0.2 | AE56: 0.2
B57: Cout d'achat production | D57: =D10*D56 -> 652.82727 | E57: =E10*E56 -> 782.29091 | F57: =F10*F56 -> 848.4 | G57: =G10*G56 -> 914.50909 | H57: =H10*H56 -> 1110.0818 | I57: =I10*I56 -> 1305.6545 | J57: =J10*J56 -> 1195.9318 | K57: =K10*K56 -> 1195.9318 | ... O57: =O10*O56 -> 599.11364 | P57: =SUM(D57:O57) -> 11487.832 | Q57: =Q10*Q56 -> 680.92364 | R57: =R10*R56 -> 680.92364 | S57: =S10*S56 -> 749.48886 | T57: =T10*T56 -> 952.82023 | U57: =U10*U56 -> 952.82023 | V57: =V10*V56 -> 1361.8473 | W57: =W10*W56 -> 1498.9777 | X57: =X10*X56 -> 1498.9777 | ... AB57: =AB10*AB56 -> 680.92364 | AC57: =SUM(Q57:AB57) -> 12190.425 | AD57: =AD10*AD56 -> 10068.288 | AE57: =AE10*AE56 -> 11606.43
B58: % Prix final - client C | D58: 0.3 | E58: 0.3 | F58: 0.3 | G58: 0.3 | H58: 0.3 | I58: 0.3 | J58: 0.25 | K58: 0.25 | L58: 0.25 | M58: 0.25 | N58: 0.25 | O58: 0.25 | P58: =AVERAGE(D58:O58) -> 0.275 | Q58: 0.25 | R58: 0.25 | S58: 0.25 | T58: 0.25 | U58: 0.25 | V58: 0.25 | W58: 0.25 | X58: 0.25 | Y58: 0.25 | Z58: 0.25 | AA58: 0.25 | AB58: 0.25 | AC58: =AVERAGE(Q58:AB58) -> 0.25 | AD58: 0.25 | AE58: 0.25
B59: Cout d'achat production | D59: =D12*D58 -> 313.09091 | E59: =E12*E58 -> 374.18182 | F59: =F12*F58 -> 404.72727 | G59: =G12*G58 -> 435.27273 | H59: =H12*H58 -> 530.72727 | I59: =I12*I58 -> 622.36364 | J59: =J12*J58 -> 569.54545 | K59: =K12*K58 -> 569.54545 | ... O59: =O12*O58 -> 286.36364 | P59: =SUM(D59:O59) -> 5480.3636 | Q59: =Q12*Q58 -> 367.05455 | R59: =R12*R58 -> 367.05455 | S59: =S12*S58 -> 403.10455 | T59: =T12*T58 -> 514.53182 | U59: =U12*U58 -> 514.53182 | V59: =V12*V58 -> 734.10909 | W59: =W12*W58 -> 806.20909 | X59: =X12*X58 -> 806.20909 | ... AB59: =AB12*AB58 -> 367.05455 | AC59: =SUM(Q59:AB59) -> 6567.6545 | AD59: =AD12*AD58 -> 5525.8423 | AE59: =AE12*AE58 -> 6376.5587
B60: % Prix final - client D | D60: 0.3 | E60: 0.3 | F60: 0.3 | G60: 0.3 | H60: 0.3 | I60: 0.3 | J60: 0.25 | K60: 0.25 | L60: 0.25 | M60: 0.25 | N60: 0.25 | O60: 0.25 | P60: =AVERAGE(D60:O60) -> 0.275 | Q60: 0.25 | R60: 0.25 | S60: 0.25 | T60: 0.25 | U60: 0.25 | V60: 0.25 | W60: 0.25 | X60: 0.25 | Y60: 0.25 | Z60: 0.25 | AA60: 0.25 | AB60: 0.25 | AC60: =AVERAGE(Q60:AB60) -> 0.25 | AD60: 0.25 | AE60: 0.25
B61: Cout d'achat production | D61: =D14*D60 -> 1261.6364 | E61: =E14*E60 -> 1512 | F61: =F14*F60 -> 1639.6364 | G61: =G14*G60 -> 1767.2727 | H61: =H14*H60 -> 2145.2727 | I61: =I14*I60 -> 2523.2727 | J61: =J14*J60 -> 2311.3636 | K61: =K14*K60 -> 2311.3636 | ... O61: =O14*O60 -> 1157.7273 | P61: =SUM(D61:O61) -> 22201.364 | Q61: =Q14*Q60 -> 1137.6818 | R61: =R14*R60 -> 1137.6818 | S61: =S14*S60 -> 1251.45 | T61: =T14*T60 -> 1592.7545 | U61: =U14*U60 -> 1592.7545 | V61: =V14*V60 -> 2275.3636 | W61: =W14*W60 -> 2502.9 | X61: =X14*X60 -> 2502.9 | ... AB61: =AB14*AB60 -> 1137.6818 | AC61: =SUM(Q61:AB61) -> 20364.505 | AD61: =AD14*AD60 -> 21769.668 | AE61: =AE14*AE60 -> 25104.906
B62: % Prix final - client E | D62: 0.3 | E62: 0.3 | F62: 0.3 | G62: 0.3 | H62: 0.3 | I62: 0.3 | J62: 0.25 | K62: 0.25 | L62: 0.25 | M62: 0.25 | N62: 0.25 | O62: 0.25 | P62: =AVERAGE(D62:O62) -> 0.275 | Q62: 0.25 | R62: 0.25 | S62: 0.25 | T62: 0.25 | U62: 0.25 | V62: 0.25 | W62: 0.25 | X62: 0.25 | Y62: 0.25 | Z62: 0.25 | AA62: 0.25 | AB62: 0.25 | AC62: =AVERAGE(Q62:AB62) -> 0.25 | AD62: 0.25 | AE62: 0.25
B63: Cout d'achat production | D63: =D16*D62 -> 1019.25 | E63: =E16*E62 -> 1223.1 | F63: =F16*F62 -> 1328.1136 | G63: =G16*G62 -> 1426.95 | H63: =H16*H62 -> 1735.8136 | I63: =I16*I62 -> 2038.5 | J63: =J16*J62 -> 1868.625 | K63: =K16*K62 -> 1868.625 | ... O63: =O16*O62 -> 936.88636 | P63: =SUM(D63:O63) -> 17950.125 | Q63: =Q16*Q62 -> 901.36705 | R63: =R16*R62 -> 901.36705 | S63: =S16*S62 -> 991.50375 | T63: =T16*T62 -> 1261.9139 | U63: =U16*U62 -> 1261.9139 | V63: =V16*V62 -> 1802.7341 | W63: =W16*W62 -> 1983.0075 | X63: =X16*X62 -> 1983.0075 | ... AB63: =AB16*AB62 -> 901.36705 | AC63: =SUM(Q63:AB63) -> 16134.47 | AD63: =AD16*AD62 -> 17301.157 | AE63: =AE16*AE62 -> 19946.465
B64: % Prix final - client F | D64: 0.3 | E64: 0.3 | F64: 0.3 | G64: 0.3 | H64: 0.3 | I64: 0.3 | J64: 0.25 | K64: 0.25 | L64: 0.25 | M64: 0.25 | N64: 0.25 | O64: 0.25 | P64: =AVERAGE(D64:O64) -> 0.275 | Q64: 0.25 | R64: 0.25 | S64: 0.25 | T64: 0.25 | U64: 0.25 | V64: 0.25 | W64: 0.25 | X64: 0.25 | Y64: 0.25 | Z64: 0.25 | AA64: 0.25 | AB64: 0.25 | AC64: =AVERAGE(Q64:AB64) -> 0.25 | AD64: 0.25 | AE64: 0.25
B65: Cout d'achat production | D65: =D18*D64 -> 0 | E65: =E18*E64 -> 0 | F65: =F18*F64 -> 0 | G65: =G18*G64 -> 0 | H65: =H18*H64 -> 0 | I65: =I18*I64 -> 0 | J65: =J18*J64 -> 0 | K65: =K18*K64 -> 0 | ... O65: =O18*O64 -> 0 | P65: =SUM(D65:O65) -> 0 | Q65: =Q18*Q64 -> 0 | R65: =R18*R64 -> 0 | S65: =S18*S64 -> 0 | T65: =T18*T64 -> 0 | U65: =U18*U64 -> 0 | V65: =V18*V64 -> 0 | W65: =W18*W64 -> 0 | X65: =X18*X64 -> 0 | ... AB65: =AB18*AB64 -> 0 | AC65: =SUM(Q65:AB65) -> 0 | AD65: =AD18*AD64 -> 0 | AE65: =AE18*AE64 -> 0
B67: =CONCAT("Cout Achats - ",B53) -> Cout Achats - Restauration | D67: =D55+D57+D59+D61+D63+D65 -> 3479.3045 | E67: =E55+E57+E59+E61+E63+E65 -> 4169.0727 | F67: =F55+F57+F59+F61+F63+F65 -> 4522.3773 | G67: =G55+G57+G59+G61+G63+G65 -> 4868.0045 | H67: =H55+H57+H59+H61+H63+H65 -> 5916.3955 | I67: =I55+I57+I59+I61+I63+I65 -> 6953.2909 | J67: =J55+J57+J59+J61+J63+J65 -> 6370.4659 | K67: =K55+K57+K59+K61+K63+K65 -> 6370.4659 | ... O67: =O55+O57+O59+O61+O63+O65 -> 3192.5909 | P67: =SUM(D67:O67) -> 61199.434 | Q67: =Q55+Q57+Q59+Q61+Q63+Q65 -> 3305.902 | R67: =R55+R57+R59+R61+R63+R65 -> 3305.902 | S67: =S55+S57+S59+S61+S63+S65 -> 3636.3097 | T67: =T55+T57+T59+T61+T63+T65 -> 4628.4455 | U67: =U55+U57+U59+U61+U63+U65 -> 4628.4455 | V67: =V55+V57+V59+V61+V63+V65 -> 6611.8041 | W67: =W55+W57+W59+W61+W63+W65 -> 7272.6193 | X67: =X55+X57+X59+X61+X63+X65 -> 7272.6193 | ... AB67: =AB55+AB57+AB59+AB61+AB63+AB65 -> 3305.902 | AC67: =SUM(Q67:AB67) -> 59174.916 | AD67: =AD55+AD57+AD59+AD61+AD63+AD65 -> 58025.887 | AE67: =AE55+AE57+AE59+AE61+AE63+AE65 -> 66909.169
B68: % couts vs CA Produit A | D68: =IFERROR(D67/D22,0) -> 0.3 | E68: =IFERROR(E67/E22,0) -> 0.3 | F68: =IFERROR(F67/F22,0) -> 0.3 | G68: =IFERROR(G67/G22,0) -> 0.3 | H68: =IFERROR(H67/H22,0) -> 0.3 | I68: =IFERROR(I67/I22,0) -> 0.3 | J68: =IFERROR(J67/J22,0) -> 0.25 | K68: =IFERROR(K67/K22,0) -> 0.25 | ... AE68: =IFERROR(AE67/AE22,0) -> 0.23632969
A69: ²
B70: Livraison / A Emporter
B71: % Cout Composant 1 / Prix final - Produit B
B72: % Cout Composant 2 / Prix final - Produit B
B73: …
B74: Total Cout Unitaire B | D74: 0 | E74: 0 | F74: 0 | G74: 0 | H74: 0 | I74: 0 | J74: 0 | K74: 0 | L74: 0 | M74: 0 | N74: 0 | O74: 0 | Q74: 0 | R74: 0 | S74: 0 | T74: 0 | U74: 0 | V74: 0 | W74: 0 | X74: 0 | Y74: 0 | Z74: 0 | AA74: 0 | AB74: 0
B75: =CONCAT("Cout Achats - ",B70) -> Cout Achats - Livraison / A Emporter | D75: =D74 -> 0 | E75: =E74 -> 0 | F75: =F74 -> 0 | G75: =G39*30% -> 1064.445 | H75: =H39*30% -> 1601.595 | I75: =I39*30% -> 1601.595 | J75: =J39*30% -> 1871.34 | K75: =K39*30% -> 1871.34 | L75: =L39*30% -> 1871.34 | M75: =M39*30% -> 1871.34 | N75: =N39*30% -> 1333.02 | O75: =O39*30% -> 794.7 | P75: =SUM(D75:O75) -> 13880.715 | Q75: =Q39*30% -> 1105.2621 | R75: =R39*30% -> 1105.2621 | S75: =S39*30% -> 1105.2621 | T75: =T39*30% -> 1105.2621 | U75: =U39*30% -> 1324.9611 | V75: =V39*30% -> 1324.9611 | W75: =W39*30% -> 1324.9611 | X75: =X39*30% -> 1324.9611 | ... AB75: =AB39*30% -> 1105.2621 | AC75: =SUM(Q75:AB75) -> 14801.038 | AD75: =AD39*30% -> 16314.743 | AE75: =AE39*30% -> 17598.784
B76: % couts vs CA Produit B | D76: =IFERROR(D75/D39,0) -> 0 | E76: =IFERROR(E75/E39,0) -> 0 | F76: =IFERROR(F75/F39,0) -> 0 | G76: =IFERROR(G75/G39,0) -> 0.3 | H76: =IFERROR(H75/H39,0) -> 0.3 | I76: =IFERROR(I75/I39,0) -> 0.3 | J76: =IFERROR(J75/J39,0) -> 0.3 | K76: =IFERROR(K75/K39,0) -> 0.3 | ... AE76: =IFERROR(AE75/AE39,0) -> 0.3
B78: Epicerie
B79: % Cout Composant 1 / Prix final - Service C
B80: % Cout Composant 2 / Prix final - Service C
B81: …
B82: Total Cout Unitaire C | D82: 0 | E82: 0 | F82: 0 | G82: 0 | H82: 0 | I82: 0 | J82: 0 | K82: 0 | L82: 0 | M82: 0 | N82: 0 | O82: 0 | Q82: 0 | R82: 0 | S82: 0 | T82: 0 | U82: 0 | V82: 0 | W82: 0 | X82: 0 | Y82: 0 | Z82: 0 | AA82: 0 | AB82: 0
B83: =CONCAT("Cout Achats - ",B78) -> Cout Achats - Epicerie | D83: =D82 -> 0 | E83: =E82 -> 0 | F83: =F82 -> 0 | G83: =G82 -> 0 | H83: =H82 -> 0 | I83: =I82 -> 0 | J83: =J82 -> 0 | K83: =K82 -> 0 | ... O83: =O82 -> 0 | P83: =SUM(D83:O83) -> 0 | Q83: =Q82 -> 0 | R83: =R82 -> 0 | S83: =S82 -> 0 | T83: =T82 -> 0 | U83: =U82 -> 0 | V83: =V82 -> 0 | W83: =W82 -> 0 | X83: =X82 -> 0 | ... AB83: =AB82 -> 0 | AC83: =SUM(Q83:AB83) -> 0 | AD83: =AD82 | AE83: =AE82
B84: % couts vs CA Service C | D84: =IFERROR(D83/D43,0) -> 0 | E84: =IFERROR(E83/E43,0) -> 0 | F84: =IFERROR(F83/F43,0) -> 0 | G84: =IFERROR(G83/G43,0) -> 0 | H84: =IFERROR(H83/H43,0) -> 0 | I84: =IFERROR(I83/I43,0) -> 0 | J84: =IFERROR(J83/J43,0) -> 0 | K84: =IFERROR(K83/K43,0) -> 0 | ... O84: =IFERROR(O83/O43,0) -> 0 | P84: =IFERROR(P83/P44,0) -> 0 | Q84: =IFERROR(Q83/Q43,0) -> 0 | R84: =IFERROR(R83/R43,0) -> 0 | S84: =IFERROR(S83/S43,0) -> 0 | T84: =IFERROR(T83/T43,0) -> 0 | U84: =IFERROR(U83/U43,0) -> 0 | V84: =IFERROR(V83/V43,0) -> 0 | W84: =IFERROR(W83/W43,0) -> 0 | X84: =IFERROR(X83/X43,0) -> 0 | ... AE84: =IFERROR(AE83/AE43,0) -> 0
A85: ²
B86: Traiteur
B87: % Couts prestations / Prix final - Service D
B88: % Couts fixes / Prix final - Service D
B89: …
B90: Total Cout Unitaire D | D90: 0 | E90: 0 | F90: 0 | G90: 0 | H90: 0 | I90: 0 | J90: 0 | K90: 0 | L90: 0 | M90: 0 | N90: 0 | O90: 0 | P90: =SUM(D90:O90) -> 0 | Q90: 0 | R90: 0 | S90: 0 | T90: 0 | U90: 0 | V90: 0 | W90: 0 | X90: 0 | Y90: 0 | Z90: 0 | AA90: 0 | AB90: 0 | AC90: =SUM(Q90:AB90) -> 0 | AD90: 0 | AE90: 0
B91: =CONCAT("Cout Achats - ",B86) -> Cout Achats - Traiteur | D91: =D90 -> 0 | E91: =E90 -> 0 | F91: =F90 -> 0 | G91: =G90 -> 0 | H91: =H90 -> 0 | I91: =I90 -> 0 | J91: =J90 -> 0 | K91: =K90 -> 0 | ... O91: =O90 -> 0 | P91: =SUM(D91:O91) -> 0 | Q91: =Q90 -> 0 | R91: =R90 -> 0 | S91: =S90 -> 0 | T91: =T90 -> 0 | U91: =U90 -> 0 | V91: =V90 -> 0 | W91: =W90 -> 0 | X91: =X90 -> 0 | ... AB91: =AB90 -> 0 | AC91: =SUM(Q91:AB91) -> 0 | AD91: =AD90 -> 0 | AE91: =AE90 -> 0
B92: % couts vs CA Service D | D92: =IFERROR(D91/D47,0) -> 0 | E92: =IFERROR(E91/E47,0) -> 0 | F92: =IFERROR(F91/F47,0) -> 0 | G92: =IFERROR(G91/G47,0) -> 0 | H92: =IFERROR(H91/H47,0) -> 0 | I92: =IFERROR(I91/I47,0) -> 0 | J92: =IFERROR(J91/J47,0) -> 0 | K92: =IFERROR(K91/K47,0) -> 0 | ... AE92: =IFERROR(AE91/AE47,0) -> 0
B94: TOTAL COUTS ACHATS PRODUCTION | D94: =D67+D75+D83+D91 -> 3479.3045 | E94: =E67+E75+E83+E91 -> 4169.0727 | F94: =F67+F75+F83+F91 -> 4522.3773 | G94: =G67+G75+G83+G91 -> 5932.4495 | H94: =H67+H75+H83+H91 -> 7517.9905 | I94: =I67+I75+I83+I91 -> 8554.8859 | J94: =J67+J75+J83+J91 -> 8241.8059 | K94: =K67+K75+K83+K91 -> 8241.8059 | ... AE94: =AE67+AE75+AE83+AE91 -> 84507.953
B95: % Cout Achats vs CA | D95: =IFERROR(D94/D50,0) -> 0.3 | E95: =IFERROR(E94/E50,0) -> 0.3 | F95: =IFERROR(F94/F50,0) -> 0.3 | G95: =IFERROR(G94/G50,0) -> 0.3 | H95: =IFERROR(H94/H50,0) -> 0.3 | I95: =IFERROR(I94/I50,0) -> 0.24431163 | J95: =IFERROR(J94/J50,0) -> 0.2598327 | K95: =IFERROR(K94/K50,0) -> 0.2598327 | ... AE95: =IFERROR(AE94/AE50,0) -> 0.22810363
O96: check | P96: =IF(SUM(D94:O94)=P94,0,P94-SUM(D94:O94)) -> 0 | AC96: =IF(SUM(Q94:AB94)=AC94,0,AC94-SUM(Q94:AB94)) -> 0
B97: COUTS SALARIAUX PRODUCTION
B98: Total Effectifs - Production | D98: =Personnel!D34 -> 1 | E98: =Personnel!E34 -> 1 | F98: =Personnel!F34 -> 1 | G98: =Personnel!G34 -> 1 | H98: =Personnel!H34 -> 1 | I98: =Personnel!I34 -> 1 | J98: =Personnel!J34 -> 1 | K98: =Personnel!K34 -> 1 | ... AE98: =Personnel!AE34 -> 1
B99: Salaires bruts - Production | D99: =Personnel!D35+Personnel!D36 -> 2200 | E99: =Personnel!E35+Personnel!E36 -> 2200 | F99: =Personnel!F35+Personnel!F36 -> 2200 | G99: =Personnel!G35+Personnel!G36 -> 2200 | H99: =Personnel!H35+Personnel!H36 -> 2700 | I99: =Personnel!I35+Personnel!I36 -> 2700 | J99: =Personnel!J35+Personnel!J36 -> 2700 | K99: =Personnel!K35+Personnel!K36 -> 2700 | ... O99: =Personnel!O35+Personnel!O36 -> 2200 | P99: =Personnel!P36 -> 3000 | Q99: =Personnel!Q35+Personnel!Q36 -> 2200 | R99: =Personnel!R35+Personnel!R36 -> 2200 | S99: =Personnel!S35+Personnel!S36 -> 2200 | T99: =Personnel!T35+Personnel!T36 -> 2200 | U99: =Personnel!U35+Personnel!U36 -> 2700 | V99: =Personnel!V35+Personnel!V36 -> 2700 | W99: =Personnel!W35+Personnel!W36 -> 2700 | X99: =Personnel!X35+Personnel!X36 -> 2700 | ... AE99: =Personnel!AE35+Personnel!AE36 -> 32413.5
B100: Charges sociales - Production | D100: =Personnel!D37 -> 990 | E100: =Personnel!E37 -> 990 | F100: =Personnel!F37 -> 990 | G100: =Personnel!G37 -> 990 | H100: =Personnel!H37 -> 990 | I100: =Personnel!I37 -> 990 | J100: =Personnel!J37 -> 990 | K100: =Personnel!K37 -> 990 | ... AE100: =Personnel!AE37 -> 13097.7
B101: Sous traitance - Production | D101: =Personnel!D38 -> 0 | E101: =Personnel!E38 -> 0 | F101: =Personnel!F38 -> 0 | G101: =Personnel!G38 -> 0 | H101: =Personnel!H38 -> 0 | I101: =Personnel!I38 -> 0 | J101: =Personnel!J38 -> 0 | K101: =Personnel!K38 -> 0 | ... AE101: =Personnel!AE38 -> 0
B102: TOTAL COÛTS DE PERSONNEL - PRODUCTION | D102: =Personnel!D39 -> 3190 | E102: =Personnel!E39 -> 3190 | F102: =Personnel!F39 -> 3190 | G102: =Personnel!G39 -> 3190 | H102: =Personnel!H39 -> 3690 | I102: =Personnel!I39 -> 3690 | J102: =Personnel!J39 -> 3690 | K102: =Personnel!K39 -> 3690 | ... AE102: =Personnel!AE39 -> 45511.2
B103: % Cout main d'œuvre de production | D103: =IFERROR(D102/D50,0) -> 0.27505497 | E103: =IFERROR(E102/E50,0) -> 0.22954745 | F103: =IFERROR(F102/F50,0) -> 0.21161437 | G103: =IFERROR(G102/G50,0) -> 0.16131616 | H103: =IFERROR(H102/H50,0) -> 0.1472468 | I103: =IFERROR(I102/I50,0) -> 0.10537954 | J103: =IFERROR(J102/J50,0) -> 0.11633162 | K103: =IFERROR(K102/K50,0) -> 0.11633162 | ... AE103: =IFERROR(AE102/AE50,0) -> 0.1228437
O104: check | P104: =IF(SUM(D102:O102)=P102,0,P102-SUM(D102:O102)) -> 0 | AC104: =IF(SUM(Q102:AB102)=AC102,0,AC102-SUM(Q102:AB102)) -> 0
B105: MARGE BRUTE
B106: Total Chiffre d'Affaires | D106: =D50 -> 11597.682 | E106: =E50 -> 13896.909 | F106: =F50 -> 15074.591 | G106: =G50 -> 19774.832 | H106: =H50 -> 25059.968 | I106: =I50 -> 35016.286 | J106: =J50 -> 31719.664 | K106: =K50 -> 31719.664 | ... AE106: =AE50 -> 370480.53
B107: Total Coûts Production | D107: =D102+D94 -> 6669.3045 | E107: =E102+E94 -> 7359.0727 | F107: =F102+F94 -> 7712.3773 | G107: =G102+G94 -> 9122.4495 | H107: =H102+H94 -> 11207.99 | I107: =I102+I94 -> 12244.886 | J107: =J102+J94 -> 11931.806 | K107: =K102+K94 -> 11931.806 | ... AE107: =AE102+AE94 -> 130019.15
B108: MARGE BRUTE | D108: =D50-D107 -> 4928.3773 | E108: =E50-E107 -> 6537.8364 | F108: =F50-F107 -> 7362.2136 | G108: =G50-G107 -> 10652.382 | H108: =H50-H107 -> 13851.978 | I108: =I50-I107 -> 22771.4 | J108: =J50-J107 -> 19787.858 | K108: =K50-K107 -> 19787.858 | ... O108: =O50-O107 -> 11742.073 | P108: =P106-P107 -> 168267.67 | Q108: =Q50-Q107 -> 9306.651 | R108: =R50-R107 -> 12431.651 | S108: =S50-S107 -> 10297.874 | T108: =T50-T107 -> 13274.281 | U108: =U50-U107 -> 16411.912 | V108: =V50-V107 -> 27786.988 | W108: =W50-W107 -> 21219.434 | X108: =X50-X107 -> 24344.434 | ... AB108: =AB50-AB107 -> 9306.651 | AC108: =AC106-AC107 -> 191830.5 | AD108: =AD106-AD107 -> 210430.61 | AE108: =AE106-AE107 -> 240461.38
B109: % Marge | D109: =IFERROR(D108/D50,0) -> 0.42494503 | E109: =IFERROR(E108/E50,0) -> 0.47045255 | F109: =IFERROR(F108/F50,0) -> 0.48838563 | G109: =IFERROR(G108/G50,0) -> 0.53868384 | H109: =IFERROR(H108/H50,0) -> 0.5527532 | I109: =IFERROR(I108/I50,0) -> 0.65030884 | J109: =IFERROR(J108/J50,0) -> 0.62383567 | K109: =IFERROR(K108/K50,0) -> 0.62383567 | ... AE109: =IFERROR(AE108/AE50,0) -> 0.64905267
O110: check | P110: =IF(SUM(D108:O108)=P108,0,P108-SUM(D108:O108)) -> 0 | AC110: =IF(SUM(Q108:AB108)=AC108,0,AC108-SUM(Q108:AB108)) -> 0
...

Sheet Personnel
B2: PERSONNEL
D4: =YEAR(date_début) -> 2025 | Q4: =YEAR(EDATE(date_début,12)) -> 2026 | AD4: =YEAR(EDATE(date_début,24)) -> 2027 | AE4: =YEAR(EDATE(date_début,36)) -> 2028
D5: Jan | E5: Fév | F5: Mar | G5: Avr | H5: Mai | I5: Juin | J5: Juil | K5: Aout | L5: Sept | M5: Oct | N5: Nov | O5: Déc | Q5: Jan | R5: Fév | S5: Mar | T5: Avr | U5: Mai | V5: Juin | W5: Juil | X5: Aout | Y5: Sept | Z5: Oct | AA5: Nov | AB5: Déc
C6: Salaires
B7: EQUIPE DE DIRECTION | C7: Annuel
B8: Directeurs généraux | C8: 25000 | D8: 1 | E8: 1 | F8: 1 | G8: 1 | H8: 1 | I8: 1 | J8: 1 | K8: 1 | L8: 1 | M8: 1 | N8: 1 | O8: 1 | P8: =SUM(D8:O8)/12 -> 1 | Q8: 1 | R8: 1 | S8: 1 | T8: 1 | U8: 1 | V8: 1 | W8: 1 | X8: 1 | Y8: 1 | Z8: 1 | AA8: 1 | AB8: 1 | AC8: =SUM(Q8:AB8)/12 -> 1 | AD8: 1 | AE8: 1
B9: Assistants - Direction | P9: =SUM(D9:O9)/12 -> 0 | AC9: =SUM(Q9:AB9)/12 -> 0
B10: Total Effectifs - Direction | D10: =SUM(D8:D9) -> 1 | E10: =SUM(E8:E9) -> 1 | F10: =SUM(F8:F9) -> 1 | G10: =SUM(G8:G9) -> 1 | H10: =SUM(H8:H9) -> 1 | I10: =SUM(I8:I9) -> 1 | J10: =SUM(J8:J9) -> 1 | K10: =SUM(K8:K9) -> 1 | ... AE10: =SUM(AE8:AE9) -> 1
B11: Salaires bruts - Direction | D11: =SUMPRODUCT($C8:$C9,D8:D9)/12 -> 2083.3333 | E11: =SUMPRODUCT($C8:$C9,E8:E9)/12 -> 2083.3333 | F11: =SUMPRODUCT($C8:$C9,F8:F9)/12 -> 2083.3333 | G11: =SUMPRODUCT($C8:$C9,G8:G9)/12 -> 2083.3333 | H11: =SUMPRODUCT($C8:$C9,H8:H9)/12 -> 2083.3333 | I11: =SUMPRODUCT($C8:$C9,I8:I9)/12 -> 2083.3333 | J11: =SUMPRODUCT($C8:$C9,J8:J9)/12 -> 2083.3333 | K11: =SUMPRODUCT($C8:$C9,K8:K9)/12 -> 2083.3333 | ... O11: =SUMPRODUCT($C8:$C9,O8:O9)/12 -> 2083.3333 | P11: =SUM(D11:O11) -> 25000 | Q11: =SUMPRODUCT($C8:$C9,Q8:Q9)/12 -> 2083.3333 | R11: =SUMPRODUCT($C8:$C9,R8:R9)/12 -> 2083.3333 | S11: =SUMPRODUCT($C8:$C9,S8:S9)/12 -> 2083.3333 | T11: =SUMPRODUCT($C8:$C9,T8:T9)/12 -> 2083.3333 | U11: =SUMPRODUCT($C8:$C9,U8:U9)/12 -> 2083.3333 | V11: =SUMPRODUCT($C8:$C9,V8:V9)/12 -> 2083.3333 | W11: =SUMPRODUCT($C8:$C9,W8:W9)/12 -> 2083.3333 | X11: =SUMPRODUCT($C8:$C9,X8:X9)/12 -> 2083.3333 | ... AB11: =SUMPRODUCT($C8:$C9,AB8:AB9)/12 -> 2083.3333 | AC11: =SUM(Q11:AB11) -> 25000 | AD11: =SUMPRODUCT($C8:$C9,AD8:AD9)*(1+Inflation_salaires)^2 -> 27562.5 | AE11: =SUMPRODUCT($C8:$C9,AE8:AE9)*(1+Inflation_salaires)^3 -> 28940.625
B12: Charges sociales - Direction | D12: =D11*Taux_charges_sociales -> 937.5 | E12: =E11*Taux_charges_sociales -> 937.5 | F12: =F11*Taux_charges_sociales -> 937.5 | G12: =G11*Taux_charges_sociales -> 937.5 | H12: =H11*Taux_charges_sociales -> 937.5 | I12: =I11*Taux_charges_sociales -> 937.5 | J12: =J11*Taux_charges_sociales -> 937.5 | K12: =K11*Taux_charges_sociales -> 937.5 | ... O12: =O11*Taux_charges_sociales -> 937.5 | P12: =SUM(D12:O12) -> 11250 | Q12: =Q11*Taux_charges_sociales -> 937.5 | R12: =R11*Taux_charges_sociales -> 937.5 | S12: =S11*Taux_charges_sociales -> 937.5 | T12: =T11*Taux_charges_sociales -> 937.5 | U12: =U11*Taux_charges_sociales -> 937.5 | V12: =V11*Taux_charges_sociales -> 937.5 | W12: =W11*Taux_charges_sociales -> 937.5 | X12: =X11*Taux_charges_sociales -> 937.5 | ... AE12: =AE11*Taux_charges_sociales -> 13023.281
B13: Total Coûts de personnel - Direction | D13: =SUM(D11:D12) -> 3020.8333 | E13: =SUM(E11:E12) -> 3020.8333 | F13: =SUM(F11:F12) -> 3020.8333 | G13: =SUM(G11:G12) -> 3020.8333 | H13: =SUM(H11:H12) -> 3020.8333 | I13: =SUM(I11:I12) -> 3020.8333 | J13: =SUM(J11:J12) -> 3020.8333 | K13: =SUM(K11:K12) -> 3020.8333 | ... O13: =SUM(O11:O12) -> 3020.8333 | P13: =SUM(D13:O13) -> 36250 | Q13: =SUM(Q11:Q12) -> 3020.8333 | R13: =SUM(R11:R12) -> 3020.8333 | S13: =SUM(S11:S12) -> 3020.8333 | T13: =SUM(T11:T12) -> 3020.8333 | U13: =SUM(U11:U12) -> 3020.8333 | V13: =SUM(V11:V12) -> 3020.8333 | W13: =SUM(W11:W12) -> 3020.8333 | X13: =SUM(X11:X12) -> 3020.8333 | ... AB13: =SUM(AB11:AB12) -> 3020.8333 | AC13: =SUM(Q13:AB13) -> 36250 | AD13: =SUM(AD11:AD12) -> 39965.625 | AE13: =SUM(AE11:AE12) -> 41963.906
B14: Part du salaire immobilisé en R&D - Hors Production | D14: =-((($C$8*D8)*Taux_charges_sociales)*Salaires_Immob_DG)/12 -> 0 | E14: =-((($C$8*E8)*Taux_charges_sociales)*Salaires_Immob_DG)/12 -> 0 | F14: =-((($C$8*F8)*Taux_charges_sociales)*Salaires_Immob_DG)/12 -> 0 | G14: =-((($C$8*G8)*Taux_charges_sociales)*Salaires_Immob_DG)/12 -> 0 | H14: =-((($C$8*H8)*Taux_charges_sociales)*Salaires_Immob_DG)/12 -> 0 | I14: =-((($C$8*I8)*Taux_charges_sociales)*Salaires_Immob_DG)/12 -> 0 | J14: =-((($C$8*J8)*Taux_charges_sociales)*Salaires_Immob_DG)/12 -> 0 | K14: =-((($C$8*K8)*Taux_charges_sociales)*Salaires_Immob_DG)/12 -> 0 | ... O14: =-((($C$8*O8)*Taux_charges_sociales)*Salaires_Immob_DG)/12 -> 0 | P14: =SUM(D14:O14) -> 0 | Q14: =-((($C$8*Q8)*Taux_charges_sociales)*Salaires_Immob_DG)/12 -> 0 | R14: =-((($C$8*R8)*Taux_charges_sociales)*Salaires_Immob_DG)/12 -> 0 | S14: =-((($C$8*S8)*Taux_charges_sociales)*Salaires_Immob_DG)/12 -> 0 | T14: =-((($C$8*T8)*Taux_charges_sociales)*Salaires_Immob_DG)/12 -> 0 | U14: =-((($C$8*U8)*Taux_charges_sociales)*Salaires_Immob_DG)/12 -> 0 | V14: =-((($C$8*V8)*Taux_charges_sociales)*Salaires_Immob_DG)/12 -> 0 | W14: =-((($C$8*W8)*Taux_charges_sociales)*Salaires_Immob_DG)/12 -> 0 | X14: =-((($C$8*X8)*Taux_charges_sociales)*Salaires_Immob_DG)/12 -> 0 | ... AB14: =-((($C$8*AB8)*Taux_charges_sociales)*Salaires_Immob_DG)/12 -> 0 | AC14: =SUM(Q14:AB14) -> 0 | AD14: =-((($C$8*AD8)*Taux_charges_sociales)*Salaires_Immob_DG) -> 0 | AE14: =-((($C$8*AE8)*Taux_charges_sociales)*Salaires_Immob_DG) -> 0
O15: check | P15: =IF(SUM(D13:O13)=P13,0,P13-SUM(D13:O13)) -> 0 | AC15: =IF(SUM(Q13:AB13)=AC13,0,AC13-SUM(Q13:AB13)) -> 0
B16: EQUIPE DE RESTAURATION - CDD/CDI | C16: Mensuel
B17: Polyvalent/ cuisinier | C17: 2200 | D17: 1 | E17: 1 | F17: 1 | G17: 1 | H17: 1 | I17: 1 | J17: 1 | K17: 1 | L17: 1 | M17: 1 | N17: 1 | O17: 1 | P17: =SUM(D17:O17)/12 -> 1 | Q17: 1 | R17: 1 | S17: 1 | T17: 1 | U17: 1 | V17: 1 | W17: 1 | X17: 1 | Y17: 1 | Z17: 1 | AA17: 1 | AB17: 1 | AC17: =SUM(Q17:AB17)/12 -> 1 | AD17: 1 | AE17: 1
B18: Polyvalent | C18: 1800 | AC18: =SUM(Q18:AB18)/12 -> 0
AC19: =SUM(Q19:AB19)/12 -> 0 | AD19: =AD1
AC20: =SUM(Q20:AB20)/12 -> 0
AC21: =SUM(Q21:AB21)/12 -> 0
AC22: =SUM(Q22:AB22)/12 -> 0
B26: EQUIPE DE RESTAURATION - HORAIRE | C26: Horaire
B27: vacataire Estival | C27: 12.5 | H27: 40 | I27: 40 | J27: 40 | K27: 40 | L27: 40 | M27: 40 | P27: =SUM(D27:O27)/12 -> 20 | U27: 40 | V27: 40 | W27: 40 | X27: 40 | Y27: 40 | Z27: 40 | AC27: =SUM(Q27:AB27)/12 -> 20 | AD27: 20 | AE27: 20
B28: vacataire midi | AE28: 20
P29: =SUM(D29:O29)/12 -> 0
P30: =SUM(D30:O30)/12 -> 0
B33: Personnel sous traité - Restauration
B34: Total Effectifs - Production fixe | D34: =COUNTIF(D17:D25,"<>") -> 1 | E34: =COUNTIF(E17:E25,"<>") -> 1 | F34: =COUNTIF(F17:F25,"<>") -> 1 | G34: =COUNTIF(G17:G25,"<>") -> 1 | H34: =COUNTIF(H17:H25,"<>") -> 1 | I34: =COUNTIF(I17:I25,"<>") -> 1 | J34: =COUNTIF(J17:J25,"<>") -> 1 | K34: =COUNTIF(K17:K25,"<>") -> 1 | ... AE34: =COUNTIF(AE17:AE25,"<>") -> 1
B35: Salaires bruts - Production - CDI/CDD | D35: =SUMPRODUCT($C17:$C25,D17:D25) -> 2200 | E35: =SUMPRODUCT($C17:$C25,E17:E25) -> 2200 | F35: =SUMPRODUCT($C17:$C25,F17:F25) -> 2200 | G35: =SUMPRODUCT($C17:$C25,G17:G25) -> 2200 | H35: =SUMPRODUCT($C17:$C25,H17:H25) -> 2200 | I35: =SUMPRODUCT($C17:$C25,I17:I25) -> 2200 | J35: =SUMPRODUCT($C17:$C25,J17:J25) -> 2200 | K35: =SUMPRODUCT($C17:$C25,K17:K25) -> 2200 | ... O35: =SUMPRODUCT($C17:$C25,O17:O25) -> 2200 | P35: =SUM(D35:O35) -> 26400 | Q35: =SUMPRODUCT($C17:$C25,Q17:Q25) -> 2200 | R35: =SUMPRODUCT($C17:$C25,R17:R25) -> 2200 | S35: =SUMPRODUCT($C17:$C25,S17:S25) -> 2200 | T35: =SUMPRODUCT($C17:$C25,T17:T25) -> 2200 | U35: =SUMPRODUCT($C17:$C25,U17:U25) -> 2200 | V35: =SUMPRODUCT($C17:$C25,V17:V25) -> 2200 | W35: =SUMPRODUCT($C17:$C25,W17:W25) -> 2200 | X35: =SUMPRODUCT($C17:$C25,X17:X25) -> 2200 | ... AB35: =SUMPRODUCT($C17:$C25,AB17:AB25) -> 2200 | AC35: =SUM(Q35:AB35) -> 26400 | AD35: =SUMPRODUCT($C16:$C25,AD16:AD25)*(1+Inflation_salaires)*12 -> 27720 | AE35: =SUMPRODUCT($C16:$C25,AE16:AE25)*(1+Inflation_salaires)^2*12 -> 29106
B36: Salaires bruts - Production - HORAIRE | D36: =SUMPRODUCT($C27:$C33,D27:D33) -> 0 | E36: =SUMPRODUCT($C27:$C33,E27:E33) -> 0 | F36: =SUMPRODUCT($C27:$C33,F27:F33) -> 0 | G36: =SUMPRODUCT($C27:$C33,G27:G33) -> 0 | H36: =SUMPRODUCT($C27:$C33,H27:H33) -> 500 | I36: =SUMPRODUCT($C27:$C33,I27:I33) -> 500 | J36: =SUMPRODUCT($C27:$C33,J27:J33) -> 500 | K36: =SUMPRODUCT($C27:$C33,K27:K33) -> 500 | ... O36: =SUMPRODUCT($C27:$C33,O27:O33) -> 0 | P36: =SUM(D36:O36) -> 3000 | Q36: =SUMPRODUCT($C27:$C33,Q27:Q33) -> 0 | R36: =SUMPRODUCT($C27:$C33,R27:R33) -> 0 | S36: =SUMPRODUCT($C27:$C33,S27:S33) -> 0 | T36: =SUMPRODUCT($C27:$C33,T27:T33) -> 0 | U36: =SUMPRODUCT($C27:$C33,U27:U33) -> 500 | V36: =SUMPRODUCT($C27:$C33,V27:V33) -> 500 | W36: =SUMPRODUCT($C27:$C33,W27:W33) -> 500 | X36: =SUMPRODUCT($C27:$C33,X27:X33) -> 500 | ... AB36: =SUMPRODUCT($C27:$C33,AB27:AB33) -> 0 | AC36: =SUM(Q36:AB36) -> 3000 | AD36: =SUMPRODUCT($C27:$C32,AD27:AD32)*(1+Inflation_salaires)*12 -> 3150 | AE36: =SUMPRODUCT($C27:$C32,AE27:AE32)*(1+Inflation_salaires)^2*12 -> 3307.5
B37: Charges sociales - Production | D37: =IF(Statut_JEI=1,Personnel!D36*Taux_Charges_Sociales_JEI,Personnel!D35*Taux_charges_sociales) -> 990 | E37: =IF(Statut_JEI=1,Personnel!E36*Taux_Charges_Sociales_JEI,Personnel!E35*Taux_charges_sociales) -> 990 | F37: =IF(Statut_JEI=1,Personnel!F36*Taux_Charges_Sociales_JEI,Personnel!F35*Taux_charges_sociales) -> 990 | G37: =IF(Statut_JEI=1,Personnel!G36*Taux_Charges_Sociales_JEI,Personnel!G35*Taux_charges_sociales) -> 990 | H37: =IF(Statut_JEI=1,Personnel!H36*Taux_Charges_Sociales_JEI,Personnel!H35*Taux_charges_sociales) -> 990 | I37: =IF(Statut_JEI=1,Personnel!I36*Taux_Charges_Sociales_JEI,Personnel!I35*Taux_charges_sociales) -> 990 | J37: =IF(Statut_JEI=1,Personnel!J36*Taux_Charges_Sociales_JEI,Personnel!J35*Taux_charges_sociales) -> 990 | K37: =IF(Statut_JEI=1,Personnel!K36*Taux_Charges_Sociales_JEI,Personnel!K35*Taux_charges_sociales) -> 990 | ... O37: =IF(Statut_JEI=1,Personnel!O36*Taux_Charges_Sociales_JEI,Personnel!O35*Taux_charges_sociales) -> 990 | P37: =SUM(D37:O37) -> 11880 | Q37: =IF(Statut_JEI=1,Personnel!Q36*Taux_Charges_Sociales_JEI,Personnel!Q35*Taux_charges_sociales) -> 990 | R37: =IF(Statut_JEI=1,Personnel!R36*Taux_Charges_Sociales_JEI,Personnel!R35*Taux_charges_sociales) -> 990 | S37: =IF(Statut_JEI=1,Personnel!S36*Taux_Charges_Sociales_JEI,Personnel!S35*Taux_charges_sociales) -> 990 | T37: =IF(Statut_JEI=1,Personnel!T36*Taux_Charges_Sociales_JEI,Personnel!T35*Taux_charges_sociales) -> 990 | U37: =IF(Statut_JEI=1,Personnel!U36*Taux_Charges_Sociales_JEI,Personnel!U35*Taux_charges_sociales) -> 990 | V37: =IF(Statut_JEI=1,Personnel!V36*Taux_Charges_Sociales_JEI,Personnel!V35*Taux_charges_sociales) -> 990 | W37: =IF(Statut_JEI=1,Personnel!W36*Taux_Charges_Sociales_JEI,Personnel!W35*Taux_charges_sociales) -> 990 | X37: =IF(Statut_JEI=1,Personnel!X36*Taux_Charges_Sociales_JEI,Personnel!X35*Taux_charges_sociales) -> 990 | ... AB37: =IF(Statut_JEI=1,Personnel!AB36*Taux_Charges_Sociales_JEI,Personnel!AB35*Taux_charges_sociales) -> 990 | AC37: =SUM(Q37:AB37) -> 11880 | AD37: =IF(Statut_JEI=1,Personnel!AD36*Taux_Charges_Sociales_JEI,Personnel!AD35*Taux_charges_sociales) -> 12474 | AE37: =IF(Statut_JEI=1,Personnel!AE36*Taux_Charges_Sociales_JEI,Personnel!AE35*Taux_charges_sociales) -> 13097.7
B38: Sous traitance - Production | D38: =D33*$C$33/12 -> 0 | E38: =E33*$C$33/12 -> 0 | F38: =F33*$C$33/12 -> 0 | G38: =G33*$C$33/12 -> 0 | H38: =H33*$C$33/12 -> 0 | I38: =I33*$C$33/12 -> 0 | J38: =J33*$C$33/12 -> 0 | K38: =K33*$C$33/12 -> 0 | ... O38: =O33*$C$33/12 -> 0 | P38: =SUM(D38:O38) -> 0 | Q38: =Q33*$C33/12*(1+Inflation_salaires) -> 0 | R38: =R33*$C33/12*(1+Inflation_salaires) -> 0 | S38: =S33*$C33/12*(1+Inflation_salaires) -> 0 | T38: =T33*$C33/12*(1+Inflation_salaires) -> 0 | U38: =U33*$C33/12*(1+Inflation_salaires) -> 0 | V38: =V33*$C33/12*(1+Inflation_salaires) -> 0 | W38: =W33*$C33/12*(1+Inflation_salaires) -> 0 | X38: =X33*$C33/12*(1+Inflation_salaires) -> 0 | ... AB38: =AB33*$C33/12*(1+Inflation_salaires) -> 0 | AC38: =SUM(Q38:AB38) -> 0 | AD38: =AD33*$C33*(1+Inflation_salaires)^2 -> 0 | AE38: =AE33*$C33*(1+Inflation_salaires)^2 -> 0
B39: Total Coûts de personnel - Production | D39: =SUM(D35:D38) -> 3190 | E39: =SUM(E35:E38) -> 3190 | F39: =SUM(F35:F38) -> 3190 | G39: =SUM(G35:G38) -> 3190 | H39: =SUM(H35:H38) -> 3690 | I39: =SUM(I35:I38) -> 3690 | J39: =SUM(J35:J38) -> 3690 | K39: =SUM(K35:K38) -> 3690 | ... O39: =SUM(O35:O38) -> 3190 | P39: =SUM(D39:O39) -> 41280 | Q39: =SUM(Q35:Q38) -> 3190 | R39: =SUM(R35:R38) -> 3190 | S39: =SUM(S35:S38) -> 3190 | T39: =SUM(T35:T38) -> 3190 | U39: =SUM(U35:U38) -> 3690 | V39: =SUM(V35:V38) -> 3690 | W39: =SUM(W35:W38) -> 3690 | X39: =SUM(X35:X38) -> 3690 | ... AB39: =SUM(AB35:AB38) -> 3190 | AC39: =SUM(Q39:AB39) -> 41280 | AD39: =SUM(AD35:AD38) -> 43344 | AE39: =SUM(AE35:AE38) -> 45511.2
B40: Part du salaire immobilisé en R&D - Production | D40: =-(D35+D36+D37+D38)*Salaires_Immob_Prod_Dev -> 0 | E40: =-(E36+E37+E38)*Salaires_Immob_Prod_Dev -> 0 | F40: =-(F36+F37+F38)*Salaires_Immob_Prod_Dev -> 0 | G40: =-(G36+G37+G38)*Salaires_Immob_Prod_Dev -> 0 | H40: =-(H36+H37+H38)*Salaires_Immob_Prod_Dev -> 0 | I40: =-(I36+I37+I38)*Salaires_Immob_Prod_Dev -> 0 | J40: =-(J36+J37+J38)*Salaires_Immob_Prod_Dev -> 0 | K40: =-(K36+K37+K38)*Salaires_Immob_Prod_Dev -> 0 | L40: =-(L36+L37+L38)*Salaires_Immob_Prod_Dev -> 0 | ... O40: =-(O36+O37+O38)*Salaires_Immob_Prod_Dev -> 0 | P40: =SUM(D40:O40) -> 0 | Q40: =-(Q36+Q37+Q38)*Salaires_Immob_Prod_Dev -> 0 | R40: =-(R36+R37+R38)*Salaires_Immob_Prod_Dev -> 0 | S40: =-(S36+S37+S38)*Salaires_Immob_Prod_Dev -> 0 | T40: =-(T36+T37+T38)*Salaires_Immob_Prod_Dev -> 0 | U40: =-(U36+U37+U38)*Salaires_Immob_Prod_Dev -> 0 | V40: =-(V36+V37+V38)*Salaires_Immob_Prod_Dev -> 0 | W40: =-(W36+W37+W38)*Salaires_Immob_Prod_Dev -> 0 | X40: =-(X36+X37+X38)*Salaires_Immob_Prod_Dev -> 0 | ... AB40: =-(AB36+AB37+AB38)*Salaires_Immob_Prod_Dev -> 0 | AC40: =SUM(Q40:AB40) -> 0 | AD40: =-(AD35+AD37+AD38)*Salaires_Immob_Prod_Dev -> 0 | AE40: =-(AE36+AE37+AE38)*Salaires_Immob_Prod_Dev -> 0
O42: check | P42: =IF(SUM(D39:O39)=P39,0,P39-SUM(D39:O39)) -> 0 | AC42: =IF(SUM(Q39:AB39)=AC39,0,AC39-SUM(Q39:AB39)) -> 0
B43: EQUIPE COMMERCIALE & MARKETING
AC44: =SUM(Q44:AB44)/12 -> 0
AC45: =SUM(Q45:AB45)/12 -> 0
AC46: =SUM(Q46:AB46)/12 -> 0
AC47: =SUM(Q47:AB47)/12 -> 0
AC48: =SUM(Q48:AB48)/12 -> 0
AC49: =SUM(Q49:AB49)/12 -> 0
B50: Stagiaires - Marketing | AC50: =SUM(Q50:AB50)/12 -> 0
B51: Personnel sous traité - Commercial/Marketing | AC51: =SUM(Q51:AB51)/12 -> 0
B52: Total Effectifs - Commercial | D52: =SUM(D44:D51) -> 0 | E52: =SUM(E44:E51) -> 0 | F52: =SUM(F44:F51) -> 0 | G52: =SUM(G44:G51) -> 0 | H52: =SUM(H44:H51) -> 0 | I52: =SUM(I44:I51) -> 0 | J52: =SUM(J44:J51) -> 0 | K52: =SUM(K44:K51) -> 0 | ... AE52: =SUM(AE44:AE51) -> 0
B53: Salaires bruts - Commercial | D53: =SUMPRODUCT($C44:$C50,D44:D50)/12 -> 0 | E53: =SUMPRODUCT($C44:$C50,E44:E50)/12 -> 0 | F53: =SUMPRODUCT($C44:$C50,F44:F50)/12 -> 0 | G53: =SUMPRODUCT($C44:$C50,G44:G50)/12 -> 0 | H53: =SUMPRODUCT($C44:$C50,H44:H50)/12 -> 0 | I53: =SUMPRODUCT($C44:$C50,I44:I50)/12 -> 0 | J53: =SUMPRODUCT($C44:$C50,J44:J50)/12 -> 0 | K53: =SUMPRODUCT($C44:$C50,K44:K50)/12 -> 0 | ... O53: =SUMPRODUCT($C44:$C50,O44:O50)/12 -> 0 | P53: =SUM(D53:O53) -> 0 | Q53: =SUMPRODUCT($C44:$C50,Q44:Q50)/12*(1+Inflation_salaires) -> 0 | R53: =SUMPRODUCT($C44:$C50,R44:R50)/12*(1+Inflation_salaires) -> 0 | S53: =SUMPRODUCT($C44:$C50,S44:S50)/12*(1+Inflation_salaires) -> 0 | T53: =SUMPRODUCT($C44:$C50,T44:T50)/12*(1+Inflation_salaires) -> 0 | U53: =SUMPRODUCT($C44:$C50,U44:U50)/12*(1+Inflation_salaires) -> 0 | V53: =SUMPRODUCT($C44:$C50,V44:V50)/12*(1+Inflation_salaires) -> 0 | W53: =SUMPRODUCT($C44:$C50,W44:W50)/12*(1+Inflation_salaires) -> 0 | X53: =SUMPRODUCT($C44:$C50,X44:X50)/12*(1+Inflation_salaires) -> 0 | ... AB53: =SUMPRODUCT($C44:$C50,AB44:AB50)/12*(1+Inflation_salaires) -> 0 | AC53: =SUM(Q53:AB53) -> 0 | AD53: =SUMPRODUCT($C44:$C50,AD44:AD50)*(1+Inflation_salaires)^2 -> 0 | AE53: =SUMPRODUCT($C44:$C50,AE44:AE50)*(1+Inflation_salaires)^3 -> 0
B54: Commissions - Commercial | D54: =D53*Taux_de_commission -> 0 | E54: =E53*Taux_de_commission -> 0 | F54: =F53*Taux_de_commission -> 0 | G54: =G53*Taux_de_commission -> 0 | H54: =H53*Taux_de_commission -> 0 | I54: =I53*Taux_de_commission -> 0 | J54: =J53*Taux_de_commission -> 0 | K54: =K53*Taux_de_commission -> 0 | ... O54: =O53*Taux_de_commission -> 0 | P54: =SUM(D54:O54) -> 0 | Q54: =Q53*Taux_de_commission -> 0 | R54: =R53*Taux_de_commission -> 0 | S54: =S53*Taux_de_commission -> 0 | T54: =T53*Taux_de_commission -> 0 | U54: =U53*Taux_de_commission -> 0 | V54: =V53*Taux_de_commission -> 0 | W54: =W53*Taux_de_commission -> 0 | X54: =X53*Taux_de_commission -> 0 | ... AB54: =AB53*Taux_de_commission -> 0 | AC54: =SUM(Q54:AB54) -> 0 | AD54: =AD53*Taux_de_commission -> 0 | AE54: =AE53*Taux_de_commission -> 0
B55: Charges sociales - Commercial | D55: =D53*Taux_charges_sociales -> 0 | E55: =E53*Taux_charges_sociales -> 0 | F55: =F53*Taux_charges_sociales -> 0 | G55: =G53*Taux_charges_sociales -> 0 | H55: =H53*Taux_charges_sociales -> 0 | I55: =I53*Taux_charges_sociales -> 0 | J55: =J53*Taux_charges_sociales -> 0 | K55: =K53*Taux_charges_sociales -> 0 | ... O55: =O53*Taux_charges_sociales -> 0 | P55: =SUM(D55:O55) -> 0 | Q55: =Q53*Taux_charges_sociales -> 0 | R55: =R53*Taux_charges_sociales -> 0 | S55: =S53*Taux_charges_sociales -> 0 | T55: =T53*Taux_charges_sociales -> 0 | U55: =U53*Taux_charges_sociales -> 0 | V55: =V53*Taux_charges_sociales -> 0 | W55: =W53*Taux_charges_sociales -> 0 | X55: =X53*Taux_charges_sociales -> 0 | ... AB55: =AB53*Taux_charges_sociales -> 0 | AC55: =SUM(Q55:AB55) -> 0 | AD55: =AD53*Taux_charges_sociales -> 0 | AE55: =AE53*Taux_charges_sociales -> 0
B56: Sous traitance - Commercial | D56: =D51*$C51/12 -> 0 | E56: =E51*$C51/12 -> 0 | F56: =F51*$C51/12 -> 0 | G56: =G51*$C51/12 -> 0 | H56: =H51*$C51/12 -> 0 | I56: =I51*$C51/12 -> 0 | J56: =J51*$C51/12 -> 0 | K56: =K51*$C51/12 -> 0 | ... O56: =O51*$C51/12 -> 0 | P56: =SUM(D56:O56) -> 0 | Q56: =Q51*$C51/12*(1+Inflation_salaires) -> 0 | R56: =R51*$C51/12*(1+Inflation_salaires) -> 0 | S56: =S51*$C51/12*(1+Inflation_salaires) -> 0 | T56: =T51*$C51/12*(1+Inflation_salaires) -> 0 | U56: =U51*$C51/12*(1+Inflation_salaires) -> 0 | V56: =V51*$C51/12*(1+Inflation_salaires) -> 0 | W56: =W51*$C51/12*(1+Inflation_salaires) -> 0 | X56: =X51*$C51/12*(1+Inflation_salaires) -> 0 | ... AB56: =AB51*$C51/12*(1+Inflation_salaires) -> 0 | AC56: =SUM(Q56:AB56) -> 0 | AD56: =AD51*$C51*(1+Inflation_salaires)^2 -> 0 | AE56: =AE51*$C51*(1+Inflation_salaires)^3 -> 0
B57: Total Coûts de personnel - Commercial | D57: =D53+D54+D55+D56 -> 0 | E57: =E53+E54+E55+E56 -> 0 | F57: =F53+F54+F55+F56 -> 0 | G57: =G53+G54+G55+G56 -> 0 | H57: =H53+H54+H55+H56 -> 0 | I57: =I53+I54+I55+I56 -> 0 | J57: =J53+J54+J55+J56 -> 0 | K57: =K53+K54+K55+K56 -> 0 | ... O57: =O53+O54+O55+O56 -> 0 | P57: =SUM(D57:O57) -> 0 | Q57: =Q53+Q54+Q55+Q56 -> 0 | R57: =R53+R54+R55+R56 -> 0 | S57: =S53+S54+S55+S56 -> 0 | T57: =T53+T54+T55+T56 -> 0 | U57: =U53+U54+U55+U56 -> 0 | V57: =V53+V54+V55+V56 -> 0 | W57: =W53+W54+W55+W56 -> 0 | X57: =X53+X54+X55+X56 -> 0 | ... AB57: =AB53+AB54+AB55+AB56 -> 0 | AC57: =SUM(Q57:AB57) -> 0 | AD57: =AD53+AD54+AD55+AD56 -> 0 | AE57: =AE53+AE54+AE55+AE56 -> 0
O58: check | P58: =IF(SUM(D57:O57)=P57,0,P57-SUM(D57:O57)) -> 0 | AC58: =IF(SUM(Q57:AB57)=AC57,0,AC57-SUM(Q57:AB57)) -> 0
B59: ADMINISTRATIF - FINANCE - INFORMATIQUE
B60: Direction - Administratif | P60: =SUM(D60:O60)/12 -> 0 | AC60: =SUM(Q60:AB60)/12 -> 0
B61: Employés - Administratif | P61: =SUM(D61:O61)/12 -> 0 | AC61: =SUM(Q61:AB61)/12 -> 0
B62: Stagiaires - Administratif | P62: =SUM(D62:O62)/12 -> 0 | AC62: =SUM(Q62:AB62)/12 -> 0
B63: Personnel sous traité - Administratif | P63: =SUM(D63:O63)/12 -> 0 | AC63: =SUM(Q63:AB63)/12 -> 0
B64: Total Effectifs - Administratif | D64: =SUM(D60:D63) -> 0 | E64: =SUM(E60:E63) -> 0 | F64: =SUM(F60:F63) -> 0 | G64: =SUM(G60:G63) -> 0 | H64: =SUM(H60:H63) -> 0 | I64: =SUM(I60:I63) -> 0 | J64: =SUM(J60:J63) -> 0 | K64: =SUM(K60:K63) -> 0 | ... AE64: =SUM(AE60:AE63) -> 0
B65: Salaires bruts- Administratif | D65: =SUMPRODUCT($C60:$C62,D60:D62)/12 -> 0 | E65: =SUMPRODUCT($C60:$C62,E60:E62)/12 -> 0 | F65: =SUMPRODUCT($C60:$C62,F60:F62)/12 -> 0 | G65: =SUMPRODUCT($C60:$C62,G60:G62)/12 -> 0 | H65: =SUMPRODUCT($C60:$C62,H60:H62)/12 -> 0 | I65: =SUMPRODUCT($C60:$C62,I60:I62)/12 -> 0 | J65: =SUMPRODUCT($C60:$C62,J60:J62)/12 -> 0 | K65: =SUMPRODUCT($C60:$C62,K60:K62)/12 -> 0 | ... O65: =SUMPRODUCT($C60:$C62,O60:O62)/12 -> 0 | P65: =SUM(D65:O65) -> 0 | Q65: =SUMPRODUCT($C60:$C62,Q60:Q62)/12*(1+Inflation_salaires) -> 0 | R65: =SUMPRODUCT($C60:$C62,R60:R62)/12*(1+Inflation_salaires) -> 0 | S65: =SUMPRODUCT($C60:$C62,S60:S62)/12*(1+Inflation_salaires) -> 0 | T65: =SUMPRODUCT($C60:$C62,T60:T62)/12*(1+Inflation_salaires) -> 0 | U65: =SUMPRODUCT($C60:$C62,U60:U62)/12*(1+Inflation_salaires) -> 0 | V65: =SUMPRODUCT($C60:$C62,V60:V62)/12*(1+Inflation_salaires) -> 0 | W65: =SUMPRODUCT($C60:$C62,W60:W62)/12*(1+Inflation_salaires) -> 0 | X65: =SUMPRODUCT($C60:$C62,X60:X62)/12*(1+Inflation_salaires) -> 0 | ... AB65: =SUMPRODUCT($C60:$C62,AB60:AB62)/12*(1+Inflation_salaires) -> 0 | AC65: =SUM(Q65:AB65) -> 0 | AD65: =SUMPRODUCT($C60:$C62,AD60:AD62)*(1+Inflation_salaires)^2 -> 0 | AE65: =SUMPRODUCT($C60:$C62,AE60:AE62)*(1+Inflation_salaires)^3 -> 0
B66: Charges sociales - Administratif | D66: =D65*Taux_charges_sociales -> 0 | E66: =E65*Taux_charges_sociales -> 0 | F66: =F65*Taux_charges_sociales -> 0 | G66: =G65*Taux_charges_sociales -> 0 | H66: =H65*Taux_charges_sociales -> 0 | I66: =I65*Taux_charges_sociales -> 0 | J66: =J65*Taux_charges_sociales -> 0 | K66: =K65*Taux_charges_sociales -> 0 | ... O66: =O65*Taux_charges_sociales -> 0 | P66: =SUM(D66:O66) -> 0 | Q66: =Q65*Taux_charges_sociales -> 0 | R66: =R65*Taux_charges_sociales -> 0 | S66: =S65*Taux_charges_sociales -> 0 | T66: =T65*Taux_charges_sociales -> 0 | U66: =U65*Taux_charges_sociales -> 0 | V66: =V65*Taux_charges_sociales -> 0 | W66: =W65*Taux_charges_sociales -> 0 | X66: =X65*Taux_charges_sociales -> 0 | ... AB66: =AB65*Taux_charges_sociales -> 0 | AC66: =SUM(Q66:AB66) -> 0 | AD66: =AD65*Taux_charges_sociales -> 0 | AE66: =AE65*Taux_charges_sociales -> 0
B67: Sous traitance - Administratif | D67: =D63*$C$63/12 -> 0 | E67: =E63*$C$63/12 -> 0 | F67: =F63*$C$63/12 -> 0 | G67: =G63*$C$63/12 -> 0 | H67: =H63*$C$63/12 -> 0 | I67: =I63*$C$63/12 -> 0 | J67: =J63*$C$63/12 -> 0 | K67: =K63*$C$63/12 -> 0 | ... O67: =O63*$C$63/12 -> 0 | P67: =SUM(D67:O67) -> 0 | Q67: =Q63*$C63/12*(1+Inflation_salaires) -> 0 | R67: =R63*$C63/12*(1+Inflation_salaires) -> 0 | S67: =S63*$C63/12*(1+Inflation_salaires) -> 0 | T67: =T63*$C63/12*(1+Inflation_salaires) -> 0 | U67: =U63*$C63/12*(1+Inflation_salaires) -> 0 | V67: =V63*$C63/12*(1+Inflation_salaires) -> 0 | W67: =W63*$C63/12*(1+Inflation_salaires) -> 0 | X67: =X63*$C63/12*(1+Inflation_salaires) -> 0 | ... AB67: =AB63*$C63/12*(1+Inflation_salaires) -> 0 | AC67: =SUM(Q67:AB67) -> 0 | AD67: =AD63*$C63*(1+Inflation_salaires)^2 -> 0 | AE67: =AE62*$C63*(1+Inflation_salaires)^3 -> 0
B68: Total Coûts de personnel - Administratif | D68: =D65+D66+D67 -> 0 | E68: =E65+E66+E67 -> 0 | F68: =F65+F66+F67 -> 0 | G68: =G65+G66+G67 -> 0 | H68: =H65+H66+H67 -> 0 | I68: =I65+I66+I67 -> 0 | J68: =J65+J66+J67 -> 0 | K68: =K65+K66+K67 -> 0 | ... O68: =O65+O66+O67 -> 0 | P68: =SUM(D68:O68) -> 0 | Q68: =Q65+Q66+Q67 -> 0 | R68: =R65+R66+R67 -> 0 | S68: =S65+S66+S67 -> 0 | T68: =T65+T66+T67 -> 0 | U68: =U65+U66+U67 -> 0 | V68: =V65+V66+V67 -> 0 | W68: =W65+W66+W67 -> 0 | X68: =X65+X66+X67 -> 0 | ... AB68: =AB65+AB66+AB67 -> 0 | AC68: =SUM(Q68:AB68) -> 0 | AD68: =SUM(AD65:AD67) -> 0 | AE68: =SUM(AE65:AE67) -> 0
O69: check | P69: =IF(SUM(D68:O68)=P68,0,P68-SUM(D68:O68)) -> 0 | AC69: =IF(SUM(Q68:AB68)=AC68,0,AC68-SUM(Q68:AB68)) -> 0
B70: TOUTES DIRECTIONS
B71: Total Général en ETP | D71: =D10+D34+D52+D64 -> 2 | E71: =E10+E34+E52+E64 -> 2 | F71: =F10+F34+F52+F64 -> 2 | G71: =G10+G34+G52+G64 -> 2 | H71: =H10+H34+H52+H64 -> 2 | I71: =I10+I34+I52+I64 -> 2 | J71: =J10+J34+J52+J64 -> 2 | K71: =K10+K34+K52+K64 -> 2 | ... O71: =O10+O34+O52+O64 -> 2 | P71: =(D71+E71+F71+G71+H71+I71+J71+K71+L71+M71+N71+O71)/12 -> 2 | Q71: =Q10+Q34+Q52+Q64 -> 2 | R71: =R10+R34+R52+R64 -> 2 | S71: =S10+S34+S52+S64 -> 2 | T71: =T10+T34+T52+T64 -> 2 | U71: =U10+U34+U52+U64 -> 2 | V71: =V10+V34+V52+V64 -> 2 | W71: =W10+W34+W52+W64 -> 2 | X71: =X10+X34+X52+X64 -> 2 | ... AB71: =AB10+AB34+AB52+AB64 -> 2 | AC71: =(Q71+R71+S71+T71+U71+V71+W71+X71+Y71+Z71+AA71+AB71)/12 -> 2 | AD71: =AD10+AD34+AD52+AD64 -> 2 | AE71: =AE10+AE34+AE52+AE64 -> 2
B72: dont stagiaires | D72: =D50+D62 -> 0 | E72: =E50+E62 -> 0 | F72: =F50+F62 -> 0 | G72: =G50+G62 -> 0 | H72: =H50+H62 -> 0 | I72: =I50+I62 -> 0 | J72: =J50+J62 -> 0 | K72: =K50+K62 -> 0 | ... O72: =O50+O62 -> 0 | P72: =(D72+E72+F72+G72+H72+I72+J72+K72+L72+M72+N72+O72)/12 -> 0 | Q72: =Q50+Q62 -> 0 | R72: =R50+R62 -> 0 | S72: =S50+S62 -> 0 | T72: =T50+T62 -> 0 | U72: =U50+U62 -> 0 | V72: =V50+V62 -> 0 | W72: =W50+W62 -> 0 | X72: =X50+X62 -> 0 | ... AB72: =AB50+AB62 -> 0 | AC72: =(Q72+R72+S72+T72+U72+V72+W72+X72+Y72+Z72+AA72+AB72)/12 -> 0 | AD72: =AD26+AD50+AD62 -> 0 | AE72: =AE26+AE50+AE62 -> 0
B73: Total Salaires bruts | D73: =D11+D35+D36+D53+D54+D65 -> 4283.3333 | E73: =E11+E35+E36+E53+E54+E65 -> 4283.3333 | F73: =F11+F35+F36+F53+F54+F65 -> 4283.3333 | G73: =G11+G35+G36+G53+G54+G65 -> 4283.3333 | H73: =H11+H35+H36+H53+H54+H65 -> 4783.3333 | I73: =I11+I35+I36+I53+I54+I65 -> 4783.3333 | J73: =J11+J35+J36+J53+J54+J65 -> 4783.3333 | K73: =K11+K35+K36+K53+K54+K65 -> 4783.3333 | ... O73: =O11+O35+O36+O53+O54+O65 -> 4283.3333 | P73: =SUM(D73:O73) -> 54400 | Q73: =Q11+Q35+Q36+Q53+Q54+Q65 -> 4283.3333 | R73: =R11+R35+R36+R53+R54+R65 -> 4283.3333 | S73: =S11+S35+S36+S53+S54+S65 -> 4283.3333 | T73: =T11+T35+T36+T53+T54+T65 -> 4283.3333 | U73: =U11+U35+U36+U53+U54+U65 -> 4783.3333 | V73: =V11+V35+V36+V53+V54+V65 -> 4783.3333 | W73: =W11+W35+W36+W53+W54+W65 -> 4783.3333 | X73: =X11+X35+X36+X53+X54+X65 -> 4783.3333 | ... AB73: =AB11+AB35+AB36+AB53+AB54+AB65 -> 4283.3333 | AC73: =AC11+AC36+AC53+AC54+AC65 -> 28000 | AD73: =AD11+AD35+AD36+AD53+AD54+AD65 -> 58432.5 | AE73: =AE11+AE35+AE36+AE53+AE54+AE65 -> 61354.125
B74: Total Charges sociales | D74: =D12+D37+D55+D66 -> 1927.5 | E74: =E12+E37+E55+E66 -> 1927.5 | F74: =F12+F37+F55+F66 -> 1927.5 | G74: =G12+G37+G55+G66 -> 1927.5 | H74: =H12+H37+H55+H66 -> 1927.5 | I74: =I12+I37+I55+I66 -> 1927.5 | J74: =J12+J37+J55+J66 -> 1927.5 | K74: =K12+K37+K55+K66 -> 1927.5 | ... O74: =O12+O37+O55+O66 -> 1927.5 | P74: =SUM(D74:O74) -> 23130 | Q74: =Q12+Q37+Q55+Q66 -> 1927.5 | R74: =R12+R37+R55+R66 -> 1927.5 | S74: =S12+S37+S55+S66 -> 1927.5 | T74: =T12+T37+T55+T66 -> 1927.5 | U74: =U12+U37+U55+U66 -> 1927.5 | V74: =V12+V37+V55+V66 -> 1927.5 | W74: =W12+W37+W55+W66 -> 1927.5 | X74: =X12+X37+X55+X66 -> 1927.5 | ... AB74: =AB12+AB37+AB55+AB66 -> 1927.5 | AC74: =SUM(Q74:AB74) -> 23130 | AD74: =AD12+AD37+AD55+AD66 -> 24877.125 | AE74: =AE12+AE37+AE55+AE66 -> 26120.981
B75: Total Sous traitance | D75: =D38+D56+D67 -> 0 | E75: =E38+E56+E67 -> 0 | F75: =F38+F56+F67 -> 0 | G75: =G38+G56+G67 -> 0 | H75: =H38+H56+H67 -> 0 | I75: =I38+I56+I67 -> 0 | J75: =J38+J56+J67 -> 0 | K75: =K38+K56+K67 -> 0 | ... O75: =O38+O56+O67 -> 0 | P75: =SUM(D75:O75) -> 0 | Q75: =Q38+Q56+Q67 -> 0 | R75: =R38+R56+R67 -> 0 | S75: =S38+S56+S67 -> 0 | T75: =T38+T56+T67 -> 0 | U75: =U38+U56+U67 -> 0 | V75: =V38+V56+V67 -> 0 | W75: =W38+W56+W67 -> 0 | X75: =X38+X56+X67 -> 0 | ... AB75: =AB38+AB56+AB67 -> 0 | AC75: =SUM(Q75:AB75) -> 0 | AD75: =AD38+AD56+AD67 -> 0 | AE75: =AE38+AE56+AE67 -> 0
B76: TOTAL COÛTS DE PERSONNEL | D76: =SUM(D73:D75) -> 6210.8333 | E76: =SUM(E73:E75) -> 6210.8333 | F76: =SUM(F73:F75) -> 6210.8333 | G76: =SUM(G73:G75) -> 6210.8333 | H76: =SUM(H73:H75) -> 6710.8333 | I76: =SUM(I73:I75) -> 6710.8333 | J76: =SUM(J73:J75) -> 6710.8333 | K76: =SUM(K73:K75) -> 6710.8333 | ... O76: =SUM(O73:O75) -> 6210.8333 | P76: =SUM(D76:O76) -> 77530 | Q76: =SUM(Q73:Q75) -> 6210.8333 | R76: =SUM(R73:R75) -> 6210.8333 | S76: =SUM(S73:S75) -> 6210.8333 | T76: =SUM(T73:T75) -> 6210.8333 | U76: =SUM(U73:U75) -> 6710.8333 | V76: =SUM(V73:V75) -> 6710.8333 | W76: =SUM(W73:W75) -> 6710.8333 | X76: =SUM(X73:X75) -> 6710.8333 | ... AB76: =SUM(AB73:AB75) -> 6210.8333 | AC76: =SUM(Q76:AB76) -> 77530 | AD76: =SUM(AD73:AD75) -> 83309.625 | AE76: =SUM(AE73:AE75) -> 87475.106
B77: Total Part du salaire immobilisé en R&D | D77: =D14+D40 -> 0 | E77: =E14+E40 -> 0 | F77: =F14+F40 -> 0 | G77: =G14+G40 -> 0 | H77: =H14+H40 -> 0 | I77: =I14+I40 -> 0 | J77: =J14+J40 -> 0 | K77: =K14+K40 -> 0 | ... O77: =O14+O40 -> 0 | P77: =SUM(D77:O77) -> 0 | Q77: =Q14+Q40 -> 0 | R77: =R14+R40 -> 0 | S77: =S14+S40 -> 0 | T77: =T14+T40 -> 0 | U77: =U14+U40 -> 0 | V77: =V14+V40 -> 0 | W77: =W14+W40 -> 0 | X77: =X14+X40 -> 0 | ... AB77: =AB14+AB40 -> 0 | AC77: =SUM(Q77:AB77) -> 0 | AD77: =AD14+AD40 -> 0 | AE77: =AE14+AE40 -> 0
O78: check | P78: =IF(SUM(D76:O76)=P76,0,P76-SUM(D76:O76)) -> 0 | AC78: =IF(SUM(Q76:AB76)=AC76,0,AC76-SUM(Q76:AB76)) -> 0

Sheet Charges dexploitation
B2: CHARGES EXTERNES
C4: =YEAR(date_début) -> 2025 | P4: =YEAR(EDATE(date_début,12)) -> 2026 | AC4: =YEAR(EDATE(date_début,24)) -> 2027 | AD4: =YEAR(EDATE(date_début,36)) -> 2028
C5: Jan | D5: Fév | E5: Mar | F5: Avr | G5: Mai | H5: Juin | I5: Juil | J5: Aout | K5: Sept | L5: Oct | M5: Nov | N5: Déc | P5: Jan | Q5: Fév | R5: Mar | S5: Avr | T5: Mai | U5: Juin | V5: Juil | W5: Aout | X5: Sept | Y5: Oct | Z5: Nov | AA5: Déc
B6: CHARGES EXTERNES
B7: Assurances | O7: =SUM(C7:N7) -> 0 | AB7: =SUM(P7:AA7) -> 0 | AC7: 0 | AD7: 0
B8: Assurance RC Pro | G8: 20 | H8: 20 | I8: 20 | J8: 20 | K8: 20 | L8: 20 | M8: 20 | N8: 20 | O8: =SUM(C8:N8) -> 160 | P8: 20 | Q8: 20 | R8: 20 | S8: 20 | T8: 20 | U8: 20 | V8: 20 | W8: 20 | X8: 20 | Y8: 20 | Z8: 20 | AA8: 20 | AB8: =SUM(P8:AA8) -> 240 | AC8: 240 | AD8: 240
B9: Assurance Restaurant | G9: 200 | H9: 200 | I9: 200 | J9: 200 | K9: 200 | L9: 200 | M9: 200 | N9: 200 | O9: =SUM(C9:N9) -> 1600 | P9: 200 | Q9: 200 | R9: 200 | S9: 200 | T9: 200 | U9: 200 | V9: 200 | W9: 200 | X9: 200 | Y9: 200 | Z9: 200 | AA9: 200 | AB9: =SUM(P9:AA9) -> 2400 | AC9: 2400 | AD9: 2400
B10: assurance pret
B11: Assurance RC dirigeants | G11: 35 | H11: 35 | I11: 35 | J11: 35 | K11: 35 | L11: 35 | M11: 35 | N11: 35 | O11: =SUM(C11:N11) -> 280 | P11: 35 | Q11: 35 | R11: 35 | S11: 35 | T11: 35 | U11: 35 | V11: 35 | W11: 35 | X11: 35 | Y11: 35 | Z11: 35 | AA11: 35 | AB11: =SUM(P11:AA11) -> 420 | AC11: 420 | AD11: 420
B12: Juridique | O12: =SUM(C12:N12) -> 0 | AB12: =SUM(P12:AA12) -> 0
B13: Frais Avocat social | O13: =SUM(C13:N13) -> 0 | AB13: =SUM(P13:AA13) -> 0 | AC13: 0 | AD13: 0
B14: Frais Avocat d'affaires | H14: 1000 | O14: =SUM(C14:N14) -> 1000 | AB14: =SUM(P14:AA14) -> 0 | AC14: 0 | AD14: 0
B15: Comptabilité et Paie et banques | O15: =SUM(C15:N15) -> 0 | AB15: =SUM(P15:AA15) -> 0
B16: Frais comptables | G16: 450 | H16: 450 | I16: 450 | J16: 450 | K16: 450 | L16: 450 | M16: 450 | N16: 900 | O16: =SUM(C16:N16) -> 4050 | P16: 450 | Q16: 450 | R16: 450 | S16: 450 | T16: 450 | U16: 450 | V16: 450 | W16: 450 | X16: 450 | Y16: 450 | Z16: 450 | AA16: 900 | AB16: =SUM(P16:AA16) -> 5850 | AC16: 5850 | AD16: 5850
B17: caisse enregistreuse | O17: =SUM(C17:N17) -> 0 | AB17: =SUM(P17:AA17) -> 0 | AC17: 520 | AD17: 520
B18: Commission cb | G18: 187 | H18: 187 | I18: 187 | J18: 187 | K18: 187 | L18: 187 | M18: 187 | N18: 187 | O18: =SUM(C18:N18) -> 1496 | P18: 187 | Q18: 187 | R18: 187 | S18: 187 | T18: 187 | U18: 187 | V18: 187 | W18: 187 | X18: 187 | Y18: 187 | Z18: 187 | AA18: 187 | AB18: =SUM(P18:AA18) -> 2244 | AC18: 2244 | AD18: 2244
B19: Frais Bancaires | G19: 35 | H19: 35 | I19: 35 | J19: 35 | K19: 35 | L19: 35 | M19: 35 | N19: 35 | O19: =SUM(C19:N19) -> 280 | P19: 40 | Q19: 40 | R19: 40 | S19: 40 | T19: 40 | U19: 40 | V19: 40 | W19: 40 | X19: 40 | Y19: 40 | Z19: 40 | AA19: 40 | AB19: =SUM(P19:AA19) -> 480 | AC19: 500 | AD19: 500
B20: commission carte resto | G20: 111 | H20: 111 | I20: 111 | J20: 111 | K20: 111 | L20: 111 | M20: 111 | N20: 111 | O20: =SUM(C20:N20) -> 888 | P20: 111 | Q20: 111 | R20: 111 | S20: 111 | T20: 111 | U20: 111 | V20: 111 | W20: 111 | X20: 111 | Y20: 111 | Z20: 111 | AA20: 111 | AB20: =SUM(P20:AA20) -> 1332 | AC20: 1332 | AD20: 1340
B21: Payfit | O21: =SUM(C21:N21) -> 0 | P21: 87 | Q21: 38 | R21: 38 | S21: 38 | T21: 38 | U21: 76 | V21: 76 | W21: 76 | X21: 38 | Y21: 38 | Z21: 38 | AA21: 38 | AB21: =SUM(P21:AA21) -> 619 | AC21: 999 | AD21: 1075
O22: =SUM(C22:N22) -> 0 | AB22: =SUM(P22:AA22) -> 0 | AC22: 0 | AD22: 0
O23: =SUM(C23:N23) -> 0 | AB23: =SUM(P23:AA23) -> 0 | AC23: 0 | AD23: 0
B24: Informatique & Communication | O24: =SUM(C24:N24) -> 0 | AB24: =SUM(P24:AA24) -> 0 | AC24: 0 | AD24: 0
B25: Frais Internet | G25: 30 | H25: 30 | I25: 30 | J25: 30 | K25: 30 | L25: 30 | M25: 30 | N25: 30 | O25: =SUM(C25:N25) -> 240 | P25: 30 | Q25: 30 | R25: 30 | S25: 30 | T25: 30 | U25: 30 | V25: 30 | W25: 30 | X25: 30 | Y25: 30 | Z25: 30 | AA25: 30 | AB25: =SUM(P25:AA25) -> 360 | AC25: 360 | AD25: 360
B26: Téléphonie | O26: =SUM(C26:N26) -> 0 | AB26: =SUM(P26:AA26) -> 0
B27: Domaines | O27: =SUM(C27:N27) -> 0 | P27: 50 | AA27: 50 | AB27: =SUM(P27:AA27) -> 100 | AD27: 50
B28: Hébergement site web | O28: =SUM(C28:N28) -> 0 | P28: 30 | Q28: 30 | R28: 30 | S28: 30 | T28: 30 | U28: 30 | V28: 30 | W28: 30 | X28: 30 | Y28: 30 | Z28: 30 | AA28: 30 | AB28: =SUM(P28:AA28) -> 360 | AC28: 360
B29: Spotify | G29: 15.17 | H29: 15.17 | I29: 15.17 | J29: 15.17 | K29: 15.17 | L29: 15.17 | M29: 15.17 | N29: 15.17 | O29: =SUM(C29:N29) -> 121.36 | P29: 15.17 | Q29: 15.17 | R29: 15.17 | S29: 15.17 | T29: 15.17 | U29: 15.17 | V29: 15.17 | W29: 15.17 | X29: 15.17 | Y29: 15.17 | Z29: 15.17 | AA29: 15.17 | AB29: =SUM(P29:AA29) -> 182.04 | AC29: 182.04 | AD29: 182.04
B30: fournistures Administrative | C30: 16.33 | D30: 16.33 | E30: 16.33 | F30: 16.33 | G30: 16.33 | H30: 16.33 | I30: 16.33 | J30: 16.33 | K30: 16.33 | L30: 16.33 | M30: 16.33 | N30: 16.33 | O30: =SUM(C30:N30) -> 195.96 | P30: 16 | Q30: 16 | R30: 16 | S30: 16 | T30: 16 | U30: 16 | V30: 16 | W30: 16 | X30: 16 | Y30: 16 | Z30: 16 | AA30: 16 | AB30: =SUM(P30:AA30) -> 192 | AC30: 200 | AD30: 200
B31: serveurs | C31: 9 | D31: 9 | E31: 9 | F31: 9 | G31: 9 | H31: 9 | I31: 9 | J31: 9 | K31: 9 | L31: 9 | M31: 9 | N31: 9 | O31: =SUM(C31:N31) -> 108 | AB31: 108 | AC31: 108 | AD31: 108
B32: Locaux | O32: =SUM(C32:N32) -> 0 | AB32: =SUM(P32:AA32) -> 0 | AC32: 0 | AD32: 0
B33: Fond de commerce | O33: =SUM(C33:N33) -> 0 | AB33: =SUM(P33:AA33) -> 0 | AC33: 0 | AD33: 0
B34: Frais d'agence - Fond de commerce | O34: =SUM(C34:N34) -> 0 | AB34: =SUM(P34:AA34) -> 0
A35: =285000 -> 285000 | B35: Caution BPI (4,06% du prêt 285k) | O35: =SUM(C35:N35) -> 0 | AB35: =SUM(P35:AA35) -> 0
B36: Dépôt de garantie loyer | O36: =SUM(C36:N36) -> 0 | AB36: =SUM(P36:AA36) -> 0 | AC36: 0 | AD36: 0
B37: Loyers et charges | H37: 2789 | I37: 2789 | J37: 2789 | K37: 2789 | L37: 2789 | M37: 2789 | N37: 2789 | O37: =SUM(C37:N37) -> 19523 | P37: 2789 | Q37: 2789 | R37: 2789 | S37: 2789 | T37: 2789 | U37: 2789 | V37: 2789 | W37: 2789 | X37: 2789 | Y37: 2789 | Z37: 2789 | AA37: 2789 | AB37: =SUM(P37:AA37) -> 33468 | AC37: 33468 | AD37: 33468
B38: Nettoyage | O38: =SUM(C38:N38) -> 0 | U38: 200 | AA38: 300 | AB38: =SUM(P38:AA38) -> 500 | AC38: 500 | AD38: 500
B39: alarme | G39: 99 | H39: 60.5 | I39: 60.5 | J39: 60.5 | K39: 60.5 | L39: 60.5 | M39: 60.5 | N39: 60.5 | O39: =SUM(C39:N39) -> 522.5 | P39: 73 | Q39: 73 | R39: 73 | S39: 73 | T39: 73 | U39: 73 | V39: 73 | W39: 73 | X39: 73 | Y39: 73 | Z39: 73 | AA39: 73 | AB39: =SUM(P39:AA39) -> 876 | AC39: 984 | AD39: 984
B40: Transports | O40: =SUM(C40:N40) -> 0 | P40: 50 | Q40: 50 | R40: 50 | S40: 50 | T40: 50 | U40: 50 | V40: 50 | W40: 50 | X40: 50 | Y40: 50 | Z40: 50 | AA40: 50 | AB40: =SUM(P40:AA40) -> 600 | AC40: 700 | AD40: 700
B41: Blanchisserie | O41: =SUM(C41:N41) -> 0 | P41: 285 | Q41: 285 | R41: 285 | S41: 285 | T41: 285 | U41: 285 | V41: 285 | W41: 285 | X41: 285 | Y41: 285 | Z41: 285 | AA41: 285 | AB41: =SUM(P41:AA41) -> 3420 | AC41: 3500 | AD41: 3500
B42: Dératisation | H42: 46 | I42: 46 | J42: 46 | K42: 46 | L42: 46 | M42: 46 | N42: 46 | O42: =SUM(C42:N42) -> 322 | P42: 46 | Q42: 46 | R42: 46 | S42: 46 | T42: 46 | U42: 46 | V42: 46 | W42: 46 | X42: 46 | Y42: 46 | Z42: 46 | AA42: 46 | AB42: =SUM(P42:AA42) -> 552 | AC42: 552 | AD42: 552
B44: Produits de nettoyage | H44: 100 | O44: =SUM(C44:N44) -> 100 | AA44: 200 | AB44: =SUM(P44:AA44) -> 200 | AC44: 200 | AD44: 200
B45: Energies | O45: =SUM(C45:N45) -> 0 | AB45: =SUM(P45:AA45) -> 0
O46: =SUM(C46:N46) -> 0 | AB46: =SUM(P46:AA46) -> 0
B47: Eau de Paris | O47: =SUM(C47:N47) -> 0 | AB47: =SUM(P47:AA47) -> 0
B48: EDF | C48: 470 | D48: 470 | E48: 470 | F48: 470 | G48: 470 | H48: 470 | I48: 470 | J48: 470 | K48: 470 | L48: 470 | M48: 470 | N48: 470 | O48: =SUM(C48:N48) -> 5640 | P48: 320 | Q48: 320 | R48: 320 | S48: 320 | T48: 320 | U48: 320 | V48: 320 | W48: 320 | X48: 320 | Y48: 320 | Z48: 320 | AA48: 320 | AB48: =SUM(P48:AA48) -> 3840 | AC48: 4000 | AD48: 4200
O49: =SUM(C49:N49) -> 0 | AB49: =SUM(P49:AA49) -> 0
B50: Obligations légales | O50: =SUM(C50:N50) -> 0 | AB50: =SUM(P50:AA50) -> 0
B51: Médecine de travail | C51: 100 | O51: =SUM(C51:N51) -> 100 | P51: 150 | AB51: 150 | AC51: 150 | AD51: 150
B52: Impots et taxes (hors IS) | O52: =SUM(C52:N52) -> 0 | AB52: =SUM(P52:AA52) -> 0
B53: CFE (Cot. Foncière des Entreprises) | C53: 26.08 | D53: 26.08 | E53: 26.08 | F53: 26.08 | G53: 26.08 | H53: 26.08 | I53: 26.08 | J53: 26.08 | K53: 26.08 | L53: 26.08 | M53: 26.08 | N53: 26.08 | O53: =SUM(C53:N53) -> 312.96 | P53: 26 | Q53: 26 | R53: 26 | S53: 26 | T53: 26 | U53: 26 | V53: 26 | W53: 26 | X53: 26 | Y53: 26 | Z53: 26 | AA53: 26 | AB53: =SUM(P53:AA53) -> 312 | AC53: 320 | AD53: 330
B54: CVAE (Cot. Valeur Ajoutée Entreprise) | O54: =SUM(C54:N54) -> 0 | AB54: =SUM(P54:AA54) -> 0
B55: Taxe foncière | N55: 1350 | O55: =SUM(C55:N55) -> 1350 | AA55: 1350 | AB55: =SUM(P55:AA55) -> 1350 | AC55: 1350 | AD55: 1350
B56: DUERP | N56: 100 | O56: =SUM(C56:N56) -> 100 | AA56: 100 | AB56: =SUM(P56:AA56) -> 100 | AC56: 100 | AD56: 100
B57: Formation professionnelle | O57: =SUM(C57:N57) -> 0 | AB57: =SUM(P57:AA57) -> 0
B58: mutuelle + retraite complémentaire salariés | C58: 56 | D58: 56 | E58: 56 | F58: 56 | G58: 56 | H58: 56 | I58: 56 | J58: 56 | K58: 56 | L58: 56 | M58: 56 | N58: 56 | O58: =SUM(C58:N58) -> 672 | AB58: 800 | AC58: 900 | AD58: 900
O59: =SUM(C59:N59) -> 0 | AB59: =SUM(P59:AA59) -> 0
O60: =SUM(C60:N60) -> 0 | AB60: =SUM(P60:AA60) -> 0
B61: Materiel de cuisine | O61: =SUM(C61:N61) -> 0 | AB61: =SUM(P61:AA61) -> 0 | AC61: 0 | AD61: 0
B62: petits équipements (vaisselles ...) | O62: =SUM(C62:N62) -> 0 | P62: 1000 | AB62: =SUM(P62:AA62) -> 1000 | AC62: 1000 | AD62: 1000
B63: Gros equipements ( four, cuisinère) | O63: =SUM(C63:N63) -> 0 | P63: 1000 | AB63: =SUM(P63:AA63) -> 1000 | AC63: 1000 | AD63: 1000
B64: uniforme | O64: =SUM(C64:N64) -> 0 | P64: 200 | AB64: =SUM(P64:AA64) -> 200
B65: conservateur vin | O65: =SUM(C65:N65) -> 0 | P65: 400
O66: =SUM(C66:N66) -> 0 | AB66: =SUM(P66:AA66) -> 0
O67: =SUM(C67:N67) -> 0 | AB67: =SUM(P67:AA67) -> 0
O68: =SUM(C68:N68) -> 0 | AB68: =SUM(P68:AA68) -> 0
B69: Outils et licences | O69: =SUM(C69:N69) -> 0 | AB69: =SUM(P69:AA69) -> 0
O70: =SUM(C70:N70) -> 0 | AB70: =SUM(P70:AA70) -> 0
B71: caisse enregistreuse | C71: 159 | D71: 159 | E71: 159 | F71: 159 | G71: 159 | H71: 159 | I71: 159 | J71: 159 | K71: 159 | L71: 159 | M71: 159 | N71: 159 | O71: =SUM(C71:N71) -> 1908 | P71: 159 | Q71: 159 | R71: 159 | S71: 159 | T71: 159 | U71: 159 | V71: 159 | W71: 159 | X71: 159 | Y71: 159 | Z71: 159 | AA71: 159 | AB71: =SUM(P71:AA71) -> 1908 | AC71: 2000 | AD71: 2200
B72: Ubereats et delivro abonnement | C72: 14 | D72: 14 | E72: 14 | F72: 14 | G72: 14 | H72: 14 | I72: 14 | J72: 14 | K72: 14 | L72: 14 | M72: 14 | N72: 14 | O72: =SUM(C72:N72) -> 168 | P72: 14 | Q72: 14 | R72: 14 | S72: 14 | T72: 14 | U72: 14 | V72: 14 | W72: 14 | X72: 14 | Y72: 14 | Z72: 14 | AA72: 14 | AB72: =SUM(P72:AA72) -> 168 | AC72: 168 | AD72: 168
B73: Sacem | C73: 60 | D73: 60 | E73: 60 | F73: 60 | G73: 60 | H73: 60 | I73: 60 | J73: 60 | K73: 60 | L73: 60 | M73: 60 | N73: 60 | O73: =SUM(C73:N73) -> 720 | P73: 60 | Q73: 60 | R73: 60 | S73: 60 | T73: 60 | U73: 60 | V73: 60 | W73: 60 | X73: 60 | Y73: 60 | Z73: 60 | AA73: 60 | AB73: =SUM(P73:AA73) -> 720 | AC73: 720 | AD73: 720
B74: gestion de personnel | O74: =SUM(C74:N74) -> 0 | P74: 110 | Q74: 110 | R74: 110 | S74: 110 | T74: 110 | U74: 110 | V74: 110 | W74: 110 | X74: 110 | Y74: 110 | Z74: 110 | AA74: 110 | AB74: =SUM(P74:AA74) -> 1320 | AC74: 1360 | AD74: 1360
B75: Entretien | O75: =SUM(C75:N75) -> 0 | AB75: =SUM(P75:AA75) -> 0
B76: Hotte | N76: 400 | O76: =SUM(C76:N76) -> 400 | AA76: 400 | AB76: =SUM(P76:AA76) -> 400 | AC76: 400 | AD76: 400
B77: machine à café | N77: 200 | O77: =SUM(C77:N77) -> 200 | AA77: 200 | AB77: =SUM(P77:AA77) -> 200 | AC77: 200 | AD77: 200
B78: eau Brita | C78: 100 | O78: =SUM(C78:N78) -> 100 | P78: 100 | AB78: =SUM(P78:AA78) -> 100 | AC78: 100 | AD78: 100
B79: Extincteur | N79: 200 | O79: =SUM(C79:N79) -> 200 | AA79: 100 | AB79: =SUM(P79:AA79) -> 100 | AC79: 100 | AD79: 100
B80: Ameublement & Travaux | O80: =SUM(C80:N80) -> 0 | AB80: =SUM(P80:AA80) -> 0
B81: Travaux de rafraishissement | O81: =SUM(C81:N81) -> 0 | P81: 1000 | AB81: =SUM(P81:AA81) -> 1000 | AC81: 1000 | AD81: 1000
B82: Meubles | O82: =SUM(C82:N82) -> 0 | P82: 1000 | AB82: =SUM(P82:AA82) -> 1000 | AC82: 1000 | AD82: 1000
B83: Décoration | O83: =SUM(C83:N83) -> 0 | P83: 500 | AB83: =SUM(P83:AA83) -> 500 | AC83: 500 | AD83: 500
O84: =SUM(C84:N84) -> 0 | AB84: =SUM(P84:AA84) -> 0
B85: Frais d'établissement | O85: =SUM(C85:N85) -> 0 | AB85: =SUM(P85:AA85) -> 0
B86: Registre des Commerces | O86: =SUM(C86:N86) -> 0 | AB86: =SUM(P86:AA86) -> 0
B87: Stage à l'installation Chambre des Metiers | O87: =SUM(C87:N87) -> 0 | AB87: =SUM(P87:AA87) -> 0
B88: Repertoire des Métiers | O88: =SUM(C88:N88) -> 0 | AB88: =SUM(P88:AA88) -> 0
B89: Bodacc | O89: =SUM(C89:N89) -> 0 | AB89: =SUM(P89:AA89) -> 0
B90: Publication | O90: =SUM(C90:N90) -> 0 | AB90: =SUM(P90:AA90) -> 0
B91: frais INPI | O91: =SUM(C91:N91) -> 0 | AB91: =SUM(P91:AA91) -> 0
O92: =SUM(C92:N92) -> 0 | AB92: =SUM(P92:AA92) -> 0
O93: =SUM(C93:N93) -> 0 | AB93: =SUM(P93:AA93) -> 0
B94: Total Charges Externes | C94: =SUM(C7:C93) -> 1010.41 | D94: =SUM(D7:D93) -> 810.41 | E94: =SUM(E7:E93) -> 810.41 | F94: =SUM(F7:F93) -> 810.41 | G94: =SUM(G7:G93) -> 1992.58 | H94: =SUM(H7:H93) -> 5889.08 | I94: =SUM(I7:I93) -> 4789.08 | J94: =SUM(J7:J93) -> 4789.08 | ... AD94: =SUM(AD7:AD93) -> 72171.04
N95: check | O95: =IF(SUM(C94:N94)=O94,0,O94-SUM(C94:N94)) -> 0 | AB95: =IF(SUM(P94:AA94)=AB94,0,AB94-SUM(P94:AA94)) -> 508

Sheet Détail investissements
B2: Details d'investissement
C4: =YEAR(date_début) -> 2025 | P4: =YEAR(EDATE(date_début,12)) -> 2026 | AC4: =YEAR(EDATE(date_début,24)) -> 2027 | AD4: =YEAR(EDATE(date_début,36)) -> 2028
C5: Jan | D5: Fév | E5: Mar | F5: Avr | G5: Mai | H5: Juin | I5: Juil | J5: Aout | K5: Sept | L5: Oct | M5: Nov | N5: Déc | P5: Jan | Q5: Fév | R5: Mar | S5: Avr | T5: Mai | U5: Juin | V5: Juil | W5: Aout | X5: Sept | Y5: Oct | Z5: Nov | AA5: Déc
B7: IMMOBILISATIONS INCORPORELLES | O7: =SUM(C7:N7) -> 0 | AB7: =SUM(P7:AA7) -> 0 | AC7: 0 | AD7: 0
B8: Frais d'établissement | G8: 787 | O8: =SUM(C8:N8) -> 787 | AB8: =SUM(P8:AA8) -> 0 | AC8: 0 | AD8: 0
B9: Registre des Commerces | O9: =SUM(C9:N9) -> 0 | AB9: =SUM(P9:AA9) -> 0 | AC9: 0 | AD9: 0
B10: Stage à l'installation Chambre des Metiers | O10: =SUM(C10:N10) -> 0 | AB10: =SUM(P10:AA10) -> 0 | AC10: 0 | AD10: 0
B11: Repertoire des Métiers | O11: =SUM(C11:N11) -> 0 | AB11: =SUM(P11:AA11) -> 0 | AC11: 0 | AD11: 0
B12: Bodacc | O12: =SUM(C12:N12) -> 0 | AB12: =SUM(P12:AA12) -> 0 | AC12: 0 | AD12: 0
B13: Publication | O13: =SUM(C13:N13) -> 0 | AB13: =SUM(P13:AA13) -> 0 | AC13: 0 | AD13: 0
B14: Autre | O14: =SUM(C14:N14) -> 0 | AB14: =SUM(P14:AA14) -> 0 | AC14: 0 | AD14: 0
O15: =SUM(C15:N15) -> 0 | AB15: =SUM(P15:AA15) -> 0 | AC15: 0 | AD15: 0
O16: =SUM(C16:N16) -> 0 | AB16: =SUM(P16:AA16) -> 0 | AC16: 0 | AD16: 0
B17: Publicité de démarrage | O17: =SUM(C17:N17) -> 0 | AB17: =SUM(P17:AA17) -> 0 | AC17: 0 | AD17: 0
B18: Marketing - Site web | O18: =SUM(C18:N18) -> 0 | AB18: =SUM(P18:AA18) -> 0 | AC18: 0 | AD18: 0
B19: Marketing - Marque | H19: 2000 | O19: =SUM(C19:N19) -> 2000 | AB19: =SUM(P19:AA19) -> 0 | AC19: 0 | AD19: 0
B20: carte visite | O20: =SUM(C20:N20) -> 0 | AB20: =SUM(P20:AA20) -> 0 | AC20: 0 | AD20: 0
B21: sponsorising | O21: =SUM(C21:N21) -> 0 | AB21: =SUM(P21:AA21) -> 0 | AC21: 0 | AD21: 0
B22: clip vidéo | O22: =SUM(C22:N22) -> 0 | AB22: =SUM(P22:AA22) -> 0 | AC22: 0 | AD22: 0
B23: affichage et enseigne | H23: 2000 | O23: =SUM(C23:N23) -> 2000 | AB23: =SUM(P23:AA23) -> 0 | AC23: 0 | AD23: 0
B24: inauguration - privée | O24: =SUM(C24:N24) -> 0 | AB24: =SUM(P24:AA24) -> 0 | AC24: 0 | AD24: 0
B25: Goodies | O25: =SUM(C25:N25) -> 0 | AB25: =SUM(P25:AA25) -> 0 | AC25: 0 | AD25: 0
B26: publicité instagram | O26: =SUM(C26:N26) -> 0
O27: =SUM(C27:N27) -> 0
B28: Logiciels | O28: =SUM(C28:N28) -> 0
B29: Gestion des stocks/clients | O29: =SUM(C29:N29) -> 0
B30: Logiciel de Caisse | G30: 748 | O30: =SUM(C30:N30) -> 748
B31: Comptabilité/Facturation | O31: =SUM(C31:N31) -> 0
B32: Bureautique (office) | O32: =SUM(C32:N32) -> 0
O33: =SUM(C33:N33) -> 0
O34: =SUM(C34:N34) -> 0
B35: Droit au bail ou Fonds de Commerce | O35: =SUM(C35:N35) -> 0
B36: Fond de commerce | G36: 135000 | O36: =SUM(C36:N36) -> 135000
B39: Droit d'enregistrement
B40: Droit d'enregistrement | G40: 4500 | O40: =SUM(C40:N40) -> 4500
B42: Autres : frais agences-honoraires-formation | O42: =SUM(C42:N42) -> 0
B43: Frais d'Agence immobiliere | G43: 15000 | O43: =SUM(C43:N43) -> 15000
B44: Frais d'Expert comptable | O44: =SUM(C44:N44) -> 0
B45: Frais d'Avocat | G45: 3500 | O45: =SUM(C45:N45) -> 3500
B46: Formations Hygiene et exploitation | G46: 749 | O46: =SUM(C46:N46) -> 749
B47: Frais INPI | G47: 190 | O47: =SUM(C47:N47) -> 190
B48: Autre | O48: =SUM(C48:N48) -> 0
B49: formation Barista | G49: 600 | O49: =SUM(C49:N49) -> 600
B50: Formation pré-ouveture | G50: 2000 | O50: =SUM(C50:N50) -> 2000
O51: =SUM(C51:N51) -> 0
O52: =SUM(C52:N52) -> 0
B53: Total imobilisations incoporelles | C53: =SUM(C8:C52) -> 0 | D53: =SUM(D8:D52) -> 0 | E53: =SUM(E8:E52) -> 0 | F53: =SUM(F8:F52) -> 0 | G53: =SUM(G8:G52) -> 163074 | H53: =SUM(H8:H52) -> 4000 | I53: =SUM(I8:I52) -> 0 | J53: =SUM(J8:J52) -> 0 | ... AD53: =SUM(AD8:AD52) -> 0
N54: check | O54: =IF(SUM(C53:N53)=O53,0,O53-SUM(C53:N53)) -> 0
B55: IMMOBILISATIONS CORPORELLES | O55: =SUM(C55:N55) -> 0
B56: Agencements et Aménagement | O56: =SUM(C56:N56) -> 0
B57: Travaux | G57: 35000 | O57: =SUM(C57:N57) -> 35000
B58: Architecture d'interieur | G58: 10000 | O58: =SUM(C58:N58) -> 10000
B59: Décoration | G59: 10000 | O59: =SUM(C59:N59) -> 10000
B60: Devanture | G60: 10000 | O60: =SUM(C60:N60) -> 10000
B61: Equipements & Ameublement | G61: 15000 | O61: =SUM(C61:N61) -> 15000
B62: Table | O62: =SUM(C62:N62) -> 0
B63: tabouret bar | O63: =SUM(C63:N63) -> 0
B64: Chaises | O64: =SUM(C64:N64) -> 0
B65: Plan de travail | O65: =SUM(C65:N65) -> 0
B66: Etageres/Armoires | O66: =SUM(C66:N66) -> 0
B67: Comptoir | O67: =SUM(C67:N67) -> 0
O68: =SUM(C68:N68) -> 0
O69: =SUM(C69:N69) -> 0
B70: Matériel informatique | O70: =SUM(C70:N70) -> 0
B71: Appareils Photos (objectif) | O71: =SUM(C71:N71) -> 0
B72: Imprimantes - fax | O72: =SUM(C72:N72) -> 0
B73: Cartouche + rame de papier+fournitures de bureau | O73: =SUM(C73:N73) -> 0
B74: Tablettes | O74: =SUM(C74:N74) -> 0
B75: Ordinateur de bureau | O75: =SUM(C75:N75) -> 0
B76: Ordinateur portable | O76: =SUM(C76:N76) -> 0
B77: Telephone portable | O77: =SUM(C77:N77) -> 0
B78: Telephone fixe | O78: =SUM(C78:N78) -> 0
B79: Materiel Audio | O79: =SUM(C79:N79) -> 0
B80: Lecteur CB | O80: =SUM(C80:N80) -> 0
B81: Caisse | O81: =SUM(C81:N81) -> 0
... B85: Autre | O85: =SUM(C85:N85) -> 0
O86: =SUM(C86:N86) -> 0
O87: =SUM(C87:N87) -> 0
B88: Matériel professionnel | O88: =SUM(C88:N88) -> 0
B89: gros équipements | G89: 5353 | O89: =SUM(C89:N89) -> 5353
B90: petits équipements | G90: 3000 | O90: =SUM(C90:N90) -> 3000
B91: vaisselle | G91: 2500 | O91: =SUM(C91:N91) -> 2500
B92: conservateur de vin | O92: =SUM(C92:N92) -> 0
B93: machine à café | G93: 15000 | O93: =SUM(C93:N93) -> 15000
O94: =SUM(C94:N94) -> 0
O95: =SUM(C95:N95) -> 0
B96: Véhicule professionnel- Transport | O96: =SUM(C96:N96) -> 0
O97: =SUM(C97:N97) -> 0
B98: Autres (Tenue Professionnelle) | G98: 500 | O98: =SUM(C98:N98) -> 500
O99: =SUM(C99:N99) -> 0
B100: Total immobilisations corporelles | C100: =SUM(C56:C99) -> 0 | D100: =SUM(D56:D99) -> 0 | E100: =SUM(E56:E99) -> 0 | F100: =SUM(F56:F99) -> 0 | G100: =SUM(G56:G99) -> 106353 | H100: =SUM(H56:H99) -> 0 | I100: =SUM(I56:I99) -> 0 | J100: =SUM(J56:J99) -> 0 | ... AD100: =SUM(AD56:AD99) -> 0
N101: check | O101: =IF(SUM(C100:N100)=O100,0,O100-SUM(C100:N100)) -> 0
B102: IMMOBILISATIONS FINANCIERES | O102: =SUM(C102:N102) -> 0
B103: Dépôt de garantie et caution bancaire | O103: =SUM(C103:N103) -> 0
B104: Dépôt de garantie (3 à 6 mois de loyer) | G104: 7335.13 | O104: =SUM(C104:N104) -> 7335.13
B105: Caution bancaire (loyer bloqué parfois entre 3 et 18 mois) | O105: =SUM(C105:N105) -> 0
O106: =SUM(C106:N106) -> 0
B107: garantie professionnelle | O107: =SUM(C107:N107) -> 0
B108: garantie 1 - Caution BPI (3,60% du 50%capital emprunté) | O108: =SUM(C108:N108) -> 0
B109: garantie 2 | O109: =SUM(C109:N109) -> 0
...

Sheet Insights 1h
A2: OFFRE RESTAURATION
C3: Heure-Jour
C4: % remplissage horaire | D4: 8 | E4: 9 | F4: 10 | G4: 11 | H4: 12 | I4: 13 | J4: 14 | K4: 15 | L4: 16 | M4: 17
C5: client A | D5: 0.35 | E5: 0.35 | F5: 0.15 | G5: 0.05 | J5: 0.35 | K5: 0.35 | L5: 0.4 | M5: 0.45
C6: client B | D6: 0.45 | E6: 0.45 | F6: 0.35 | G6: 0.1 | J6: 0.35 | K6: 0.35 | L6: 0.55 | M6: 0.55
C7: client C | D7: 0.1 | E7: 0.1 | F7: 0.3 | G7: 0.3 | H7: 0.3 | I7: 0.3 | J7: 0.15 | K7: 0.15 | L7: 0.05
C8: client D | D8: 0.05 | E8: 0.05 | F8: 0.1 | G8: 0.3 | H8: 0.35 | I8: 0.35 | J8: 0.1 | K8: 0.1
C9: client E | D9: 0.05 | E9: 0.05 | F9: 0.05 | G9: 0.15 | H9: 0.15 | I9: 0.15 | J9: 0.05 | K9: 0.05
C10: client F | F10: 0.05 | G10: 0.1 | H10: 0.2 | I10: 0.2
D11: =SUM(D5:D10) -> 1 | E11: =SUM(E5:E10) -> 1 | F11: =SUM(F5:F10) -> 1 | G11: =SUM(G5:G10) -> 1 | H11: =SUM(H5:H10) -> 1 | I11: =SUM(I5:I10) -> 1 | J11: =SUM(J5:J10) -> 1 | K11: =SUM(K5:K10) -> 1 | ... M11: =SUM(M5:M10) -> 1
C14: Heure-Jour
D15: 8 | E15: 9 | F15: 10 | G15: 11 | H15: 12 | I15: 13 | J15: 14 | K15: 15 | L15: 16 | M15: 17
C16: Nombre de clients | D16: 5 | E16: 10 | F16: 24 | G16: 20 | H16: 30 | I16: 35 | J16: 20 | K16: 15 | L16: 15 | M16: 10
C17: client A | D17: =ROUND( D$16*D5,0) -> 2 | E17: =ROUND( E$16*E5,0) -> 4 | F17: =ROUND( F$16*F5,0) -> 4 | G17: =ROUND( G$16*G5,0) -> 1 | H17: =ROUND( H$16*H5,0) -> 0 | I17: =ROUND( I$16*I5,0) -> 0 | J17: =ROUND( J$16*J5,0) -> 7 | K17: =ROUND( K$16*K5,0) -> 5 | ... M17: =ROUND( M$16*M5,0) -> 5
C18: client B | D18: =ROUND( D$16*D6,0) -> 2 | E18: =ROUND( E$16*E6,0) -> 5 | F18: =ROUND( F$16*F6,0) -> 8 | G18: =ROUND( G$16*G6,0) -> 2 | H18: =ROUND( H$16*H6,0) -> 0 | I18: =ROUND( I$16*I6,0) -> 0 | J18: =ROUND( J$16*J6,0) -> 7 | K18: =ROUND( K$16*K6,0) -> 5 | ... M18: =ROUND( M$16*M6,0) -> 6
C19: client C | D19: =ROUND( D$16*D7,0) -> 1 | E19: =ROUND( E$16*E7,0) -> 1 | F19: =ROUND( F$16*F7,0) -> 7 | G19: =ROUND( G$16*G7,0) -> 6 | H19: =ROUND( H$16*H7,0) -> 9 | I19: =ROUND( I$16*I7,0) -> 11 | J19: =ROUND( J$16*J7,0) -> 3 | K19: =ROUND( K$16*K7,0) -> 2 | ... M19: =ROUND( M$16*M7,0) -> 0
C20: client D | D20: =ROUND( D$16*D8,0) -> 0 | E20: =ROUND( E$16*E8,0) -> 1 | F20: =ROUND( F$16*F8,0) -> 2 | G20: =ROUND( G$16*G8,0) -> 6 | H20: =ROUND( H$16*H8,0) -> 11 | I20: =ROUND( I$16*I8,0) -> 12 | J20: =ROUND( J$16*J8,0) -> 2 | K20: =ROUND( K$16*K8,0) -> 2 | ... M20: =ROUND( M$16*M8,0) -> 0
C21: client E | D21: =ROUND( D$16*D9,0) -> 0 | E21: =ROUND( E$16*E9,0) -> 1 | F21: =ROUND( F$16*F9,0) -> 1 | G21: =ROUND( G$16*G9,0) -> 3 | H21: =ROUND( H$16*H9,0) -> 5 | I21: =ROUND( I$16*I9,0) -> 5 | J21: =ROUND( J$16*J9,0) -> 1 | K21: =ROUND( K$16*K9,0) -> 1 | ... M21: =ROUND( M$16*M9,0) -> 0
C22: client F | D22: =ROUND( D$16*D10,0) -> 0 | E22: =ROUND( E$16*E10,0) -> 0 | F22: =ROUND( F$16*F10,0) -> 1 | G22: =ROUND( G$16*G10,0) -> 2 | H22: =ROUND( H$16*H10,0) -> 6 | I22: =ROUND( I$16*I10,0) -> 7 | J22: =ROUND( J$16*J10,0) -> 0 | K22: =ROUND( K$16*K10,0) -> 0 | ... M22: =ROUND( M$16*M10,0) -> 0
D23: =SUM(D17:D22) -> 5 | E23: =SUM(E17:E22) -> 12 | F23: =SUM(F17:F22) -> 23 | G23: =SUM(G17:G22) -> 20 | H23: =SUM(H17:H22) -> 31 | I23: =SUM(I17:I22) -> 35 | J23: =SUM(J17:J22) -> 20 | K23: =SUM(K17:K22) -> 15 | ... M23: =SUM(M17:M22) -> 11
C25: jour/mois | D25: mardi | E25: mercredi | F25: jeudi | G25: vendredi | H25: samedi | I25: dimanche | J25: mardi | K25: mercredi | L25: jeudi | M25: vendredi | N25: samedi | O25: dimanche | P25: mardi | Q25: mercredi | R25: jeudi | S25: vendredi | T25: samedi | U25: dimanche | V25: mardi | W25: mercredi | X25: jeudi | Y25: vendredi | Z25: samedi | AA25: dimanche
D26: 1 | E26: 2 | F26: 3 | G26: 4 | H26: 5 | I26: 6 | J26: 7 | K26: 8 | L26: 9 | M26: 10 | N26: 11 | O26: 12 | P26: 13 | Q26: 14 | R26: 15 | S26: 16 | T26: 17 | U26: 18 | V26: 19 | W26: 20 | X26: 21 | Y26: 22 | Z26: 23 | AA26: 24
C27: % remplissage journalier | D27: 0.5 | E27: 0.6 | F27: 0.6 | G27: 0.7 | H27: 0.9 | I27: 0.9 | J27: 0.5 | K27: 0.6 | L27: 0.6 | M27: 0.7 | N27: 0.9 | O27: 0.9 | P27: 0.5 | Q27: 0.6 | R27: 0.6 | S27: 0.7 | T27: 0.9 | U27: 0.9 | V27: 0.5 | W27: 0.6 | X27: 0.6 | Y27: 0.7 | Z27: 0.9 | AA27: 0.9
C28: client A | D28: =ROUND(SUM($D17:$M17)*D$27,0) -> 17 | E28: =ROUND(SUM($D17:$M17)*E27,0) -> 20 | F28: =ROUND(SUM($D17:$M17)*F27,0) -> 20 | G28: =ROUND(SUM($D17:$M17)*G27,0) -> 24 | H28: =ROUND(SUM($D17:$M17)*H27,0) -> 31 | I28: =ROUND(SUM($D17:$M17)*I27,0) -> 31 | J28: =ROUND(SUM($D17:$M17)*J27,0) -> 17 | K28: =ROUND(SUM($D17:$M17)*K27,0) -> 20 | L28: =ROUND(SUM($D17:$M17)*L27,0) -> 20 | ... AA28: =ROUND(SUM($D17:$M17)*AA27,0) -> 31
C29: client B | D29: =ROUND(SUM($D18:$M18)*D$27,0) -> 22 | E29: =ROUND(SUM($D18:$M18)*E$27,0) -> 26 | F29: =ROUND(SUM($D18:$M18)*F$27,0) -> 26 | G29: =ROUND(SUM($D18:$M18)*G$27,0) -> 30 | H29: =ROUND(SUM($D18:$M18)*H$27,0) -> 39 | I29: =ROUND(SUM($D18:$M18)*I$27,0) -> 39 | J29: =ROUND(SUM($D18:$M18)*J$27,0) -> 22 | K29: =ROUND(SUM($D18:$M18)*K$27,0) -> 26 | ... AA29: =ROUND(SUM($D18:$M18)*AA$27,0) -> 39
C30: client C | D30: =ROUND(SUM($D19:$M19)*D$27,0) -> 21 | E30: =ROUND(SUM($D19:$M19)*E$27,0) -> 25 | F30: =ROUND(SUM($D19:$M19)*F$27,0) -> 25 | G30: =ROUND(SUM($D19:$M19)*G$27,0) -> 29 | H30: =ROUND(SUM($D19:$M19)*H$27,0) -> 37 | I30: =ROUND(SUM($D19:$M19)*I$27,0) -> 37 | J30: =ROUND(SUM($D19:$M19)*J$27,0) -> 21 | K30: =ROUND(SUM($D19:$M19)*K$27,0) -> 25 | ... AA30: =ROUND(SUM($D19:$M19)*AA$27,0) -> 37
C31: client D | D31: =ROUND(SUM($D20:$M20)*D$27,0) -> 18 | E31: =ROUND(SUM($D20:$M20)*E$27,0) -> 22 | F31: =ROUND(SUM($D20:$M20)*F$27,0) -> 22 | G31: =ROUND(SUM($D20:$M20)*G$27,0) -> 25 | H31: =ROUND(SUM($D20:$M20)*H$27,0) -> 32 | I31: =ROUND(SUM($D20:$M20)*I$27,0) -> 32 | J31: =ROUND(SUM($D20:$M20)*J$27,0) -> 18 | K31: =ROUND(SUM($D20:$M20)*K$27,0) -> 22 | ... AA31: =ROUND(SUM($D20:$M20)*AA$27,0) -> 32
C32: client E | D32: =ROUND(SUM($D21:$M21)*D$27,0) -> 9 | E32: =ROUND(SUM($D21:$M21)*E$27,0) -> 10 | F32: =ROUND(SUM($D21:$M21)*F$27,0) -> 10 | G32: =ROUND(SUM($D21:$M21)*G$27,0) -> 12 | H32: =ROUND(SUM($D21:$M21)*H$27,0) -> 15 | I32: =ROUND(SUM($D21:$M21)*I$27,0) -> 15 | J32: =ROUND(SUM($D21:$M21)*J$27,0) -> 9 | K32: =ROUND(SUM($D21:$M21)*K$27,0) -> 10 | ... AA32: =ROUND(SUM($D21:$M21)*AA$27,0) -> 15
C33: client F | D33: =ROUND(SUM($D22:$M22)*D$27,0) -> 8 | E33: =ROUND(SUM($D22:$M22)*E$27,0) -> 10 | F33: =ROUND(SUM($D22:$M22)*F$27,0) -> 10 | G33: =ROUND(SUM($D22:$M22)*G$27,0) -> 11 | H33: =ROUND(SUM($D22:$M22)*H$27,0) -> 14 | I33: =ROUND(SUM($D22:$M22)*I$27,0) -> 14 | J33: =ROUND(SUM($D22:$M22)*J$27,0) -> 8 | K33: =ROUND(SUM($D22:$M22)*K$27,0) -> 10 | ... AA33: =ROUND(SUM($D22:$M22)*AA$27,0) -> 14
D34: =SUM(D28:D33) -> 95 | E34: =SUM(E28:E33) -> 113 | F34: =SUM(F28:F33) -> 113 | G34: =SUM(G28:G33) -> 131 | H34: =SUM(H28:H33) -> 168 | I34: =SUM(I28:I33) -> 168 | J34: =SUM(J28:J33) -> 95 | K34: =SUM(K28:K33) -> 113 | ... AA34: =SUM(AA28:AA33) -> 168
C36: Evolution des mois
D37: 2024 | K37: aout | P37: 2025 | W37: aout
C38: Mois | D38: 1 | E38: 2 | F38: 3 | G38: 4 | H38: 5 | I38: 6 | J38: 7 | K38: 8 | L38: 9 | M38: 10 | N38: 11 | O38: 12 | P38: 1 | Q38: 2 | R38: 3 | S38: 4 | T38: 5 | U38: 6 | V38: 7 | W38: 8 | X38: 9 | Y38: 10 | Z38: 11 | AA38: 12
C39: % remplissage mensuel | D39: 0.05 | E39: 0.1 | F39: 0.25 | G39: 0.3 | H39: 0.5 | I39: 0.8 | J39: 0.8 | K39: 0.2 | L39: 0.6 | M39: 0.6 | N39: 0.6 | O39: 0.4 | P39: 0.5 | Q39: 0.6 | R39: 0.7 | S39: 0.7 | T39: 0.8 | U39: 0.9 | V39: 0.9 | W39: 0.3 | X39: 0.9 | Y39: 0.8 | Z39: 0.7 | AA39: 0.5
C40: client A | D40: =ROUND(SUM($D28:$AA28)*D$39,0) -> 29 | E40: =ROUND(SUM($D28:$AA28)*E$39,0) -> 57 | F40: =ROUND(SUM($D28:$AA28)*F$39,0) -> 143 | G40: =ROUND(SUM($D28:$AA28)*G$39,0) -> 172 | H40: =ROUND(SUM($D28:$AA28)*H$39,0) -> 286 | I40: =ROUND(SUM($D28:$AA28)*I$39,0) -> 458 | J40: =ROUND(SUM($D28:$AA28)*J$39,0) -> 458 | K40: =ROUND(SUM($D28:$AA28)*K$39,0) -> 114 | ... AA40: =ROUND(SUM($D28:$AA28)*AA$39,0) -> 286
C41: client B | D41: =ROUND(SUM($D29:$AA29)*D$39,0) -> 36 | E41: =ROUND(SUM($D29:$AA29)*E$39,0) -> 73 | F41: =ROUND(SUM($D29:$AA29)*F$39,0) -> 182 | G41: =ROUND(SUM($D29:$AA29)*G$39,0) -> 218 | H41: =ROUND(SUM($D29:$AA29)*H$39,0) -> 364 | I41: =ROUND(SUM($D29:$AA29)*I$39,0) -> 582 | J41: =ROUND(SUM($D29:$AA29)*J$39,0) -> 582 | K41: =ROUND(SUM($D29:$AA29)*K$39,0) -> 146 | ... AA41: =ROUND(SUM($D29:$AA29)*AA$39,0) -> 364
C42: client C | D42: =ROUND(SUM($D30:$AA30)*D$39,0) -> 35 | E42: =ROUND(SUM($D30:$AA30)*E$39,0) -> 70 | F42: =ROUND(SUM($D30:$AA30)*F$39,0) -> 174 | G42: =ROUND(SUM($D30:$AA30)*G$39,0) -> 209 | H42: =ROUND(SUM($D30:$AA30)*H$39,0) -> 348 | I42: =ROUND(SUM($D30:$AA30)*I$39,0) -> 557 | J42: =ROUND(SUM($D30:$AA30)*J$39,0) -> 557 | K42: =ROUND(SUM($D30:$AA30)*K$39,0) -> 139 | ... AA42: =ROUND(SUM($D30:$AA30)*AA$39,0) -> 348
C43: client D | D43: =ROUND(SUM($D31:$AA31)*D$39,0) -> 30 | E43: =ROUND(SUM($D31:$AA31)*E$39,0) -> 60 | F43: =ROUND(SUM($D31:$AA31)*F$39,0) -> 151 | G43: =ROUND(SUM($D31:$AA31)*G$39,0) -> 181 | H43: =ROUND(SUM($D31:$AA31)*H$39,0) -> 302 | I43: =ROUND(SUM($D31:$AA31)*I$39,0) -> 483 | J43: =ROUND(SUM($D31:$AA31)*J$39,0) -> 483 | K43: =ROUND(SUM($D31:$AA31)*K$39,0) -> 121 | ... AA43: =ROUND(SUM($D31:$AA31)*AA$39,0) -> 302
C44: client E | D44: =ROUND(SUM($D32:$AA32)*D$39,0) -> 14 | E44: =ROUND(SUM($D32:$AA32)*E$39,0) -> 28 | F44: =ROUND(SUM($D32:$AA32)*F$39,0) -> 71 | G44: =ROUND(SUM($D32:$AA32)*G$39,0) -> 85 | H44: =ROUND(SUM($D32:$AA32)*H$39,0) -> 142 | I44: =ROUND(SUM($D32:$AA32)*I$39,0) -> 227 | J44: =ROUND(SUM($D32:$AA32)*J$39,0) -> 227 | K44: =ROUND(SUM($D32:$AA32)*K$39,0) -> 57 | ... AA44: =ROUND(SUM($D32:$AA32)*AA$39,0) -> 142
C45: client F | D45: =ROUND(SUM($D33:$AA33)*D$39,0) -> 13 | E45: =ROUND(SUM($D33:$AA33)*E$39,0) -> 27 | F45: =ROUND(SUM($D33:$AA33)*F$39,0) -> 67 | G45: =ROUND(SUM($D33:$AA33)*G$39,0) -> 80 | H45: =ROUND(SUM($D33:$AA33)*H$39,0) -> 134 | I45: =ROUND(SUM($D33:$AA33)*I$39,0) -> 214 | J45: =ROUND(SUM($D33:$AA33)*J$39,0) -> 214 | K45: =ROUND(SUM($D33:$AA33)*K$39,0) -> 54 | ... AA45: =ROUND(SUM($D33:$AA33)*AA$39,0) -> 134
D46: =SUM(D40:D45) -> 157 | E46: =SUM(E40:E45) -> 315 | F46: =SUM(F40:F45) -> 788 | G46: =SUM(G40:G45) -> 945 | H46: =SUM(H40:H45) -> 1576 | I46: =SUM(I40:I45) -> 2521 | J46: =SUM(J40:J45) -> 2521 | K46: =SUM(K40:K45) -> 631 | ... AA46: =SUM(AA40:AA45) -> 1576
C49: CA jour/mois
D50: 2024 | P50: 2025
C51: Mois | D51: 1 | E51: 2 | F51: 3 | G51: 4 | H51: 5 | I51: 6 | J51: 7 | K51: 8 | L51: 9 | M51: 10 | N51: 11 | O51: 12 | P51: 1 | Q51: 2 | R51: 3 | S51: 4 | T51: 5 | U51: 6 | V51: 7 | W51: 8 | X51: 9 | Y51: 10 | Z51: 11 | AA51: 12
C52: CA moyen journalier | D52: =D53/24 -> 70.840909 | E52: =E53/24 -> 141.85606 | F52: =F53/24 -> 355.5625 | G52: =G53/24 -> 426.40341 | H52: =H53/24 -> 711.125 | I52: =I53/24 -> 1137.5284 | J52: =J53/24 -> 1137.5284 | K52: =K53/24 -> 284.72159 | ... AA52: =AA53/24 -> 711.125
C53: CA mensuel | D53: =SUM(D54:D59) -> 1700.1818 | E53: =SUM(E54:E59) -> 3404.5455 | F53: =SUM(F54:F59) -> 8533.5 | G53: =SUM(G54:G59) -> 10233.682 | H53: =SUM(H54:H59) -> 17067 | I53: =SUM(I54:I59) -> 27300.682 | J53: =SUM(J54:J59) -> 27300.682 | K53: =SUM(K54:K59) -> 6833.3182 | ... AA53: =SUM(AA54:AA59) -> 17067
B54: =UNIT_PRICE_CLIENT_A -> 5 | C54: client A | D54: =D40*$B54 -> 145 | E54: =E40*$B54 -> 285 | F54: =F40*$B54 -> 715 | G54: =G40*$B54 -> 860 | H54: =H40*$B54 -> 1430 | I54: =I40*$B54 -> 2290 | J54: =J40*$B54 -> 2290 | K54: =K40*$B54 -> 570 | ... AA54: =AA40*$B54 -> 1430
B55: =UNIT_PRICE_CLIENT_B -> 9.1818182 | C55: client B | D55: =D41*$B55 -> 330.54545 | E55: =E41*$B55 -> 670.27273 | F55: =F41*$B55 -> 1671.0909 | G55: =G41*$B55 -> 2001.6364 | H55: =H41*$B55 -> 3342.1818 | I55: =I41*$B55 -> 5343.8182 | J55: =J41*$B55 -> 5343.8182 | K55: =K41*$B55 -> 1340.5455 | ... AA55: =AA41*$B55 -> 3342.1818
B56: =UNIT_PRICE_CLIENT_C -> 12.727273 | C56: client C | D56: =D42*$B56 -> 445.45455 | E56: =E42*$B56 -> 890.90909 | F56: =F42*$B56 -> 2214.5455 | G56: =G42*$B56 -> 2660 | H56: =H42*$B56 -> 4429.0909 | I56: =I42*$B56 -> 7089.0909 | J56: =J42*$B56 -> 7089.0909 | K56: =K42*$B56 -> 1769.0909 | ... AA56: =AA42*$B56 -> 4429.0909
B57: =UNIT_PRICE_CLIENT_D -> 16.363636 | C57: client D | D57: =D43*$B57 -> 490.90909 | E57: =E43*$B57 -> 981.81818 | F57: =F43*$B57 -> 2470.9091 | G57: =G43*$B57 -> 2961.8182 | H57: =H43*$B57 -> 4941.8182 | I57: =I43*$B57 -> 7903.6364 | J57: =J43*$B57 -> 7903.6364 | K57: =K43*$B57 -> 1980 | ... AA57: =AA43*$B57 -> 4941.8182
B58: =UNIT_PRICE_CLIENT_E -> 20.590909 | C58: client E | D58: =D44*$B58 -> 288.27273 | E58: =E44*$B58 -> 576.54545 | F58: =F44*$B58 -> 1461.9545 | G58: =G44*$B58 -> 1750.2273 | H58: =H44*$B58 -> 2923.9091 | I58: =I44*$B58 -> 4674.1364 | J58: =J44*$B58 -> 4674.1364 | K58: =K44*$B58 -> 1173.6818 | ... AA58: =AA44*$B58 -> 2923.9091
B59: =UNIT_PRICE_CLIENT_F -> 0 | C59: client F | D59: =D45*$B59 -> 0 | E59: =E45*$B59 -> 0 | F59: =F45*$B59 -> 0 | G59: =G45*$B59 -> 0 | H59: =H45*$B59 -> 0 | I59: =I45*$B59 -> 0 | J59: =J45*$B59 -> 0 | K59: =K45*$B59 -> 0 | ... AA59: =AA45*$B59 -> 0
D60: =SUM(D53:O53) -> 177450.68 | P60: =SUM(P53:AA53) -> 283329.91
O62: =(P60-D60)/D60 -> 0.59666847
A73: OFFRE LIVRAISON / A EMPORTER
C74: Heure-Jour
C75: % remplissage journalier | D75: 8 | E75: 9 | F75: 10 | G75: 11 | H75: 12 | I75: 13 | J75: 14 | K75: 15 | L75: 16 | M75: 17
C76: client A | D76: 0.35 | E76: 0.5 | F76: 0.5 | G76: 0.05 | H76: 0.02 | J76: 0.2 | K76: 0.2 | L76: 0.4 | M76: 0.45
C77: client B | D77: 0.35 | E77: 0.4 | F77: 0.3 | G77: 0.1 | H77: 0.05 | J77: 0.25 | K77: 0.35 | L77: 0.55 | M77: 0.55
C78: client C | D78: 0.3 | E78: 0.05 | F78: 0.1 | G78: 0.25 | H78: 0.16 | I78: 0.1 | J78: 0.1 | K78: 0.05 | L78: 0.05
C79: client D | E79: 0.05 | F79: 0.1 | G79: 0.35 | H79: 0.5 | I79: 0.35 | J79: 0.15 | K79: 0.15
C80: client E | G80: 0.18 | H80: 0.2 | I80: 0.35 | J80: 0.2 | K80: 0.2
C81: client F | G81: 0.07 | H81: 0.07 | I81: 0.2 | J81: 0.1 | K81: 0.05
D82: =SUM(D76:D81) -> 1 | E82: =SUM(E76:E81) -> 1 | F82: =SUM(F76:F81) -> 1 | G82: =SUM(G76:G81) -> 1 | H82: =SUM(H76:H81) -> 1 | I82: =SUM(I76:I81) -> 1 | J82: =SUM(J76:J81) -> 1 | K82: =SUM(K76:K81) -> 1 | ... M82: =SUM(M76:M81) -> 1
C85: Heure-Jour
D86: 8 | E86: 9 | F86: 10 | G86: 11 | H86: 12 | I86: 13 | J86: 14 | K86: 15 | L86: 16 | M86: 17
C87: Nombre de clients | D87: 2 | E87: 3 | F87: 3 | G87: 3 | H87: 5 | I87: 5 | J87: 5 | K87: 5 | L87: 2 | M87: 0
C88: client A | D88: =ROUND( D$87*D76,0) -> 1 | E88: =ROUND( E$87*E76,0) -> 2 | F88: =ROUND( F$87*F76,0) -> 2 | G88: =ROUND( G$87*G76,0) -> 0 | H88: =ROUND( H$87*H76,0) -> 0 | I88: =ROUND( I$87*I76,0) -> 0 | J88: =ROUND( J$87*J76,0) -> 1 | K88: =ROUND( K$87*K76,0) -> 1 | ... M88: =ROUND( M$87*M76,0) -> 0
C89: client B | D89: =ROUND( D$87*D77,0) -> 1 | E89: =ROUND( E$87*E77,0) -> 1 | F89: =ROUND( F$87*F77,0) -> 1 | G89: =ROUND( G$87*G77,0) -> 0 | H89: =ROUND( H$87*H77,0) -> 0 | I89: =ROUND( I$87*I77,0) -> 0 | J89: =ROUND( J$87*J77,0) -> 1 | K89: =ROUND( K$87*K77,0) -> 2 | ... M89: =ROUND( M$87*M77,0) -> 0
C90: client C | D90: =ROUND( D$87*D78,0) -> 1 | E90: =ROUND( E$87*E78,0) -> 0 | F90: =ROUND( F$87*F78,0) -> 0 | G90: =ROUND( G$87*G78,0) -> 1 | H90: =ROUND( H$87*H78,0) -> 1 | I90: =ROUND( I$87*I78,0) -> 1 | J90: =ROUND( J$87*J78,0) -> 1 | K90: =ROUND( K$87*K78,0) -> 0 | ... M90: =ROUND( M$87*M78,0) -> 0
C91: client D | D91: =ROUND( D$87*D79,0) -> 0 | E91: =ROUND( E$87*E79,0) -> 0 | F91: =ROUND( F$87*F79,0) -> 0 | G91: =ROUND( G$87*G79,0) -> 1 | H91: =ROUND( H$87*H79,0) -> 3 | I91: =ROUND( I$87*I79,0) -> 2 | J91: =ROUND( J$87*J79,0) -> 1 | K91: =ROUND( K$87*K79,0) -> 1 | ... M91: =ROUND( M$87*M79,0) -> 0
C92: client E | D92: =ROUND( D$87*D80,0) -> 0 | E92: =ROUND( E$87*E80,0) -> 0 | F92: =ROUND( F$87*F80,0) -> 0 | G92: =ROUND( G$87*G80,0) -> 1 | H92: =ROUND( H$87*H80,0) -> 1 | I92: =ROUND( I$87*I80,0) -> 2 | J92: =ROUND( J$87*J80,0) -> 1 | K92: =ROUND( K$87*K80,0) -> 1 | ... M92: =ROUND( M$87*M80,0) -> 0
C93: client F | D93: =ROUND( D$87*D81,0) -> 0 | E93: =ROUND( E$87*E81,0) -> 0 | F93: =ROUND( F$87*F81,0) -> 0 | G93: =ROUND( G$87*G81,0) -> 0 | H93: =ROUND( H$87*H81,0) -> 0 | I93: =ROUND( I$87*I81,0) -> 1 | J93: =ROUND( J$87*J81,0) -> 1 | K93: =ROUND( K$87*K81,0) -> 0 | ... M93: =ROUND( M$87*M81,0) -> 0
D94: =SUM(D88:D93) -> 3 | E94: =SUM(E88:E93) -> 3 | F94: =SUM(F88:F93) -> 3 | G94: =SUM(G88:G93) -> 3 | H94: =SUM(H88:H93) -> 5 | I94: =SUM(I88:I93) -> 6 | J94: =SUM(J88:J93) -> 6 | K94: =SUM(K88:K93) -> 5 | ... M94: =SUM(M88:M93) -> 0
C95: jour/mois | D95: mardi | E95: mercredi | F95: jeudi | G95: vendredi | H95: samedi | I95: dimanche | J95: mardi | K95: mercredi | L95: jeudi | M95: vendredi | N95: samedi | O95: dimanche | P95: mardi | Q95: mercredi | R95: jeudi | S95: vendredi | T95: samedi | U95: dimanche | V95: mardi | W95: mercredi | X95: jeudi | Y95: vendredi | Z95: samedi | AA95: dimanche
D96: 1 | E96: 2 | F96: 3 | G96: 4 | H96: 5 | I96: 6 | J96: 7 | K96: 8 | L96: 9 | M96: 10 | N96: 11 | O96: 12 | P96: 13 | Q96: 14 | R96: 15 | S96: 16 | T96: 17 | U96: 18 | V96: 19 | W96: 20 | X96: 21 | Y96: 22 | Z96: 23 | AA96: 24
C97: % remplissage journalier | D97: 0.8 | E97: 0.8 | F97: 0.7 | G97: 0.6 | H97: 0.7 | I97: 0.8 | J97: 0.8 | K97: 0.8 | L97: 0.7 | M97: 0.6 | N97: 0.7 | O97: 0.8 | P97: 0.8 | Q97: 0.8 | R97: 0.7 | S97: 0.6 | T97: 0.7 | U97: 0.8 | V97: 0.8 | W97: 0.8 | X97: 0.7 | Y97: 0.6 | Z97: 0.7 | AA97: 0.8
C98: client A | D98: =ROUND(SUM($D88:$M88)*D$97,0) -> 6 | E98: =ROUND(SUM($D88:$M88)*E$97,0) -> 6 | F98: =ROUND(SUM($D88:$M88)*F$97,0) -> 6 | G98: =ROUND(SUM($D88:$M88)*G$97,0) -> 5 | H98: =ROUND(SUM($D88:$M88)*H$97,0) -> 6 | I98: =ROUND(SUM($D88:$M88)*I$97,0) -> 6 | J98: =ROUND(SUM($D88:$M88)*J$97,0) -> 6 | K98: =ROUND(SUM($D88:$M88)*K$97,0) -> 6 | ... AA98: =ROUND(SUM($D88:$M88)*AA$97,0) -> 6
C99: client B | D99: =ROUND(SUM($D89:$M89)*D$97,0) -> 6 | E99: =ROUND(SUM($D89:$M89)*E$97,0) -> 6 | F99: =ROUND(SUM($D89:$M89)*F$97,0) -> 5 | G99: =ROUND(SUM($D89:$M89)*G$97,0) -> 4 | H99: =ROUND(SUM($D89:$M89)*H$97,0) -> 5 | I99: =ROUND(SUM($D89:$M89)*I$97,0) -> 6 | J99: =ROUND(SUM($D89:$M89)*J$97,0) -> 6 | K99: =ROUND(SUM($D89:$M89)*K$97,0) -> 6 | ... AA99: =ROUND(SUM($D89:$M89)*AA$97,0) -> 6
